Workbook
Name LEFTVARBLUE: Histogram!$B$4
Name rightVARBlue: Histogram!$B$6

Sheet INDEX
A4: WORKSHEET | H4: DESCRIPTION
A6: SUMMARY | H6: EVERYTHING IMPORTANT AT A GLANCE
A7: HISTORICAL RISK | H7: DETAILED HISTORICAL STATISTICS
A8: SIMULATED RISK | H8: DETAILED SIMULATED STATISTICS
A9: RISK BUDGETING (ETL) | H9: RISK BUDGETING ANALYSIS, BASED ON TAIL RISK
A10: RISK BUDGETING (StDev) | H10: RISK BUDGETING ANALYSIS, BASED ON TRADITIONAL RISK
A11: FACTOR CONTRIBUTION | H11: FACTOR CONTRIBUTION TO RISK; SYSTEMATIC VS. SPECIFIC FACTOR RISK
A12: EXPOSURE BY FACTOR BUCKET | H12: DETAILED EXPOSURES FROM FACTOR BUCKETS
A13: PORTFOLIO STRESS TEST | H13: SELECTED MULTI-FACTOR SCENARIO STRESS ANALYSIS
A14: STRESSED FACTOR VALUES | H14: FACTOR RETURNS UNDER THE SCENARIO STRESS ANALYSIS
A15: FACTOR ANALYSIS | H15: DETAILED RISK DRIVER ANALYSIS
A16: ASSET CORRELATIONS | H16: ASSET CLASSICAL VS ROBUST CORRELATIONS
... A19: GLOSSARY | H19: GLOSSARY OF THE USED STATISTICS
A24: CALCULATION SETTINGS | U24: Portfolio Composition
A25: PORTFOLIO | H25: ='SIMULATED RISK'!A9 -> Current 7.26
A26: PORTFOLIO VALUE | H26: 1000000
A27: NUMBER OF ASSETS | H27: 37
A28: BACKFILL | H28: No
A29: FACTOR MODEL | H29: Template General Factor Model
A30: DISTRIBUTION TYPE | H30: Asymmetric Student-t
A31: CORRELATIONS | H31: EWMA
A32: STRESS TESTS | H32: 11
A33: ANALYSIS PERIOD | H33: 07/31/2019 - 04/30/2026
A34: TIME WINDOW | H34: 81
A35: CONFIDENCE LEVEL | H35: 95
A36: RFR (Annualized) | H36: 4
A37: CURRENCY | H37: USD

Sheet Histogram
B1: HISTOGRAM (BLUE bars) | P1: RETURNS | R1: X-AXIS | T1: #SIMULATIONS per BIN | V1: #TAIL SIMULATIONS per BIN | X1: Tooltips BLUE | AB1: #TAIL SIMULATIONS per BIN
A2: Present Value (as of Evaluation Date) | B2: =INDEX!H26 -> 1000000 | P2: BLUE | T2: BLUE | V2: BLUE | X2: =UPPER($B$10 & CHAR(10) & TEXT($B$4,"0.00%")) -> VAR AT 95%, -0.29% | Y2: =UPPER($B$12 & CHAR(10) & TEXT($B$6,"0.00%")) -> VAR AT 5%, 2.06% | Z2: =UPPER($B$14 & CHAR(10) & TEXT($B$8,"0.00%")) -> MEAN, 0.94%
R3: -0.038627503 | T3: 0 | V3: =IF(OR(R3<LEFTVARBLUE,R3>rightVARBlue),IF(OR(AND(R4>=LEFTVARBLUE,R3<LEFTVARBLUE),AND(R3>=rightVARBlue,R2<rightVARBlue)),T3,T3),0) -> 0 | X3: =IF(AND(R4>=$B$4,R3<$B$4),MAX($T$3:$T$103)*1.1,NA()) -> #N/A | Y3: =IF(AND(R3>=$B$6,R2<$B$6),MAX($T$3:$T$103)*1.1,NA()) -> #N/A | Z3: =IF(AND(R3>=$B$8,R2<$B$8),MAX($T$3:$T$103)*1.1,NA()) -> #N/A | AB3: =IF(R3<LEFTVARBLUE,LEFTVARBLUE,0) -> -0.0028728808
A4: Left -tail VAR (as negative percentage) | B4: =SUMMARY!AD9/100 -> -0.0028728808 | R4: -0.037691282 | T4: 12 | V4: =IF(OR(R4<LEFTVARBLUE,R4>rightVARBlue),IF(OR(AND(R5>=LEFTVARBLUE,R4<LEFTVARBLUE),AND(R4>=rightVARBlue,R3<rightVARBlue)),T4,T4),0) -> 12 | X4: =IF(AND(R5>=$B$4,R4<$B$4),MAX($T$3:$T$103)*1.1,NA()) -> #N/A | Y4: =IF(AND(R4>=$B$6,R3<$B$6),MAX($T$3:$T$103)*1.1,NA()) -> #N/A | Z4: =IF(AND(R4>=$B$8,R3<$B$8),MAX($T$3:$T$103)*1.1,NA()) -> #N/A | AB4: =IF(R4<LEFTVARBLUE,LEFTVARBLUE,0) -> -0.0028728808
R5: -0.036755062 | T5: 6 | V5: =IF(OR(R5<LEFTVARBLUE,R5>rightVARBlue),IF(OR(AND(R6>=LEFTVARBLUE,R5<LEFTVARBLUE),AND(R5>=rightVARBlue,R4<rightVARBlue)),T5,T5),0) -> 6 | X5: =IF(AND(R6>=$B$4,R5<$B$4),MAX($T$3:$T$103)*1.1,NA()) -> #N/A | Y5: =IF(AND(R5>=$B$6,R4<$B$6),MAX($T$3:$T$103)*1.1,NA()) -> #N/A | Z5: =IF(AND(R5>=$B$8,R4<$B$8),MAX($T$3:$T$103)*1.1,NA()) -> #N/A | AB5: =IF(R5<LEFTVARBLUE,LEFTVARBLUE,0) -> -0.0028728808
A6: Right -tail VAR (as positive percentage) | B6: =SUMMARY!AF9/100 -> 0.020635408 | R6: -0.035818842 | T6: 6 | V6: =IF(OR(R6<LEFTVARBLUE,R6>rightVARBlue),IF(OR(AND(R7>=LEFTVARBLUE,R6<LEFTVARBLUE),AND(R6>=rightVARBlue,R5<rightVARBlue)),T6,T6),0) -> 6 | X6: =IF(AND(R7>=$B$4,R6<$B$4),MAX($T$3:$T$103)*1.1,NA()) -> #N/A | Y6: =IF(AND(R6>=$B$6,R5<$B$6),MAX($T$3:$T$103)*1.1,NA()) -> #N/A | Z6: =IF(AND(R6>=$B$8,R5<$B$8),MAX($T$3:$T$103)*1.1,NA()) -> #N/A | AB6: =IF(R6<LEFTVARBLUE,LEFTVARBLUE,0) -> -0.0028728808
R7: -0.034882621 | T7: 7 | V7: =IF(OR(R7<LEFTVARBLUE,R7>rightVARBlue),IF(OR(AND(R8>=LEFTVARBLUE,R7<LEFTVARBLUE),AND(R7>=rightVARBlue,R6<rightVARBlue)),T7,T7),0) -> 7 | X7: =IF(AND(R8>=$B$4,R7<$B$4),MAX($T$3:$T$103)*1.1,NA()) -> #N/A | Y7: =IF(AND(R7>=$B$6,R6<$B$6),MAX($T$3:$T$103)*1.1,NA()) -> #N/A | Z7: =IF(AND(R7>=$B$8,R6<$B$8),MAX($T$3:$T$103)*1.1,NA()) -> #N/A | AB7: =IF(R7<LEFTVARBLUE,LEFTVARBLUE,0) -> -0.0028728808
A8: Mean (as positive percentage) | B8: =SUMMARY!W9/100 -> 0.009376494 | R8: -0.033946401 | T8: 10 | V8: =IF(OR(R8<LEFTVARBLUE,R8>rightVARBlue),IF(OR(AND(R9>=LEFTVARBLUE,R8<LEFTVARBLUE),AND(R8>=rightVARBlue,R7<rightVARBlue)),T8,T8),0) -> 10 | X8: =IF(AND(R9>=$B$4,R8<$B$4),MAX($T$3:$T$103)*1.1,NA()) -> #N/A | Y8: =IF(AND(R8>=$B$6,R7<$B$6),MAX($T$3:$T$103)*1.1,NA()) -> #N/A | Z8: =IF(AND(R8>=$B$8,R7<$B$8),MAX($T$3:$T$103)*1.1,NA()) -> #N/A | AB8: =IF(R8<LEFTVARBLUE,LEFTVARBLUE,0) -> -0.0028728808
R9: -0.03301018 | T9: 16 | V9: =IF(OR(R9<LEFTVARBLUE,R9>rightVARBlue),IF(OR(AND(R10>=LEFTVARBLUE,R9<LEFTVARBLUE),AND(R9>=rightVARBlue,R8<rightVARBlue)),T9,T9),0) -> 16 | X9: =IF(AND(R10>=$B$4,R9<$B$4),MAX($T$3:$T$103)*1.1,NA()) -> #N/A | Y9: =IF(AND(R9>=$B$6,R8<$B$6),MAX($T$3:$T$103)*1.1,NA()) -> #N/A | Z9: =IF(AND(R9>=$B$8,R8<$B$8),MAX($T$3:$T$103)*1.1,NA()) -> #N/A | AB9: =IF(R9<LEFTVARBLUE,LEFTVARBLUE,0) -> -0.0028728808
A10: Tooltip Name for left-tail VAR | B10: VAR at 95%, | R10: -0.03207396 | T10: 15 | V10: =IF(OR(R10<LEFTVARBLUE,R10>rightVARBlue),IF(OR(AND(R11>=LEFTVARBLUE,R10<LEFTVARBLUE),AND(R10>=rightVARBlue,R9<rightVARBlue)),T10,T10),0) -> 15 | X10: =IF(AND(R11>=$B$4,R10<$B$4),MAX($T$3:$T$103)*1.1,NA()) -> #N/A | Y10: =IF(AND(R10>=$B$6,R9<$B$6),MAX($T$3:$T$103)*1.1,NA()) -> #N/A | Z10: =IF(AND(R10>=$B$8,R9<$B$8),MAX($T$3:$T$103)*1.1,NA()) -> #N/A | AB10: =IF(R10<LEFTVARBLUE,LEFTVARBLUE,0) -> -0.0028728808
R11: -0.03113774 | T11: 17 | V11: =IF(OR(R11<LEFTVARBLUE,R11>rightVARBlue),IF(OR(AND(R12>=LEFTVARBLUE,R11<LEFTVARBLUE),AND(R11>=rightVARBlue,R10<rightVARBlue)),T11,T11),0) -> 17 | X11: =IF(AND(R12>=$B$4,R11<$B$4),MAX($T$3:$T$103)*1.1,NA()) -> #N/A | Y11: =IF(AND(R11>=$B$6,R10<$B$6),MAX($T$3:$T$103)*1.1,NA()) -> #N/A | Z11: =IF(AND(R11>=$B$8,R10<$B$8),MAX($T$3:$T$103)*1.1,NA()) -> #N/A | AB11: =IF(R11<LEFTVARBLUE,LEFTVARBLUE,0) -> -0.0028728808
A12: Tooltip Name for right-tail VAR | B12: VAR at 5%, | R12: -0.030201519 | T12: 20 | V12: =IF(OR(R12<LEFTVARBLUE,R12>rightVARBlue),IF(OR(AND(R13>=LEFTVARBLUE,R12<LEFTVARBLUE),AND(R12>=rightVARBlue,R11<rightVARBlue)),T12,T12),0) -> 20 | X12: =IF(AND(R13>=$B$4,R12<$B$4),MAX($T$3:$T$103)*1.1,NA()) -> #N/A | Y12: =IF(AND(R12>=$B$6,R11<$B$6),MAX($T$3:$T$103)*1.1,NA()) -> #N/A | Z12: =IF(AND(R12>=$B$8,R11<$B$8),MAX($T$3:$T$103)*1.1,NA()) -> #N/A | AB12: =IF(R12<LEFTVARBLUE,LEFTVARBLUE,0) -> -0.0028728808
R13: -0.029265299 | T13: 25 | V13: =IF(OR(R13<LEFTVARBLUE,R13>rightVARBlue),IF(OR(AND(R14>=LEFTVARBLUE,R13<LEFTVARBLUE),AND(R13>=rightVARBlue,R12<rightVARBlue)),T13,T13),0) -> 25 | X13: =IF(AND(R14>=$B$4,R13<$B$4),MAX($T$3:$T$103)*1.1,NA()) -> #N/A | Y13: =IF(AND(R13>=$B$6,R12<$B$6),MAX($T$3:$T$103)*1.1,NA()) -> #N/A | Z13: =IF(AND(R13>=$B$8,R12<$B$8),MAX($T$3:$T$103)*1.1,NA()) -> #N/A | AB13: =IF(R13<LEFTVARBLUE,LEFTVARBLUE,0) -> -0.0028728808
A14: Tooltip Name for right-tail VAR | B14: Mean, | R14: -0.028329078 | T14: 21 | V14: =IF(OR(R14<LEFTVARBLUE,R14>rightVARBlue),IF(OR(AND(R15>=LEFTVARBLUE,R14<LEFTVARBLUE),AND(R14>=rightVARBlue,R13<rightVARBlue)),T14,T14),0) -> 21 | X14: =IF(AND(R15>=$B$4,R14<$B$4),MAX($T$3:$T$103)*1.1,NA()) -> #N/A | Y14: =IF(AND(R14>=$B$6,R13<$B$6),MAX($T$3:$T$103)*1.1,NA()) -> #N/A | Z14: =IF(AND(R14>=$B$8,R13<$B$8),MAX($T$3:$T$103)*1.1,NA()) -> #N/A | AB14: =IF(R14<LEFTVARBLUE,LEFTVARBLUE,0) -> -0.0028728808
R15: -0.027392858 | T15: 18 | V15: =IF(OR(R15<LEFTVARBLUE,R15>rightVARBlue),IF(OR(AND(R16>=LEFTVARBLUE,R15<LEFTVARBLUE),AND(R15>=rightVARBlue,R14<rightVARBlue)),T15,T15),0) -> 18 | X15: =IF(AND(R16>=$B$4,R15<$B$4),MAX($T$3:$T$103)*1.1,NA()) -> #N/A | Y15: =IF(AND(R15>=$B$6,R14<$B$6),MAX($T$3:$T$103)*1.1,NA()) -> #N/A | Z15: =IF(AND(R15>=$B$8,R14<$B$8),MAX($T$3:$T$103)*1.1,NA()) -> #N/A | AB15: =IF(R15<LEFTVARBLUE,LEFTVARBLUE,0) -> -0.0028728808
R16: -0.026456638 | T16: 22 | V16: =IF(OR(R16<LEFTVARBLUE,R16>rightVARBlue),IF(OR(AND(R17>=LEFTVARBLUE,R16<LEFTVARBLUE),AND(R16>=rightVARBlue,R15<rightVARBlue)),T16,T16),0) -> 22 | X16: =IF(AND(R17>=$B$4,R16<$B$4),MAX($T$3:$T$103)*1.1,NA()) -> #N/A | Y16: =IF(AND(R16>=$B$6,R15<$B$6),MAX($T$3:$T$103)*1.1,NA()) -> #N/A | Z16: =IF(AND(R16>=$B$8,R15<$B$8),MAX($T$3:$T$103)*1.1,NA()) -> #N/A | AB16: =IF(R16<LEFTVARBLUE,LEFTVARBLUE,0) -> -0.0028728808
A17: Simulations | R17: -0.025520417 | T17: 28 | V17: =IF(OR(R17<LEFTVARBLUE,R17>rightVARBlue),IF(OR(AND(R18>=LEFTVARBLUE,R17<LEFTVARBLUE),AND(R17>=rightVARBlue,R16<rightVARBlue)),T17,T17),0) -> 28 | X17: =IF(AND(R18>=$B$4,R17<$B$4),MAX($T$3:$T$103)*1.1,NA()) -> #N/A | Y17: =IF(AND(R17>=$B$6,R16<$B$6),MAX($T$3:$T$103)*1.1,NA()) -> #N/A | Z17: =IF(AND(R17>=$B$8,R16<$B$8),MAX($T$3:$T$103)*1.1,NA()) -> #N/A | AB17: =IF(R17<LEFTVARBLUE,LEFTVARBLUE,0) -> -0.0028728808
R18: -0.024584197 | T18: 31 | V18: =IF(OR(R18<LEFTVARBLUE,R18>rightVARBlue),IF(OR(AND(R19>=LEFTVARBLUE,R18<LEFTVARBLUE),AND(R18>=rightVARBlue,R17<rightVARBlue)),T18,T18),0) -> 31 | X18: =IF(AND(R19>=$B$4,R18<$B$4),MAX($T$3:$T$103)*1.1,NA()) -> #N/A | Y18: =IF(AND(R18>=$B$6,R17<$B$6),MAX($T$3:$T$103)*1.1,NA()) -> #N/A | Z18: =IF(AND(R18>=$B$8,R17<$B$8),MAX($T$3:$T$103)*1.1,NA()) -> #N/A | AB18: =IF(R18<LEFTVARBLUE,LEFTVARBLUE,0) -> -0.0028728808
R19: -0.023647977 | T19: 22 | V19: =IF(OR(R19<LEFTVARBLUE,R19>rightVARBlue),IF(OR(AND(R20>=LEFTVARBLUE,R19<LEFTVARBLUE),AND(R19>=rightVARBlue,R18<rightVARBlue)),T19,T19),0) -> 22 | X19: =IF(AND(R20>=$B$4,R19<$B$4),MAX($T$3:$T$103)*1.1,NA()) -> #N/A | Y19: =IF(AND(R19>=$B$6,R18<$B$6),MAX($T$3:$T$103)*1.1,NA()) -> #N/A | Z19: =IF(AND(R19>=$B$8,R18<$B$8),MAX($T$3:$T$103)*1.1,NA()) -> #N/A | AB19: =IF(R19<LEFTVARBLUE,LEFTVARBLUE,0) -> -0.0028728808
R20: -0.022711756 | T20: 44 | V20: =IF(OR(R20<LEFTVARBLUE,R20>rightVARBlue),IF(OR(AND(R21>=LEFTVARBLUE,R20<LEFTVARBLUE),AND(R20>=rightVARBlue,R19<rightVARBlue)),T20,T20),0) -> 44 | X20: =IF(AND(R21>=$B$4,R20<$B$4),MAX($T$3:$T$103)*1.1,NA()) -> #N/A | Y20: =IF(AND(R20>=$B$6,R19<$B$6),MAX($T$3:$T$103)*1.1,NA()) -> #N/A | Z20: =IF(AND(R20>=$B$8,R19<$B$8),MAX($T$3:$T$103)*1.1,NA()) -> #N/A | AB20: =IF(R20<LEFTVARBLUE,LEFTVARBLUE,0) -> -0.0028728808
R21: -0.021775536 | T21: 45 | V21: =IF(OR(R21<LEFTVARBLUE,R21>rightVARBlue),IF(OR(AND(R22>=LEFTVARBLUE,R21<LEFTVARBLUE),AND(R21>=rightVARBlue,R20<rightVARBlue)),T21,T21),0) -> 45 | X21: =IF(AND(R22>=$B$4,R21<$B$4),MAX($T$3:$T$103)*1.1,NA()) -> #N/A | Y21: =IF(AND(R21>=$B$6,R20<$B$6),MAX($T$3:$T$103)*1.1,NA()) -> #N/A | Z21: =IF(AND(R21>=$B$8,R20<$B$8),MAX($T$3:$T$103)*1.1,NA()) -> #N/A | AB21: =IF(R21<LEFTVARBLUE,LEFTVARBLUE,0) -> -0.0028728808
R22: -0.020839315 | T22: 45 | V22: =IF(OR(R22<LEFTVARBLUE,R22>rightVARBlue),IF(OR(AND(R23>=LEFTVARBLUE,R22<LEFTVARBLUE),AND(R22>=rightVARBlue,R21<rightVARBlue)),T22,T22),0) -> 45 | X22: =IF(AND(R23>=$B$4,R22<$B$4),MAX($T$3:$T$103)*1.1,NA()) -> #N/A | Y22: =IF(AND(R22>=$B$6,R21<$B$6),MAX($T$3:$T$103)*1.1,NA()) -> #N/A | Z22: =IF(AND(R22>=$B$8,R21<$B$8),MAX($T$3:$T$103)*1.1,NA()) -> #N/A | AB22: =IF(R22<LEFTVARBLUE,LEFTVARBLUE,0) -> -0.0028728808
R23: -0.019903095 | T23: 60 | V23: =IF(OR(R23<LEFTVARBLUE,R23>rightVARBlue),IF(OR(AND(R24>=LEFTVARBLUE,R23<LEFTVARBLUE),AND(R23>=rightVARBlue,R22<rightVARBlue)),T23,T23),0) -> 60 | X23: =IF(AND(R24>=$B$4,R23<$B$4),MAX($T$3:$T$103)*1.1,NA()) -> #N/A | Y23: =IF(AND(R23>=$B$6,R22<$B$6),MAX($T$3:$T$103)*1.1,NA()) -> #N/A | Z23: =IF(AND(R23>=$B$8,R22<$B$8),MAX($T$3:$T$103)*1.1,NA()) -> #N/A | AB23: =IF(R23<LEFTVARBLUE,LEFTVARBLUE,0) -> -0.0028728808
R24: -0.018966875 | T24: 62 | V24: =IF(OR(R24<LEFTVARBLUE,R24>rightVARBlue),IF(OR(AND(R25>=LEFTVARBLUE,R24<LEFTVARBLUE),AND(R24>=rightVARBlue,R23<rightVARBlue)),T24,T24),0) -> 62 | X24: =IF(AND(R25>=$B$4,R24<$B$4),MAX($T$3:$T$103)*1.1,NA()) -> #N/A | Y24: =IF(AND(R24>=$B$6,R23<$B$6),MAX($T$3:$T$103)*1.1,NA()) -> #N/A | Z24: =IF(AND(R24>=$B$8,R23<$B$8),MAX($T$3:$T$103)*1.1,NA()) -> #N/A | AB24: =IF(R24<LEFTVARBLUE,LEFTVARBLUE,0) -> -0.0028728808
R25: -0.018030654 | T25: 70 | V25: =IF(OR(R25<LEFTVARBLUE,R25>rightVARBlue),IF(OR(AND(R26>=LEFTVARBLUE,R25<LEFTVARBLUE),AND(R25>=rightVARBlue,R24<rightVARBlue)),T25,T25),0) -> 70 | X25: =IF(AND(R26>=$B$4,R25<$B$4),MAX($T$3:$T$103)*1.1,NA()) -> #N/A | Y25: =IF(AND(R25>=$B$6,R24<$B$6),MAX($T$3:$T$103)*1.1,NA()) -> #N/A | Z25: =IF(AND(R25>=$B$8,R24<$B$8),MAX($T$3:$T$103)*1.1,NA()) -> #N/A | AB25: =IF(R25<LEFTVARBLUE,LEFTVARBLUE,0) -> -0.0028728808
R26: -0.017094434 | T26: 67 | V26: =IF(OR(R26<LEFTVARBLUE,R26>rightVARBlue),IF(OR(AND(R27>=LEFTVARBLUE,R26<LEFTVARBLUE),AND(R26>=rightVARBlue,R25<rightVARBlue)),T26,T26),0) -> 67 | X26: =IF(AND(R27>=$B$4,R26<$B$4),MAX($T$3:$T$103)*1.1,NA()) -> #N/A | Y26: =IF(AND(R26>=$B$6,R25<$B$6),MAX($T$3:$T$103)*1.1,NA()) -> #N/A | Z26: =IF(AND(R26>=$B$8,R25<$B$8),MAX($T$3:$T$103)*1.1,NA()) -> #N/A | AB26: =IF(R26<LEFTVARBLUE,LEFTVARBLUE,0) -> -0.0028728808
R27: -0.016158214 | T27: 103 | V27: =IF(OR(R27<LEFTVARBLUE,R27>rightVARBlue),IF(OR(AND(R28>=LEFTVARBLUE,R27<LEFTVARBLUE),AND(R27>=rightVARBlue,R26<rightVARBlue)),T27,T27),0) -> 103 | X27: =IF(AND(R28>=$B$4,R27<$B$4),MAX($T$3:$T$103)*1.1,NA()) -> #N/A | Y27: =IF(AND(R27>=$B$6,R26<$B$6),MAX($T$3:$T$103)*1.1,NA()) -> #N/A | Z27: =IF(AND(R27>=$B$8,R26<$B$8),MAX($T$3:$T$103)*1.1,NA()) -> #N/A | AB27: =IF(R27<LEFTVARBLUE,LEFTVARBLUE,0) -> -0.0028728808
R28: -0.015221993 | T28: 96 | V28: =IF(OR(R28<LEFTVARBLUE,R28>rightVARBlue),IF(OR(AND(R29>=LEFTVARBLUE,R28<LEFTVARBLUE),AND(R28>=rightVARBlue,R27<rightVARBlue)),T28,T28),0) -> 96 | X28: =IF(AND(R29>=$B$4,R28<$B$4),MAX($T$3:$T$103)*1.1,NA()) -> #N/A | Y28: =IF(AND(R28>=$B$6,R27<$B$6),MAX($T$3:$T$103)*1.1,NA()) -> #N/A | Z28: =IF(AND(R28>=$B$8,R27<$B$8),MAX($T$3:$T$103)*1.1,NA()) -> #N/A | AB28: =IF(R28<LEFTVARBLUE,LEFTVARBLUE,0) -> -0.0028728808
R29: -0.014285773 | T29: 141 | V29: =IF(OR(R29<LEFTVARBLUE,R29>rightVARBlue),IF(OR(AND(R30>=LEFTVARBLUE,R29<LEFTVARBLUE),AND(R29>=rightVARBlue,R28<rightVARBlue)),T29,T29),0) -> 141 | X29: =IF(AND(R30>=$B$4,R29<$B$4),MAX($T$3:$T$103)*1.1,NA()) -> #N/A | Y29: =IF(AND(R29>=$B$6,R28<$B$6),MAX($T$3:$T$103)*1.1,NA()) -> #N/A | Z29: =IF(AND(R29>=$B$8,R28<$B$8),MAX($T$3:$T$103)*1.1,NA()) -> #N/A | AB29: =IF(R29<LEFTVARBLUE,LEFTVARBLUE,0) -> -0.0028728808
... R103: 0.054994535 | T103: 1 | V103: =IF(OR(R103<LEFTVARBLUE,R103>rightVARBlue),IF(OR(AND(R104>=LEFTVARBLUE,R103<LEFTVARBLUE),AND(R103>=rightVARBlue,R102<rightVARBlue)),T103,T103),0) -> 1 | X103: =IF(AND(R104>=$B$4,R103<$B$4),MAX($T$3:$T$103)*1.1,NA()) -> #N/A | Y103: =IF(AND(R103>=$B$6,R102<$B$6),MAX($T$3:$T$103)*1.1,NA()) -> #N/A | Z103: =IF(AND(R103>=$B$8,R102<$B$8),MAX($T$3:$T$103)*1.1,NA()) -> #N/A | AB103: =IF(R103<LEFTVARBLUE,LEFTVARBLUE,0) -> 0

Sheet SUMMARY
A4: PORTFOLIO RISK SNAPSHOT
A6: SIMULATIONS DISTRIBUTION CHART | S6: SIMULATED PORTFOLIO RISK STATISTICS
S7: TRADITIONAL | AB7: TAIL MEASURES
S8: StDev | U8: Ann. StDev | W8: Mean | Y8: Ann. Mean | AB8: ETL 95 | AD8: VaR 95 | AF8: VaR 5 | AH8: ETR 95
S9: =IF(ISBLANK(SUMMARY_DATA!B16)=TRUE,"",SUMMARY_DATA!B16) -> 0.75095534 | U9: =IF(ISBLANK(SUMMARY_DATA!C16)=TRUE,"",SUMMARY_DATA!C16) -> 2.6013856 | W9: =IF(ISBLANK(SUMMARY_DATA!D16)=TRUE,"",SUMMARY_DATA!D16) -> 0.9376494 | Y9: =IF(ISBLANK(SUMMARY_DATA!E16)=TRUE,"",SUMMARY_DATA!E16) -> 11.251793 | AB9: =IF(ISBLANK(SUMMARY_DATA!F16)=TRUE,"",SUMMARY_DATA!F16) -> 0.87394068 | AD9: =IF(ISBLANK(SUMMARY_DATA!G16)=TRUE,"",SUMMARY_DATA!G16*(-1)) -> -0.28728808 | AF9: =IF(ISBLANK(SUMMARY_DATA!H16)=TRUE,"",SUMMARY_DATA!H16*(-1)) -> 2.0635408 | AH9: =IF(ISBLANK(SUMMARY_DATA!I16)=TRUE,"",SUMMARY_DATA!I16) -> 2.4409617
S11: TOP 10 FACTORS BY SYSTEMATIC RISK (STDEV) | AB11: TOP 10 FACTORS BY SYSTEMATIC RISK (ETL)
W12: Factor PC to StDev | Y12: Factor MC to StDev | AF12: Factor PC to ETL | AH12: Factor MC to ETL
S13: TOTAL SYSTEMATIC RISK | W13: =SUMMARY_DATA!B23 -> 47.149713 | AB13: TOTAL SYSTEMATIC RISK | AF13: =SUMMARY_DATA!B26 -> 115.77315
S14: ML Global High Yield - AAA Spread USD | W14: 40.774773 | Y14: 1.5212307 | AB14: ML Global High Yield - AAA Spread USD | AF14: 101.54616 | AH14: 4.408947
S15: MSCI Small Minus Large World USD | W15: 4.6628847 | Y15: 0.92771053 | AB15: MSCI Small Minus Large World USD | AF15: 12.4419 | AH15: 2.8807951
S16: MSCI The World USD | W16: 3.2915027 | Y16: 1.6779847 | AB16: MSCI The World USD | AF16: 6.8117282 | AH16: 4.0412801
S17: ML Global Govt Bond II USD | W17: 1.9769688 | Y17: -0.3459997 | AB17: ML Global Govt Bond II USD | AF17: 2.3484622 | AH17: -0.47832969
S18: CBOE Volatility Index as Difference USD | W18: 0.80402133 | Y18: -1.244496 | AB18: CBOE Volatility Index as Difference USD | AF18: 1.6721821 | AH18: -3.0121552
S19: US Treasury 10Yr - 2Yr Spread USD | W19: 0.061423329 | Y19: 0.64135966 | AB19: US Treasury 10Yr - 2Yr Spread USD | AF19: 0.12630521 | AH19: 1.5348198
S20: MSCI Value Minus Growth World USD | W20: -0.18859047 | Y20: 0.10299873 | AB20: MSCI Value Minus Growth World USD | AF20: -0.17970689 | AH20: 0.11422066
S21: Trade Weighted Exchange Index: Broad | W21: -0.20667012 | Y21: -0.35462328 | AB21: Trade Weighted Exchange Index: Broad | AF21: -0.5659147 | AH21: -1.1300779
S22: S&P GSCI Index | W22: -4.0265997 | Y22: 2.5408459 | AB22: S&P GSCI Index | AF22: -8.4279646 | AH22: 6.1891416
S24: SPECIFIC RISK | W24: =100-W13 -> 52.850287 | AB24: SPECIFIC RISK | AF24: =100-AF13 -> -15.773153
A27: STRESS TEST SNAPSHOT
A29: TOP LOSER BY STRESS SCENARIO | I29: SCENARIOS BY PORTFOLIO IMPACT
F30: Asset Return | O30: Portfolio Return
A31: =IF(F31="","",INDEX(SCENARIOS_ORDERED_BY_PF_VALUE!A:A,MATCH(F31,SCENARIOS_ORDERED_BY_PF_VALUE!D:D,0))) -> Silver Point Capital: Silver Point Distressed Opportunity Institutional Partners + Silver Point HF | F31: =IF(ISBLANK(SCENARIOS_ORDERED_BY_PF_VALUE!D1)=TRUE,"",MIN(SCENARIOS_ORDERED_BY_PF_VALUE!D2:'SCENARIOS_ORDERED_BY_PF_VALUE'!D100)) -> -42.289325 | I31: =IF('PORTFOLIO STRESS TEST'!O13="%scenario", "", 'PORTFOLIO STRESS TEST'!O13) -> 2008 Lehman Blow-Up | O31: =IF('PORTFOLIO STRESS TEST'!O13="%scenario", "", 'PORTFOLIO STRESS TEST'!O14) -> -3.5256818
A32: =IF(F32="","",INDEX(SCENARIOS_ORDERED_BY_PF_VALUE!A:A,MATCH(F32,SCENARIOS_ORDERED_BY_PF_VALUE!E:E,0))) -> PIMCO: PIMCO Commodity Alpha Fund | F32: =IF(ISBLANK(SCENARIOS_ORDERED_BY_PF_VALUE!E1)=TRUE,"",MIN(SCENARIOS_ORDERED_BY_PF_VALUE!E2:'SCENARIOS_ORDERED_BY_PF_VALUE'!E100)) -> -26.684504 | I32: =IF('PORTFOLIO STRESS TEST'!Q13="%scenario", "", 'PORTFOLIO STRESS TEST'!Q13) -> 2002 Market Downturn | O32: =IF('PORTFOLIO STRESS TEST'!Q13="%scenario", "", 'PORTFOLIO STRESS TEST'!Q14) -> -1.7508844
A33: =IF(F33="","",INDEX(SCENARIOS_ORDERED_BY_PF_VALUE!A:A,MATCH(F33,SCENARIOS_ORDERED_BY_PF_VALUE!F:F,0))) -> Silver Point Capital: Silver Point Distressed Opportunity Institutional Partners + Silver Point HF | F33: =IF(ISBLANK(SCENARIOS_ORDERED_BY_PF_VALUE!F1)=TRUE,"",MIN(SCENARIOS_ORDERED_BY_PF_VALUE!F2:'SCENARIOS_ORDERED_BY_PF_VALUE'!F100)) -> -11.380305 | I33: =IF('PORTFOLIO STRESS TEST'!S13="%scenario", "", 'PORTFOLIO STRESS TEST'!S13) -> 2001 WTC Attack | O33: =IF('PORTFOLIO STRESS TEST'!S13="%scenario", "", 'PORTFOLIO STRESS TEST'!S14) -> -1.1625695
A34: =IF(F34="","",INDEX(SCENARIOS_ORDERED_BY_PF_VALUE!A:A,MATCH(F34,SCENARIOS_ORDERED_BY_PF_VALUE!G:G,0))) -> Silver Point Capital: Silver Point Distressed Opportunity Institutional Partners + Silver Point HF | F34: =IF(ISBLANK(SCENARIOS_ORDERED_BY_PF_VALUE!G1)=TRUE,"",MIN(SCENARIOS_ORDERED_BY_PF_VALUE!G2:'SCENARIOS_ORDERED_BY_PF_VALUE'!G100)) -> -28.416508 | I34: =IF('PORTFOLIO STRESS TEST'!U13="%scenario", "", 'PORTFOLIO STRESS TEST'!U13) -> 1987 Black Monday | O34: =IF('PORTFOLIO STRESS TEST'!U13="%scenario", "", 'PORTFOLIO STRESS TEST'!U14) -> -0.6952119
A35: =IF(F35="","",INDEX(SCENARIOS_ORDERED_BY_PF_VALUE!A:A,MATCH(F35,SCENARIOS_ORDERED_BY_PF_VALUE!H:H,0))) -> PIMCO: PIMCO Commodity Alpha Fund | F35: =IF(ISBLANK(SCENARIOS_ORDERED_BY_PF_VALUE!H1)=TRUE,"",MIN(SCENARIOS_ORDERED_BY_PF_VALUE!H2:'SCENARIOS_ORDERED_BY_PF_VALUE'!H100)) -> -7.5970198 | I35: =IF('PORTFOLIO STRESS TEST'!W13="%scenario", "", 'PORTFOLIO STRESS TEST'!W13) -> 1998 Russian Crisis | O35: =IF('PORTFOLIO STRESS TEST'!W13="%scenario", "", 'PORTFOLIO STRESS TEST'!W14) -> -0.68043189
A36: =IF(F36="","",INDEX(SCENARIOS_ORDERED_BY_PF_VALUE!A:A,MATCH(F36,SCENARIOS_ORDERED_BY_PF_VALUE!I:I,0))) -> PIMCO: PIMCO Commodity Alpha Fund | F36: =IF(ISBLANK(SCENARIOS_ORDERED_BY_PF_VALUE!I1)=TRUE,"",MIN(SCENARIOS_ORDERED_BY_PF_VALUE!I2:'SCENARIOS_ORDERED_BY_PF_VALUE'!I100)) -> -7.5670559 | I36: =IF('PORTFOLIO STRESS TEST'!Y13="%scenario", "", 'PORTFOLIO STRESS TEST'!Y13) -> 2008 January Crisis | O36: =IF('PORTFOLIO STRESS TEST'!Y13="%scenario", "", 'PORTFOLIO STRESS TEST'!Y14) -> -0.30050481
A37: =IF(F37="","",INDEX(SCENARIOS_ORDERED_BY_PF_VALUE!A:A,MATCH(F37,SCENARIOS_ORDERED_BY_PF_VALUE!J:J,0))) -> Saba: CEF1 MN - 2.75x | F37: =IF(ISBLANK(SCENARIOS_ORDERED_BY_PF_VALUE!J1)=TRUE,"",MIN(SCENARIOS_ORDERED_BY_PF_VALUE!J2:'SCENARIOS_ORDERED_BY_PF_VALUE'!J100)) -> -3.8341475 | I37: =IF('PORTFOLIO STRESS TEST'!AA13="%scenario", "", 'PORTFOLIO STRESS TEST'!AA13) -> 2007 August Crisis | O37: =IF('PORTFOLIO STRESS TEST'!AA13="%scenario", "", 'PORTFOLIO STRESS TEST'!AA14) -> -0.024435815
A38: =IF(F38="","",INDEX(SCENARIOS_ORDERED_BY_PF_VALUE!A:A,MATCH(F38,SCENARIOS_ORDERED_BY_PF_VALUE!K:K,0))) -> Silver Point Capital: Silver Point Distressed Opportunity Institutional Partners + Silver Point HF | F38: =IF(ISBLANK(SCENARIOS_ORDERED_BY_PF_VALUE!K1)=TRUE,"",MIN(SCENARIOS_ORDERED_BY_PF_VALUE!K2:'SCENARIOS_ORDERED_BY_PF_VALUE'!K100)) -> -8.6402481 | I38: =IF('PORTFOLIO STRESS TEST'!AC13="%scenario", "", 'PORTFOLIO STRESS TEST'!AC13) -> 2001 Nasdaq | O38: =IF('PORTFOLIO STRESS TEST'!AC13="%scenario", "", 'PORTFOLIO STRESS TEST'!AC14) -> 0.072055902
A39: =IF(F39="","",INDEX(SCENARIOS_ORDERED_BY_PF_VALUE!A:A,MATCH(F39,SCENARIOS_ORDERED_BY_PF_VALUE!L:L,0))) -> PIMCO: PIMCO Commodity Alpha Fund | F39: =IF(ISBLANK(SCENARIOS_ORDERED_BY_PF_VALUE!L1)=TRUE,"",MIN(SCENARIOS_ORDERED_BY_PF_VALUE!L2:'SCENARIOS_ORDERED_BY_PF_VALUE'!L100)) -> -2.779568 | I39: =IF('PORTFOLIO STRESS TEST'!AE13="%scenario", "", 'PORTFOLIO STRESS TEST'!AE13) -> 1997 - 1998 Asian Crisis | O39: =IF('PORTFOLIO STRESS TEST'!AE13="%scenario", "", 'PORTFOLIO STRESS TEST'!AE14) -> 0.1020368
A40: =IF(F40="","",INDEX(SCENARIOS_ORDERED_BY_PF_VALUE!A:A,MATCH(F40,SCENARIOS_ORDERED_BY_PF_VALUE!M:M,0))) -> Rokos Global Macro Fund LP: Rokos Global Macro Fund LP | F40: =IF(ISBLANK(SCENARIOS_ORDERED_BY_PF_VALUE!M1)=TRUE,"",MIN(SCENARIOS_ORDERED_BY_PF_VALUE!M2:'SCENARIOS_ORDERED_BY_PF_VALUE'!M100)) -> -7.6864085 | I40: =IF('PORTFOLIO STRESS TEST'!AG13="%scenario", "", 'PORTFOLIO STRESS TEST'!AG13) -> 1990 Kuwait Invasion | O40: =IF('PORTFOLIO STRESS TEST'!AG13="%scenario", "", 'PORTFOLIO STRESS TEST'!AG14) -> 0.29266168
A41: =IF(F41="","",INDEX(SCENARIOS_ORDERED_BY_PF_VALUE!A:A,MATCH(F41,SCENARIOS_ORDERED_BY_PF_VALUE!N:N,0))) -> Silver Point Capital: Silver Point Distressed Opportunity Institutional Partners + Silver Point HF | F41: =IF(ISBLANK(SCENARIOS_ORDERED_BY_PF_VALUE!N1)=TRUE,"",MIN(SCENARIOS_ORDERED_BY_PF_VALUE!N2:'SCENARIOS_ORDERED_BY_PF_VALUE'!N100)) -> -2.802416 | I41: =IF('PORTFOLIO STRESS TEST'!AI13="%scenario", "", 'PORTFOLIO STRESS TEST'!AI13) -> 2005 Katrina | O41: =IF('PORTFOLIO STRESS TEST'!AI13="%scenario", "", 'PORTFOLIO STRESS TEST'!AI14) -> 1.1043836
A45: PORTFOLIO RISK CONTRIBUTION SNAPSHOT
A47: TOP 5 CONTRIBUTORS BY MARGINAL CONTRIBUTION TO ETL | N47: PERCENTAGE CONTRIBUTION (%) | AA47: MARGINAL CONTRIBUTION (bps)
J48: Weight | N48: PC to ETL • | P48: PC to ETR • | R48: PC to StDev | T48: PC to Return | AA48: MC to ETL • | AC48: MC to ETR • | AE48: MC to StDev
A49: =IF(ISBLANK(SUMMARY_DATA!A2)=TRUE,"",SUMMARY_DATA!A2) -> Silver Point Capital: Silver Point Distressed Opportunity Institutional Partners + Silver Point HF | J49: =IF(ISBLANK(SUMMARY_DATA!B2)=TRUE,"",SUMMARY_DATA!B2) -> 0.77463136 | N49: =IF(ISBLANK(SUMMARY_DATA!C2)=TRUE,"",SUMMARY_DATA!C2) -> 7.5420822 | P49: =IF(ISBLANK(SUMMARY_DATA!D2)=TRUE,"",SUMMARY_DATA!D2) -> 2.0514522 | R49: =IF(ISBLANK(SUMMARY_DATA!E2)=TRUE,"",SUMMARY_DATA!E2) -> 3.4079492 | T49: =IF(ISBLANK(SUMMARY_DATA!F2)=TRUE,"",SUMMARY_DATA!F2) -> 0.96608254 | AA49: =IF(ISBLANK(SUMMARY_DATA!G2)=TRUE,"",SUMMARY_DATA!G2) -> 8.5089926 | AC49: =IF(ISBLANK(SUMMARY_DATA!H2)=TRUE,"",SUMMARY_DATA!H2) -> 6.464386 | AE49: =IF(ISBLANK(SUMMARY_DATA!I2)=TRUE,"",SUMMARY_DATA!I2) -> 3.3037878
A50: =IF(ISBLANK(SUMMARY_DATA!A3)=TRUE,"",SUMMARY_DATA!A3) -> LibreMax Partners LP: LibreMax Partners LP | J50: =IF(ISBLANK(SUMMARY_DATA!B3)=TRUE,"",SUMMARY_DATA!B3) -> 2.4519223 | N50: =IF(ISBLANK(SUMMARY_DATA!C3)=TRUE,"",SUMMARY_DATA!C3) -> 12.799681 | P50: =IF(ISBLANK(SUMMARY_DATA!D3)=TRUE,"",SUMMARY_DATA!D3) -> 3.1550345 | R50: =IF(ISBLANK(SUMMARY_DATA!E3)=TRUE,"",SUMMARY_DATA!E3) -> 5.7525972 | T50: =IF(ISBLANK(SUMMARY_DATA!F3)=TRUE,"",SUMMARY_DATA!F3) -> 1.3572666 | AA50: =IF(ISBLANK(SUMMARY_DATA!G3)=TRUE,"",SUMMARY_DATA!G3) -> 4.5622008 | AC50: =IF(ISBLANK(SUMMARY_DATA!H3)=TRUE,"",SUMMARY_DATA!H3) -> 3.1409309 | AE50: =IF(ISBLANK(SUMMARY_DATA!I3)=TRUE,"",SUMMARY_DATA!I3) -> 1.7618599
A51: =IF(ISBLANK(SUMMARY_DATA!A4)=TRUE,"",SUMMARY_DATA!A4) -> PIMCO: PIMCO Commodity Alpha Fund | J51: =IF(ISBLANK(SUMMARY_DATA!B4)=TRUE,"",SUMMARY_DATA!B4) -> 0.86866099 | N51: =IF(ISBLANK(SUMMARY_DATA!C4)=TRUE,"",SUMMARY_DATA!C4) -> 3.9419554 | P51: =IF(ISBLANK(SUMMARY_DATA!D4)=TRUE,"",SUMMARY_DATA!D4) -> 0.76642305 | R51: =IF(ISBLANK(SUMMARY_DATA!E4)=TRUE,"",SUMMARY_DATA!E4) -> 1.602493 | T51: =IF(ISBLANK(SUMMARY_DATA!F4)=TRUE,"",SUMMARY_DATA!F4) -> 0.44874509 | AA51: =IF(ISBLANK(SUMMARY_DATA!G4)=TRUE,"",SUMMARY_DATA!G4) -> 3.9659145 | AC51: =IF(ISBLANK(SUMMARY_DATA!H4)=TRUE,"",SUMMARY_DATA!H4) -> 2.1536702 | AE51: =IF(ISBLANK(SUMMARY_DATA!I4)=TRUE,"",SUMMARY_DATA!I4) -> 1.3853514
A52: =IF(ISBLANK(SUMMARY_DATA!A5)=TRUE,"",SUMMARY_DATA!A5) -> Graham Absolute Return Ltd: Graham Absolute Return Ltd | J52: =IF(ISBLANK(SUMMARY_DATA!B5)=TRUE,"",SUMMARY_DATA!B5) -> 2.953922 | N52: =IF(ISBLANK(SUMMARY_DATA!C5)=TRUE,"",SUMMARY_DATA!C5) -> 12.454063 | P52: =IF(ISBLANK(SUMMARY_DATA!D5)=TRUE,"",SUMMARY_DATA!D5) -> 4.2246702 | R52: =IF(ISBLANK(SUMMARY_DATA!E5)=TRUE,"",SUMMARY_DATA!E5) -> 6.4583783 | T52: =IF(ISBLANK(SUMMARY_DATA!F5)=TRUE,"",SUMMARY_DATA!F5) -> 2.3210597 | AA52: =IF(ISBLANK(SUMMARY_DATA!G5)=TRUE,"",SUMMARY_DATA!G5) -> 3.684631 | AC52: =IF(ISBLANK(SUMMARY_DATA!H5)=TRUE,"",SUMMARY_DATA!H5) -> 3.4910394 | AE52: =IF(ISBLANK(SUMMARY_DATA!I5)=TRUE,"",SUMMARY_DATA!I5) -> 1.6418692
A53: =IF(ISBLANK(SUMMARY_DATA!A6)=TRUE,"",SUMMARY_DATA!A6) -> Saba: CEF1 MN - 2.75x | J53: =IF(ISBLANK(SUMMARY_DATA!B6)=TRUE,"",SUMMARY_DATA!B6) -> 1.2214834 | N53: =IF(ISBLANK(SUMMARY_DATA!C6)=TRUE,"",SUMMARY_DATA!C6) -> 4.6594918 | P53: =IF(ISBLANK(SUMMARY_DATA!D6)=TRUE,"",SUMMARY_DATA!D6) -> 1.8678244 | R53: =IF(ISBLANK(SUMMARY_DATA!E6)=TRUE,"",SUMMARY_DATA!E6) -> 2.611006 | T53: =IF(ISBLANK(SUMMARY_DATA!F6)=TRUE,"",SUMMARY_DATA!F6) -> 1.79201 | AA53: =IF(ISBLANK(SUMMARY_DATA!G6)=TRUE,"",SUMMARY_DATA!G6) -> 3.3337494 | AC53: =IF(ISBLANK(SUMMARY_DATA!H6)=TRUE,"",SUMMARY_DATA!H6) -> 3.7325828 | AE53: =IF(ISBLANK(SUMMARY_DATA!I6)=TRUE,"",SUMMARY_DATA!I6) -> 1.6052194
A55: TOTAL | J55: =SUM(J49:J53) -> 8.27062 | N55: =SUM(N49:N53) -> 41.397274 | P55: =SUM(P49:P53) -> 12.065404 | R55: =SUM(R49:R53) -> 19.832424 | T55: =SUM(T49:T53) -> 6.8851639
A57: TOP 5 DIVERSIFIERS BY MARGINAL CONTRIBUTION TO ETL | N57: PERCENTAGE CONTRIBUTION (%) | AA57: MARGINAL CONTRIBUTION (bps)
J58: Weight | N58: PC to ETL • | P58: PC to ETR • | R58: PC to StDev | T58: PC to Return | AA58: MC to ETL • | AC58: MC to ETR • | AE58: MC to StDev
A59: =IF(ISBLANK(SUMMARY_DATA!A9)=TRUE,"",SUMMARY_DATA!A9) -> DYAL: DYAL II - Aksia | J59: =IF(ISBLANK(SUMMARY_DATA!B9)=TRUE,"",SUMMARY_DATA!B9) -> 1.9130169 | N59: =IF(ISBLANK(SUMMARY_DATA!C9)=TRUE,"",SUMMARY_DATA!C9) -> -4.9577199 | P59: =IF(ISBLANK(SUMMARY_DATA!D9)=TRUE,"",SUMMARY_DATA!D9) -> 2.6406145 | R59: =IF(ISBLANK(SUMMARY_DATA!E9)=TRUE,"",SUMMARY_DATA!E9) -> 0.51031426 | T59: =IF(ISBLANK(SUMMARY_DATA!F9)=TRUE,"",SUMMARY_DATA!F9) -> 2.6393619 | AA59: =IF(ISBLANK(SUMMARY_DATA!G9)=TRUE,"",SUMMARY_DATA!G9) -> -2.2648796 | AC59: =IF(ISBLANK(SUMMARY_DATA!H9)=TRUE,"",SUMMARY_DATA!H9) -> 3.3693579 | AE59: =IF(ISBLANK(SUMMARY_DATA!I9)=TRUE,"",SUMMARY_DATA!I9) -> 0.20032401
A60: =IF(ISBLANK(SUMMARY_DATA!A10)=TRUE,"",SUMMARY_DATA!A10) -> LibreMax CLO: LibreMax CLO | J60: =IF(ISBLANK(SUMMARY_DATA!B10)=TRUE,"",SUMMARY_DATA!B10) -> 2.0217776 | N60: =IF(ISBLANK(SUMMARY_DATA!C10)=TRUE,"",SUMMARY_DATA!C10) -> -1.5395183 | P60: =IF(ISBLANK(SUMMARY_DATA!D10)=TRUE,"",SUMMARY_DATA!D10) -> 0.028637601 | R60: =IF(ISBLANK(SUMMARY_DATA!E10)=TRUE,"",SUMMARY_DATA!E10) -> -0.37425995 | T60: =IF(ISBLANK(SUMMARY_DATA!F10)=TRUE,"",SUMMARY_DATA!F10) -> 0.73649479 | AA60: =IF(ISBLANK(SUMMARY_DATA!G10)=TRUE,"",SUMMARY_DATA!G10) -> -0.66547759 | AC60: =IF(ISBLANK(SUMMARY_DATA!H10)=TRUE,"",SUMMARY_DATA!H10) -> 0.034575161 | AE60: =IF(ISBLANK(SUMMARY_DATA!I10)=TRUE,"",SUMMARY_DATA!I10) -> -0.13901257
A61: =IF(ISBLANK(SUMMARY_DATA!A11)=TRUE,"",SUMMARY_DATA!A11) -> DE Shaw Composite Fund LLC: DE Shaw Composite Fund LLC | J61: =IF(ISBLANK(SUMMARY_DATA!B11)=TRUE,"",SUMMARY_DATA!B11) -> 9.3802815 | N61: =IF(ISBLANK(SUMMARY_DATA!C11)=TRUE,"",SUMMARY_DATA!C11) -> -7.0757864 | P61: =IF(ISBLANK(SUMMARY_DATA!D11)=TRUE,"",SUMMARY_DATA!D11) -> 9.7672504 | R61: =IF(ISBLANK(SUMMARY_DATA!E11)=TRUE,"",SUMMARY_DATA!E11) -> 5.5487738 | T61: =IF(ISBLANK(SUMMARY_DATA!F11)=TRUE,"",SUMMARY_DATA!F11) -> 14.257919 | AA61: =IF(ISBLANK(SUMMARY_DATA!G11)=TRUE,"",SUMMARY_DATA!G11) -> -0.65923583 | AC61: =IF(ISBLANK(SUMMARY_DATA!H11)=TRUE,"",SUMMARY_DATA!H11) -> 2.5416598 | AE61: =IF(ISBLANK(SUMMARY_DATA!I11)=TRUE,"",SUMMARY_DATA!I11) -> 0.44421708
A62: =IF(ISBLANK(SUMMARY_DATA!A12)=TRUE,"",SUMMARY_DATA!A12) -> Brevan Howard MB Macro Fund: Brevan Howard MB Macro Fund with proforma | J62: =IF(ISBLANK(SUMMARY_DATA!B12)=TRUE,"",SUMMARY_DATA!B12) -> 2.6002026 | N62: =IF(ISBLANK(SUMMARY_DATA!C12)=TRUE,"",SUMMARY_DATA!C12) -> -1.7935205 | P62: =IF(ISBLANK(SUMMARY_DATA!D12)=TRUE,"",SUMMARY_DATA!D12) -> 1.8080417 | R62: =IF(ISBLANK(SUMMARY_DATA!E12)=TRUE,"",SUMMARY_DATA!E12) -> 0.91589207 | T62: =IF(ISBLANK(SUMMARY_DATA!F12)=TRUE,"",SUMMARY_DATA!F12) -> 2.4690797 | AA62: =IF(ISBLANK(SUMMARY_DATA!G12)=TRUE,"",SUMMARY_DATA!G12) -> -0.60281092 | AC62: =IF(ISBLANK(SUMMARY_DATA!H12)=TRUE,"",SUMMARY_DATA!H12) -> 1.6973142 | AE62: =IF(ISBLANK(SUMMARY_DATA!I12)=TRUE,"",SUMMARY_DATA!I12) -> 0.26451556
A63: =IF(ISBLANK(SUMMARY_DATA!A13)=TRUE,"",SUMMARY_DATA!A13) -> Ares: Ares Pathfinder II | J63: =IF(ISBLANK(SUMMARY_DATA!B13)=TRUE,"",SUMMARY_DATA!B13) -> 1.6485661 | N63: =IF(ISBLANK(SUMMARY_DATA!C13)=TRUE,"",SUMMARY_DATA!C13) -> -0.97570762 | P63: =IF(ISBLANK(SUMMARY_DATA!D13)=TRUE,"",SUMMARY_DATA!D13) -> 1.3646659 | R63: =IF(ISBLANK(SUMMARY_DATA!E13)=TRUE,"",SUMMARY_DATA!E13) -> 0.69449676 | T63: =IF(ISBLANK(SUMMARY_DATA!F13)=TRUE,"",SUMMARY_DATA!F13) -> 1.7267151 | AA63: =IF(ISBLANK(SUMMARY_DATA!G13)=TRUE,"",SUMMARY_DATA!G13) -> -0.51724379 | AC63: =IF(ISBLANK(SUMMARY_DATA!H13)=TRUE,"",SUMMARY_DATA!H13) -> 2.0206028 | AE63: =IF(ISBLANK(SUMMARY_DATA!I13)=TRUE,"",SUMMARY_DATA!I13) -> 0.31635738
A65: TOTAL | J65: =SUM(J59:J63) -> 17.563845 | N65: =SUM(N59:N63) -> -16.342253 | P65: =SUM(P59:P63) -> 15.60921 | R65: =SUM(R59:R63) -> 7.2952169 | T65: =SUM(T59:T63) -> 21.829571

Sheet SUMMARY_DATA
A1: TOP 5 RISK CONTRIBUTORS - POSITIONS
A2: Silver Point Capital: Silver Point Distressed Opportunity Institutional Partners + Silver Point HF | B2: 0.77463136 | C2: 7.5420822 | D2: 2.0514522 | E2: 3.4079492 | F2: 0.96608254 | G2: 8.5089926 | H2: 6.464386 | I2: 3.3037878
A3: LibreMax Partners LP: LibreMax Partners LP | B3: 2.4519223 | C3: 12.799681 | D3: 3.1550345 | E3: 5.7525972 | F3: 1.3572666 | G3: 4.5622008 | H3: 3.1409309 | I3: 1.7618599
A4: PIMCO: PIMCO Commodity Alpha Fund | B4: 0.86866099 | C4: 3.9419554 | D4: 0.76642305 | E4: 1.602493 | F4: 0.44874509 | G4: 3.9659145 | H4: 2.1536702 | I4: 1.3853514
A5: Graham Absolute Return Ltd: Graham Absolute Return Ltd | B5: 2.953922 | C5: 12.454063 | D5: 4.2246702 | E5: 6.4583783 | F5: 2.3210597 | G5: 3.684631 | H5: 3.4910394 | I5: 1.6418692
A6: Saba: CEF1 MN - 2.75x | B6: 1.2214834 | C6: 4.6594918 | D6: 1.8678244 | E6: 2.611006 | F6: 1.79201 | G6: 3.3337494 | H6: 3.7325828 | I6: 1.6052194
A8: TOP 5 RISK DIVERSIFIERS - POSITIONS
A9: DYAL: DYAL II - Aksia | B9: 1.9130169 | C9: -4.9577199 | D9: 2.6406145 | E9: 0.51031426 | F9: 2.6393619 | G9: -2.2648796 | H9: 3.3693579 | I9: 0.20032401
A10: LibreMax CLO: LibreMax CLO | B10: 2.0217776 | C10: -1.5395183 | D10: 0.028637601 | E10: -0.37425995 | F10: 0.73649479 | G10: -0.66547759 | H10: 0.034575161 | I10: -0.13901257
A11: DE Shaw Composite Fund LLC: DE Shaw Composite Fund LLC | B11: 9.3802815 | C11: -7.0757864 | D11: 9.7672504 | E11: 5.5487738 | F11: 14.257919 | G11: -0.65923583 | H11: 2.5416598 | I11: 0.44421708
A12: Brevan Howard MB Macro Fund: Brevan Howard MB Macro Fund with proforma | B12: 2.6002026 | C12: -1.7935205 | D12: 1.8080417 | E12: 0.91589207 | F12: 2.4690797 | G12: -0.60281092 | H12: 1.6973142 | I12: 0.26451556
A13: Ares: Ares Pathfinder II | B13: 1.6485661 | C13: -0.97570762 | D13: 1.3646659 | E13: 0.69449676 | F13: 1.7267151 | G13: -0.51724379 | H13: 2.0206028 | I13: 0.31635738
A15: UP-RIGHT - SIMULATED PORTFOLIO RISK STATISTICS
A16: 00000MP87KPZC-3AM47H-TTQARV | B16: 0.75095534 | C16: 2.6013856 | D16: 0.9376494 | E16: 11.251793 | F16: 0.87394068 | G16: 0.28728808 | H16: -2.0635408 | I16: 2.4409617
A22: Factor Risk
A23: Factor Risk | B23: 47.149713
A25: Factor Risk
A26: Factor Risk | B26: 115.77315
A29: Portfolio Composition
A30: Multi Strategy | B30: 29.910414
A31: Relative Value | B31: 19.285614
A32: Global Macro | B32: 14.563052
A33: Dockside | B33: 13.589956
A34: Equity Long Short | B34: 8.6928088
A35: Credit | B35: 6.6920936
A36: Specialty Finance | B36: 5.1152413
A37: Coinvests | B37: 2.1508199

Sheet HISTORICAL RISK
A4: DETAILED HISTORICAL STATISTICS
A5: Ex-post (Historical) information about the assets in the portfolio
G7: HISTORICAL STATISTICS
G8: Weight | I8: Mean | K8: StDev | M8: Sharpe | O8: STARR | Q8: Rachev | S8: Skew | U8: Excess Kurtosis | W8: Upside Volatility | Y8: Max Drawdown (%) | AA8: Downside Volatility | AC8: Total Winning Periods | AE8: Total Losing Periods | AG8: Ann.Mean | AI8: Ann. StDev
A9: 12267: Trexquant Onshore Fund LP | G9: 3.1198357 | I9: 1.0714815 | K9: 2.7732815 | M9: 0.26616416 | O9: 0.13287995 | Q9: 1.1476148 | S9: -0.35813677 | U9: 0.52433027 | W9: 1.8450521 | Y9: 8.05852 | AA9: 1.9567993 | AC9: 57 | AE9: 24 | AG9: =IF(ISBLANK(I9)=TRUE,"",I9*12) -> 12.857778 | AI9: =IF(ISBLANK(K9)=TRUE,"",K9*SQRT(12)) -> 9.6069289
A10: Aquatic: Aquatic - Nautilus CFM (Net) | G10: 0.38382851 | I10: -0.59070988 | K10: 3.2964614 | M10: -0.28031368 | O10: -0.11889196 | Q10: 0.70764431 | S10: -0.34573448 | U10: -0.12929051 | W10: 1.5874962 | Y10: 53.023867 | AA10: 2.3075354 | AC10: 39 | AE10: 42 | AG10: =IF(ISBLANK(I10)=TRUE,"",I10*12) -> -7.0885185 | AI10: =IF(ISBLANK(K10)=TRUE,"",K10*SQRT(12)) -> 11.419277
A11: Ares: Ares Pathfinder II | G11: 1.6485661 | I11: 0.99953086 | K11: 2.4718761 | M11: 0.26951089 | O11: 0.26098272 | Q11: 3.7605723 | S11: 2.1223157 | U11: 10.458279 | W11: 2.6226884 | Y11: 7.7806 | AA11: 3.7834455 | AC11: 79 | AE11: 2 | AG11: =IF(ISBLANK(I11)=TRUE,"",I11*12) -> 11.99437 | AI11: =IF(ISBLANK(K11)=TRUE,"",K11*SQRT(12)) -> 8.56283
A12: Bayview Asset Management: MSR Fund | G12: 2.2527339 | I12: 0.76405802 | K12: 0.83007776 | M12: 0.5188968 | O12: 0.30058074 | Q12: 1.113069 | S12: -7.0557875 | U12: 58.545269 | W12: 0.30165825 | Y12: 6.06 | AA12: 4.2284986 | AC12: 79 | AE12: 2 | AG12: =IF(ISBLANK(I12)=TRUE,"",I12*12) -> 9.1686963 | AI12: =IF(ISBLANK(K12)=TRUE,"",K12*SQRT(12)) -> 2.8754737
A13: Benefit Street Partners: Benefit Street Partners Origination Fund (CCFLX) | G13: 0.074708538 | I13: 0.8767284 | K13: 1.2028065 | M13: 0.45177263 | O13: 0.49157117 | Q13: 3.6423548 | S13: 5.4820265 | U13: 45.27914 | W13: 1.1229234 | Y13: 2.15 | AA13: 1.0369588 | AC13: 76 | AE13: 5 | AG13: =IF(ISBLANK(I13)=TRUE,"",I13*12) -> 10.520741 | AI13: =IF(ISBLANK(K13)=TRUE,"",K13*SQRT(12)) -> 4.1666439
A14: BlackRock: GAO | G14: 2.3161392 | I14: 1.2238272 | K14: 2.5901726 | M14: 0.3437971 | O14: 0.27526857 | Q14: 2.4397218 | S14: 0.6274458 | U14: 0.58996153 | W14: 2.0488955 | Y14: 5.3062721 | AA14: 0.97837613 | AC14: 55 | AE14: 26 | AG14: =IF(ISBLANK(I14)=TRUE,"",I14*12) -> 14.685926 | AI14: =IF(ISBLANK(K14)=TRUE,"",K14*SQRT(12)) -> 8.972621
A15: Blackstone: Badgerstone Access | G15: 5.0884559 | I15: 0.90211975 | K15: 0.9046461 | M15: 0.62873915 | O15: 1.0778084 | Q15: 6.2826283 | S15: 1.1036542 | U15: 2.9265605 | W15: 0.80004345 | Y15: 0.82781485 | AA15: 0.23978028 | AC15: 69 | AE15: 12 | AG15: =IF(ISBLANK(I15)=TRUE,"",I15*12) -> 10.825437 | AI15: =IF(ISBLANK(K15)=TRUE,"",K15*SQRT(12)) -> 3.133786
A16: Blue Owl: Blue Owl Funding Partners (CCLFX) | G16: 0.31241515 | I16: 0.84897654 | K16: 1.0539468 | M16: 0.48924976 | O16: 0.84879541 | Q16: 6.7930453 | S16: 1.782033 | U16: 6.2391716 | W16: 0.99566105 | Y16: 2.15 | AA16: 1.1615507 | AC16: 78 | AE16: 3 | AG16: =IF(ISBLANK(I16)=TRUE,"",I16*12) -> 10.187719 | AI16: =IF(ISBLANK(K16)=TRUE,"",K16*SQRT(12)) -> 3.6509787
A17: Brevan Howard Coinvests (Aksia): Brevan Howard Special Opportunities SPC | G17: 0.63216727 | I17: 0.25170741 | K17: 4.1750216 | M17: -0.019551019 | O17: -0.009796855 | Q17: 1.3375091 | S17: -0.19749069 | U17: 6.2696774 | W17: 3.2020631 | Y17: 37.348796 | AA17: 3.0206739 | AC17: 43 | AE17: 38 | AG17: =IF(ISBLANK(I17)=TRUE,"",I17*12) -> 3.0204889 | AI17: =IF(ISBLANK(K17)=TRUE,"",K17*SQRT(12)) -> 14.462699
A18: Brevan Howard MB Macro Fund: Brevan Howard MB Macro Fund with proforma | G18: 2.6002026 | I18: 0.8908284 | K18: 1.6667634 | M18: 0.33447762 | O18: 0.20678408 | Q18: 1.6845727 | S18: -0.024429776 | U18: 0.76532594 | W18: 1.1667057 | Y18: 4.3158265 | AA18: 0.95197621 | AC18: 61 | AE18: 20 | AG18: =IF(ISBLANK(I18)=TRUE,"",I18*12) -> 10.689941 | AI18: =IF(ISBLANK(K18)=TRUE,"",K18*SQRT(12)) -> 5.7738379
A19: D. E. Shaw: Cogence | G19: 1.9781362 | I19: 1.6964556 | K19: 2.7684984 | M19: 0.49236879 | O19: 0.3063196 | Q19: 1.7696629 | S19: 0.020854954 | U19: 1.3372808 | W19: 2.057393 | Y19: 8.2034 | AA19: 1.7979819 | AC19: 63 | AE19: 18 | AG19: =IF(ISBLANK(I19)=TRUE,"",I19*12) -> 20.357467 | AI19: =IF(ISBLANK(K19)=TRUE,"",K19*SQRT(12)) -> 9.5903598
A20: DE Shaw Composite Fund LLC: DE Shaw Composite Fund LLC | G20: 9.3802815 | I20: 1.4251519 | K20: 1.0274129 | M20: 1.0626872 | O20: 4.1928515 | Q20: 14.871736 | S20: 0.67740955 | U20: 1.3904342 | W20: 0.94066441 | Y20: 0.4098 | AA20: 0.13087777 | AC20: 74 | AE20: 7 | AG20: =IF(ISBLANK(I20)=TRUE,"",I20*12) -> 17.101822 | AI20: =IF(ISBLANK(K20)=TRUE,"",K20*SQRT(12)) -> 3.5590626
... A45: Walleye: Walleye Opportunities Fund | G45: 3.5814946 | I45: 0.94420494 | K45: 1.9389349 | M45: 0.31505524 | O45: 0.20156289 | Q45: 2.0127529 | S45: 0.61809322 | U45: 7.774838 | W45: 1.5995428 | Y45: 7 | AA45: 1.5057421 | AC45: 61 | AE45: 20 | AG45: =IF(ISBLANK(I45)=TRUE,"",I45*12) -> 11.330459 | AI45: =IF(ISBLANK(K45)=TRUE,"",K45*SQRT(12)) -> 6.7166675
AG46: =IF(ISBLANK(I46)=TRUE,"",I46*12) | AI46: =IF(ISBLANK(K46)=TRUE,"",K46*SQRT(12))
AG47: =IF(ISBLANK(I47)=TRUE,"",I47*12) | AI47: =IF(ISBLANK(K47)=TRUE,"",K47*SQRT(12))
AG48: =IF(ISBLANK(I48)=TRUE,"",I48*12) | AI48: =IF(ISBLANK(K48)=TRUE,"",K48*SQRT(12))
AG49: =IF(ISBLANK(I49)=TRUE,"",I49*12) | AI49: =IF(ISBLANK(K49)=TRUE,"",K49*SQRT(12))
AG50: =IF(ISBLANK(I50)=TRUE,"",I50*12) | AI50: =IF(ISBLANK(K50)=TRUE,"",K50*SQRT(12))
AG51: =IF(ISBLANK(I51)=TRUE,"",I51*12) | AI51: =IF(ISBLANK(K51)=TRUE,"",K51*SQRT(12))
AG52: =IF(ISBLANK(I52)=TRUE,"",I52*12) | AI52: =IF(ISBLANK(K52)=TRUE,"",K52*SQRT(12))
AG53: =IF(ISBLANK(I53)=TRUE,"",I53*12) | AI53: =IF(ISBLANK(K53)=TRUE,"",K53*SQRT(12))
AG54: =IF(ISBLANK(I54)=TRUE,"",I54*12) | AI54: =IF(ISBLANK(K54)=TRUE,"",K54*SQRT(12))
AG55: =IF(ISBLANK(I55)=TRUE,"",I55*12) | AI55: =IF(ISBLANK(K55)=TRUE,"",K55*SQRT(12))
AG56: =IF(ISBLANK(I56)=TRUE,"",I56*12) | AI56: =IF(ISBLANK(K56)=TRUE,"",K56*SQRT(12))
AG57: =IF(ISBLANK(I57)=TRUE,"",I57*12) | AI57: =IF(ISBLANK(K57)=TRUE,"",K57*SQRT(12))
... AG83: =IF(ISBLANK(I83)=TRUE,"",I83*12) | AI83: =IF(ISBLANK(K83)=TRUE,"",K83*SQRT(12))

Sheet SIMULATED RISK
A4: DETAILED SIMULATED RISK STATISTICS
A5: Ex-ante (Simulated) statistics for portfolio and assets
G7: SIMULATED STATISTICS
G8: Weight | I8: ETR (%) | K8: ETL (%) | M8: VaR(%) | O8: PC to StDev (%) | Q8: PC to ETL (%) • | S8: PC to ETR (%) • | U8: MC to StDev (bps) | W8: MC to ETL (bps) | Y8: MC to ETR | AA8: PC to Return
A9: Current 7.26 | G9: 100 | I9: 2.4409617 | K9: 0.87394068 | M9: 0.28728808 | O9: 100 | Q9: 100 | S9: 100 | AA9: 100
A10: Coinvests | G10: 2.1508199 | I10: 5.1194606 | K10: 3.7155407 | M10: 2.5626743 | O10: 1.7959471 | Q10: 1.8814124 | S10: 1.8035228 | U10: 0.62705206 | W10: 0.76447256 | Y10: 2.0468148 | AA10: 1.2087765
A11: Brevan Howard Coinvests (Aksia): Brevan Howard Special Opportunities SPC | G11: 0.63216727 | I11: 9.301136 | K11: 7.4569555 | M11: 5.5038922 | O11: 0.15244034 | Q11: -0.35162447 | S11: 0.36461956 | U11: 0.18108481 | W11: -0.48610383 | Y11: 1.4078906 | AA11: 0.15861723
A12: HF: Current Coinvests (Excluding BH Coinvests) | G12: 1.5186526 | I12: 6.342087 | K12: 4.7769625 | M12: 3.3566353 | O12: 1.6435067 | Q12: 2.2330368 | S12: 1.4389032 | U12: 0.81269418 | W12: 1.2850481 | Y12: 2.3127788 | AA12: 1.0501593
A13: Credit | G13: 6.6920936 | I13: 4.6156241 | K13: 3.9996909 | M13: 2.4511342 | O13: 10.070044 | Q13: 18.998554 | S13: 6.9948532 | U13: 1.1300131 | W13: 2.4810784 | Y13: 2.5513942 | AA13: 5.0733679
A14: Benefit Street Partners: Benefit Street Partners Origination Fund (CCFLX) | G14: 0.074708538 | I14: 2.6701565 | K14: 0.76548264 | M14: 0.33810438 | O14: 0.014358306 | Q14: -0.041206618 | S14: 0.034903801 | U14: 0.14432684 | W14: -0.48203513 | Y14: 1.1404164 | AA14: 0.06954936
A15: Blue Owl: Blue Owl Funding Partners (CCLFX) | G15: 0.31241515 | I15: 3.7858317 | K15: 0.83186561 | M15: 0.45820667 | O15: 0.11343669 | Q15: -0.077156142 | S15: 0.19093011 | U15: 0.27266888 | W15: -0.21583426 | Y15: 1.4917749 | AA15: 0.28285448
A16: King Street Capital LP: King Street Capital LP | G16: 0.061233379 | I16: 3.2682707 | K16: 4.38086 | M16: 3.0140197 | O16: 0.05328955 | Q16: 0.14474075 | S16: 0.019131274 | U16: 0.65353361 | W16: 2.0657822 | Y16: 0.7626348 | AA16: -0.0045952032
A17: LibreMax CLO: LibreMax CLO | G17: 2.0217776 | I17: 3.8398542 | K17: 3.64007 | M17: 2.3798548 | O17: -0.37425995 | Q17: -1.5395183 | S17: 0.028637601 | U17: -0.13901257 | W17: -0.66547759 | Y17: 0.034575161 | AA17: 0.73649479
A18: LibreMax Partners LP: LibreMax Partners LP | G18: 2.4519223 | I18: 6.3598225 | K18: 7.0560159 | M18: 4.6273557 | O18: 5.7525972 | Q18: 12.799681 | S18: 3.1550345 | U18: 1.7618599 | W18: 4.5622008 | Y18: 3.1409309 | AA18: 1.3572666
A19: Silver Point Capital Fund II LP: Silver Point Capital Fund II LP | G19: 0.99540528 | I19: 8.9126466 | K19: 2.7710748 | M19: 1.8439552 | O19: 1.102673 | Q19: 0.16993092 | S19: 1.5147637 | U19: 0.83188046 | W19: 0.14919505 | Y19: 3.7145474 | AA19: 1.6657154
A20: Silver Point Capital: Silver Point Distressed Opportunity Institutional Partners + Silver Point HF | G20: 0.77463136 | I20: 14.922523 | K20: 13.930755 | M20: 8.90648 | O20: 3.4079492 | Q20: 7.5420822 | S20: 2.0514522 | U20: 3.3037878 | W20: 8.5089926 | Y20: 6.464386 | AA20: 0.96608254
A21: Dockside | G21: 13.589956 | I21: 3.9051153 | K21: 2.1224448 | M21: 1.23642 | O21: 19.710672 | Q21: 25.089923 | S21: 17.643214 | U21: 1.0891745 | W21: 1.6134786 | Y21: 3.168988 | AA21: 14.166789
... A54: HF: Current Specialty Finance (Excluding Pathfinder) | G54: 3.4666752 | I54: 4.0530587 | K54: 2.7827868 | M54: 1.6243823 | O54: 4.5704652 | Q54: 7.0467326 | S54: 3.6899738 | U54: 0.99005965 | W54: 1.7764648 | Y54: 2.5981911 | AA54: 3.2415104

Sheet RISK BUDGETING (ETL)
A4: RISK BUDGETING (ETL)
A5: Implied Return (IR) is the required return of the asset to justify its contribution to the portfolio risk assuming that the current portfolio has optimal performance ratio. To improve the risk-adjusted performance of the portfolio one should consider increasing the weights of the assets with IRs lower that the expected returns of those assets and lowering those with IRs higher than their expected retuns.
Z9: Weight (%) | AB9: Mean | AD9: MC to ETL | AF9: Implied Return (ETL) | AH9: Difference
Q10: Current 7.26 | Z10: 100 | AB10: 0.9376494
P11: =IF(ISBLANK(Q11)=TRUE,"",1) -> 1 | Q11: Coinvests | Z11: 2.1508199 | AB11: 0.5269658 | AD11: 0.76447256 | AF11: 0.82020125 | AH11: -0.29323544
P12: =IF(ISBLANK(Q12)=TRUE,"",2) -> 2 | Q12: Brevan Howard Coinvests (Aksia): Brevan Howard Special Opportunities SPC | Z12: 0.63216727 | AB12: 0.23526582 | AD12: -0.48610383 | AF12: -0.52153993 | AH12: 0.75680575
P13: =IF(ISBLANK(Q13)=TRUE,"",3) -> 3 | Q13: HF: Current Coinvests (Excluding BH Coinvests) | Z13: 1.5186526 | AB13: 0.64839132 | AD13: 1.2850481 | AF13: 1.3787258 | AH13: -0.73033453
P14: =IF(ISBLANK(Q14)=TRUE,"",4) -> 4 | Q14: Credit | Z14: 6.6920936 | AB14: 0.71084487 | AD14: 2.4810784 | AF14: 2.6619446 | AH14: -1.9510997
P15: =IF(ISBLANK(Q15)=TRUE,"",5) -> 5 | Q15: Benefit Street Partners: Benefit Street Partners Origination Fund (CCFLX) | Z15: 0.074708538 | AB15: 0.87289776 | AD15: -0.48203513 | AF15: -0.51717463 | AH15: 1.3900724
P16: =IF(ISBLANK(Q16)=TRUE,"",6) -> 6 | Q16: Blue Owl: Blue Owl Funding Partners (CCLFX) | Z16: 0.31241515 | AB16: 0.84892915 | AD16: -0.21583426 | AF16: -0.23156819 | AH16: 1.0804973
P17: =IF(ISBLANK(Q17)=TRUE,"",7) -> 7 | Q17: King Street Capital LP: King Street Capital LP | Z17: 0.061233379 | AB17: -0.070365046 | AD17: 2.0657822 | AF17: 2.2163741 | AH17: -2.2867391
P18: =IF(ISBLANK(Q18)=TRUE,"",8) -> 8 | Q18: LibreMax CLO: LibreMax CLO | Z18: 2.0217776 | AB18: 0.34156768 | AD18: -0.66547759 | AF18: -0.71398972 | AH18: 1.0555574
P19: =IF(ISBLANK(Q19)=TRUE,"",9) -> 9 | Q19: LibreMax Partners LP: LibreMax Partners LP | Z19: 2.4519223 | AB19: 0.51903774 | AD19: 4.5622008 | AF19: 4.8947771 | AH19: -4.3757394
P20: =IF(ISBLANK(Q20)=TRUE,"",10) -> 10 | Q20: Silver Point Capital Fund II LP: Silver Point Capital Fund II LP | Z20: 0.99540528 | AB20: 1.5690665 | AD20: 0.14919505 | AF20: 0.16007111 | AH20: 1.4089953
P21: =IF(ISBLANK(Q21)=TRUE,"",11) -> 11 | Q21: Silver Point Capital: Silver Point Distressed Opportunity Institutional Partners + Silver Point HF | Z21: 0.77463136 | AB21: 1.1693907 | AD21: 8.5089926 | AF21: 9.1292829 | AH21: -7.9598922
P22: =IF(ISBLANK(Q22)=TRUE,"",12) -> 12 | Q22: Dockside | Z22: 13.589956 | AB22: 0.97744842 | AD22: 1.6134786 | AF22: 1.7310983 | AH22: -0.75364993
P23: =IF(ISBLANK(Q23)=TRUE,"",13) -> 13 | Q23: 12267: Trexquant Onshore Fund LP | Z23: 3.1198357 | AB23: 1.070413 | AD23: 0.079299843 | AF23: 0.08508066 | AH23: 0.98533231
P24: =IF(ISBLANK(Q24)=TRUE,"",14) -> 14 | Q24: Dockside: I-94 Minus Standalones | Z24: 6.254264 | AB24: 1.0463513 | AD24: 2.4134516 | AF24: 2.5893879 | AH24: -1.5430366
P25: =IF(ISBLANK(Q25)=TRUE,"",15) -> 15 | Q25: Dorsal Capital Partners LP: Dorsal Capital Partners LP | Z25: 2.9943734 | AB25: 0.57425515 | AD25: 0.83931385 | AF25: 0.90049833 | AH25: -0.32624318
P26: =IF(ISBLANK(Q26)=TRUE,"",16) -> 16 | Q26: Saba: CEF1 MN - 2.75x | Z26: 1.2214834 | AB26: 1.3756037 | AD26: 3.3337494 | AF26: 3.5767738 | AH26: -2.20117
P27: =IF(ISBLANK(Q27)=TRUE,"",17) -> 17 | Q27: Equity Long Short | Z27: 8.6928088 | AB27: 0.82495862 | AD27: -0.068971375 | AF27: -0.073999265 | AH27: 0.89895788
P28: =IF(ISBLANK(Q28)=TRUE,"",18) -> 18 | Q28: Four World: FWGO | Z28: 2.1319734 | AB28: 0.86964862 | AD28: 0.054908594 | AF28: 0.058911332 | AH28: 0.81073729
P29: =IF(ISBLANK(Q29)=TRUE,"",19) -> 19 | Q29: Four World: FWGO Minority Descent | Z29: 1.7445328 | AB29: 0.6302408 | AD29: 0.87795682 | AF29: 0.9419583 | AH29: -0.3117175
P30: =IF(ISBLANK(Q30)=TRUE,"",20) -> 20 | Q30: Holocene: Holocene Advisors Master | Z30: 4.8163025 | AB30: 0.87570579 | AD30: -0.46679857 | AF30: -0.50082736 | AH30: 1.3765331
P31: =IF(ISBLANK(Q31)=TRUE,"",21) -> 21 | Q31: Global Macro | Z31: 14.563052 | AB31: 0.96297434 | AD31: 2.1472414 | AF31: 2.3037714 | AH31: -1.3407971
P32: =IF(ISBLANK(Q32)=TRUE,"",22) -> 22 | Q32: Brevan Howard MB Macro Fund: Brevan Howard MB Macro Fund with proforma | Z32: 2.6002026 | AB32: 0.89036567 | AD32: -0.60281092 | AF32: -0.64675475 | AH32: 1.5371204
P33: =IF(ISBLANK(Q33)=TRUE,"",23) -> 23 | Q33: Graham Absolute Return Ltd: Graham Absolute Return Ltd | Z33: 2.953922 | AB33: 0.73676293 | AD33: 3.684631 | AF33: 3.953234 | AH33: -3.2164711
P34: =IF(ISBLANK(Q34)=TRUE,"",24) -> 24 | Q34: Mesarete: Prior TR+back with Pharo Macro+Mesarete Capital Fund | Z34: 2.6503264 | AB34: 0.5603043 | AD34: 2.6105921 | AF34: 2.8008996 | AH34: -2.2405953
P35: =IF(ISBLANK(Q35)=TRUE,"",25) -> 25 | Q35: PIMCO: PIMCO Commodity Alpha Fund | Z35: 0.86866099 | AB35: 0.48438409 | AD35: 3.9659145 | AF35: 4.2550225 | AH35: -3.7706385
P36: =IF(ISBLANK(Q36)=TRUE,"",26) -> 26 | Q36: Rokos Global Macro Fund LP: Rokos Global Macro Fund LP | Z36: 5.4899402 | AB36: 1.389199 | AD36: 2.1110885 | AF36: 2.2649831 | AH36: -0.87578407
P37: =IF(ISBLANK(Q37)=TRUE,"",27) -> 27 | Q37: Multi Strategy | Z37: 29.910414 | AB37: 1.0985524 | AD37: 0.13950148 | AF37: 0.14967089 | AH37: 0.94888151
P38: =IF(ISBLANK(Q38)=TRUE,"",28) -> 28 | Q38: Blackstone: Badgerstone Access | Z38: 5.0884559 | AB38: 0.90210472 | AD38: -0.18409756 | AF38: -0.19751794 | AH38: 1.0996227
P39: =IF(ISBLANK(Q39)=TRUE,"",29) -> 29 | Q39: D. E. Shaw: Cogence | Z39: 1.9781362 | AB39: 1.7007494 | AD39: 2.2178291 | AF39: 2.3795049 | AH39: -0.67875552
P40: =IF(ISBLANK(Q40)=TRUE,"",30) -> 30 | Q40: DE Shaw Composite Fund LLC: DE Shaw Composite Fund LLC | Z40: 9.3802815 | AB40: 1.4252162 | AD40: -0.65923583 | AF40: -0.70729294 | AH40: 2.1325092
P41: =IF(ISBLANK(Q41)=TRUE,"",31) -> 31 | Q41: DYAL: DYAL II - Aksia | Z41: 1.9130169 | AB41: 1.2936614 | AD41: -2.2648796 | AF41: -2.4299853 | AH41: 3.7236467
P42: =IF(ISBLANK(Q42)=TRUE,"",32) -> 32 | Q42: Elliott Associates LP: Elliott Associates LP | Z42: 7.9690284 | AB42: 0.71204297 | AD42: 0.16092826 | AF42: 0.17265964 | AH42: 0.53938333
P43: =IF(ISBLANK(Q43)=TRUE,"",33) -> 33 | Q43: Walleye: Walleye Opportunities Fund | Z43: 3.5814946 | AB43: 0.94527756 | AD43: 2.7799233 | AF43: 2.9825747 | AH43: -2.0372972
P44: =IF(ISBLANK(Q44)=TRUE,"",34) -> 34 | Q44: Relative Value | Z44: 19.285614 | AB44: 0.82337777 | AD44: 0.36659533 | AF44: 0.39331948 | AH44: 0.43005829
P45: =IF(ISBLANK(Q45)=TRUE,"",35) -> 35 | Q45: Aquatic: Aquatic - Nautilus CFM (Net) | Z45: 0.38382851 | AB45: -0.59150315 | AD45: 1.9869707 | AF45: 2.1318173 | AH45: -2.7233205
F46: • Implied Return (ETL) | I46: • Mean Return (%) | P46: =IF(ISBLANK(Q46)=TRUE,"",36) -> 36 | Q46: Bayview Asset Management: MSR Fund | Z46: 2.2527339 | AB46: 0.76373881 | AD46: 0.50817708 | AF46: 0.54522228 | AH46: 0.21851653
P47: =IF(ISBLANK(Q47)=TRUE,"",37) -> 37 | Q47: BlackRock: GAO | Z47: 2.3161392 | AB47: 1.2240246 | AD47: 0.29927867 | AF47: 0.32109555 | AH47: 0.90292904
P48: =IF(ISBLANK(Q48)=TRUE,"",38) -> 38 | Q48: Hudson Structured: HSCM w MFC | Z48: 0.70577308 | AB48: 0.096190573 | AD48: 0.41708352 | AF48: 0.44748817 | AH48: -0.35129759
P49: =IF(ISBLANK(Q49)=TRUE,"",39) -> 39 | Q49: PIMCO Global Credit Opportunity Onshore Fund LLC: PIMCO Global Credit Opportunity Onshore Fund LLC | Z49: 3.7762459 | AB49: 0.8145471 | AD49: 0.22079253 | AF49: 0.23688791 | AH49: 0.57765919
P50: =IF(ISBLANK(Q50)=TRUE,"",40) -> 40 | Q50: Reflow Full Track: ReFlow LO Excess Plus Market Neutral | Z50: 2.4542568 | AB50: 0.47235154 | AD50: -0.19166954 | AF50: -0.20564191 | AH50: 0.67799345
P51: =IF(ISBLANK(Q51)=TRUE,"",41) -> 41 | Q51: Taula: SWIB-DM Taula | Z51: 3.5329348 | AB51: 1.222481 | AD51: -0.21440135 | AF51: -0.23003082 | AH51: 1.4525118
P52: =IF(ISBLANK(Q52)=TRUE,"",42) -> 42 | Q52: Voleon Composition Domestic Fund LP: Voleon Composition Domestic Fund LP | Z52: 3.8637021 | AB52: 0.7580382 | AD52: 1.1825809 | AF52: 1.268789 | AH52: -0.51075076
P53: =IF(ISBLANK(Q53)=TRUE,"",43) -> 43 | Q53: Specialty Finance | Z53: 5.1152413 | AB53: 0.91070065 | AD53: 1.0372366 | AF53: 1.1128493 | AH53: -0.20214869
P54: =IF(ISBLANK(Q54)=TRUE,"",44) -> 44 | Q54: Ares: Ares Pathfinder II | Z54: 1.6485661 | AB54: 0.98209792 | AD54: -0.51724379 | AF54: -0.55494994 | AH54: 1.5370479
P55: =IF(ISBLANK(Q55)=TRUE,"",45) -> 45 | Q55: HF: Current Specialty Finance (Excluding Pathfinder) | Z55: 3.4666752 | AB55: 0.87674791 | AD55: 1.7764648 | AF55: 1.9059659 | AH55: -1.029218
P56: =IF(ISBLANK(Q56)=TRUE,"",46)
P57: =IF(ISBLANK(Q57)=TRUE,"",47)
P58: =IF(ISBLANK(Q58)=TRUE,"",48)
P59: =IF(ISBLANK(Q59)=TRUE,"",49)
P60: =IF(ISBLANK(Q60)=TRUE,"",50)
P61: =IF(ISBLANK(Q61)=TRUE,"",51)
P62: =IF(ISBLANK(Q62)=TRUE,"",52)
P63: =IF(ISBLANK(Q63)=TRUE,"",53)
P64: =IF(ISBLANK(Q64)=TRUE,"",54)
P65: =IF(ISBLANK(Q65)=TRUE,"",55)
P66: =IF(ISBLANK(Q66)=TRUE,"",56)
P67: =IF(ISBLANK(Q67)=TRUE,"",57)
P68: =IF(ISBLANK(Q68)=TRUE,"",58)
P69: =IF(ISBLANK(Q69)=TRUE,"",59)
P70: =IF(ISBLANK(Q70)=TRUE,"",60)
P71: =IF(ISBLANK(Q71)=TRUE,"",61)
P72: =IF(ISBLANK(Q72)=TRUE,"",62)
P73: =IF(ISBLANK(Q73)=TRUE,"",63)
P74: =IF(ISBLANK(Q74)=TRUE,"",64)
P75: =IF(ISBLANK(Q75)=TRUE,"",65)
P76: =IF(ISBLANK(Q76)=TRUE,"",66)
P77: =IF(ISBLANK(Q77)=TRUE,"",67)
P78: =IF(ISBLANK(Q78)=TRUE,"",68)
P79: =IF(ISBLANK(Q79)=TRUE,"",69)
P80: =IF(ISBLANK(Q80)=TRUE,"",70)
P81: =IF(ISBLANK(Q81)=TRUE,"",71)
P82: =IF(ISBLANK(Q82)=TRUE,"",72)
P83: =IF(ISBLANK(Q83)=TRUE,"",73)

Sheet RB_ETL
B1: Portfolio/Groups | C1: Mean | D1: MC to ETL | E1: Impl.Return | F1: Diff | I1: Assets | J1: Mean | K1: MC to ETL | L1: Impl.Return | M1: Diff
B2: Current 7.26 | C2: 0.9376494 | I2: Current 7.26 | J2: 0.9376494
A3: {=INDEX('RISK BUDGETING (ETL)'!P$11:P$87, MATCH(1, (B3='RISK BUDGETING (ETL)'!Q$11:Q$87) * (C3='RISK BUDGETING (ETL)'!AB$11:AB$87) * (D3='RISK BUDGETING (ETL)'!AD$11:AD$87) * (E3='RISK BUDGETING (ETL)'!AF$11:AF$87), 0))} -> 1 | B3: Coinvests | C3: 0.5269658 | D3: 0.76447256 | E3: 0.82020125 | F3: -0.29323544 | H3: {=INDEX('RISK BUDGETING (ETL)'!P$11:P$87, MATCH(1, (I3='RISK BUDGETING (ETL)'!Q$11:Q$87) * (J3='RISK BUDGETING (ETL)'!AB$11:AB$87) * (K3='RISK BUDGETING (ETL)'!AD$11:AD$87) * (L3='RISK BUDGETING (ETL)'!AF$11:AF$87), 0))} -> 13 | I3: 12267: Trexquant Onshore Fund LP | J3: 1.070413 | K3: 0.079299843 | L3: 0.08508066 | M3: 0.98533231
A4: {=INDEX('RISK BUDGETING (ETL)'!P$11:P$87, MATCH(1, (B4='RISK BUDGETING (ETL)'!Q$11:Q$87) * (C4='RISK BUDGETING (ETL)'!AB$11:AB$87) * (D4='RISK BUDGETING (ETL)'!AD$11:AD$87) * (E4='RISK BUDGETING (ETL)'!AF$11:AF$87), 0))} -> 4 | B4: Credit | C4: 0.71084487 | D4: 2.4810784 | E4: 2.6619446 | F4: -1.9510997 | H4: {=INDEX('RISK BUDGETING (ETL)'!P$11:P$87, MATCH(1, (I4='RISK BUDGETING (ETL)'!Q$11:Q$87) * (J4='RISK BUDGETING (ETL)'!AB$11:AB$87) * (K4='RISK BUDGETING (ETL)'!AD$11:AD$87) * (L4='RISK BUDGETING (ETL)'!AF$11:AF$87), 0))} -> 35 | I4: Aquatic: Aquatic - Nautilus CFM (Net) | J4: -0.59150315 | K4: 1.9869707 | L4: 2.1318173 | M4: -2.7233205
A5: {=INDEX('RISK BUDGETING (ETL)'!P$11:P$87, MATCH(1, (B5='RISK BUDGETING (ETL)'!Q$11:Q$87) * (C5='RISK BUDGETING (ETL)'!AB$11:AB$87) * (D5='RISK BUDGETING (ETL)'!AD$11:AD$87) * (E5='RISK BUDGETING (ETL)'!AF$11:AF$87), 0))} -> 12 | B5: Dockside | C5: 0.97744842 | D5: 1.6134786 | E5: 1.7310983 | F5: -0.75364993 | H5: {=INDEX('RISK BUDGETING (ETL)'!P$11:P$87, MATCH(1, (I5='RISK BUDGETING (ETL)'!Q$11:Q$87) * (J5='RISK BUDGETING (ETL)'!AB$11:AB$87) * (K5='RISK BUDGETING (ETL)'!AD$11:AD$87) * (L5='RISK BUDGETING (ETL)'!AF$11:AF$87), 0))} -> 44 | I5: Ares: Ares Pathfinder II | J5: 0.98209792 | K5: -0.51724379 | L5: -0.55494994 | M5: 1.5370479
A6: {=INDEX('RISK BUDGETING (ETL)'!P$11:P$87, MATCH(1, (B6='RISK BUDGETING (ETL)'!Q$11:Q$87) * (C6='RISK BUDGETING (ETL)'!AB$11:AB$87) * (D6='RISK BUDGETING (ETL)'!AD$11:AD$87) * (E6='RISK BUDGETING (ETL)'!AF$11:AF$87), 0))} -> 17 | B6: Equity Long Short | C6: 0.82495862 | D6: -0.068971375 | E6: -0.073999265 | F6: 0.89895788 | H6: {=INDEX('RISK BUDGETING (ETL)'!P$11:P$87, MATCH(1, (I6='RISK BUDGETING (ETL)'!Q$11:Q$87) * (J6='RISK BUDGETING (ETL)'!AB$11:AB$87) * (K6='RISK BUDGETING (ETL)'!AD$11:AD$87) * (L6='RISK BUDGETING (ETL)'!AF$11:AF$87), 0))} -> 36 | I6: Bayview Asset Management: MSR Fund | J6: 0.76373881 | K6: 0.50817708 | L6: 0.54522228 | M6: 0.21851653
A7: {=INDEX('RISK BUDGETING (ETL)'!P$11:P$87, MATCH(1, (B7='RISK BUDGETING (ETL)'!Q$11:Q$87) * (C7='RISK BUDGETING (ETL)'!AB$11:AB$87) * (D7='RISK BUDGETING (ETL)'!AD$11:AD$87) * (E7='RISK BUDGETING (ETL)'!AF$11:AF$87), 0))} -> 21 | B7: Global Macro | C7: 0.96297434 | D7: 2.1472414 | E7: 2.3037714 | F7: -1.3407971 | H7: {=INDEX('RISK BUDGETING (ETL)'!P$11:P$87, MATCH(1, (I7='RISK BUDGETING (ETL)'!Q$11:Q$87) * (J7='RISK BUDGETING (ETL)'!AB$11:AB$87) * (K7='RISK BUDGETING (ETL)'!AD$11:AD$87) * (L7='RISK BUDGETING (ETL)'!AF$11:AF$87), 0))} -> 5 | I7: Benefit Street Partners: Benefit Street Partners Origination Fund (CCFLX) | J7: 0.87289776 | K7: -0.48203513 | L7: -0.51717463 | M7: 1.3900724
A8: {=INDEX('RISK BUDGETING (ETL)'!P$11:P$87, MATCH(1, (B8='RISK BUDGETING (ETL)'!Q$11:Q$87) * (C8='RISK BUDGETING (ETL)'!AB$11:AB$87) * (D8='RISK BUDGETING (ETL)'!AD$11:AD$87) * (E8='RISK BUDGETING (ETL)'!AF$11:AF$87), 0))} -> 27 | B8: Multi Strategy | C8: 1.0985524 | D8: 0.13950148 | E8: 0.14967089 | F8: 0.94888151 | H8: {=INDEX('RISK BUDGETING (ETL)'!P$11:P$87, MATCH(1, (I8='RISK BUDGETING (ETL)'!Q$11:Q$87) * (J8='RISK BUDGETING (ETL)'!AB$11:AB$87) * (K8='RISK BUDGETING (ETL)'!AD$11:AD$87) * (L8='RISK BUDGETING (ETL)'!AF$11:AF$87), 0))} -> 37 | I8: BlackRock: GAO | J8: 1.2240246 | K8: 0.29927867 | L8: 0.32109555 | M8: 0.90292904
A9: {=INDEX('RISK BUDGETING (ETL)'!P$11:P$87, MATCH(1, (B9='RISK BUDGETING (ETL)'!Q$11:Q$87) * (C9='RISK BUDGETING (ETL)'!AB$11:AB$87) * (D9='RISK BUDGETING (ETL)'!AD$11:AD$87) * (E9='RISK BUDGETING (ETL)'!AF$11:AF$87), 0))} -> 34 | B9: Relative Value | C9: 0.82337777 | D9: 0.36659533 | E9: 0.39331948 | F9: 0.43005829 | H9: {=INDEX('RISK BUDGETING (ETL)'!P$11:P$87, MATCH(1, (I9='RISK BUDGETING (ETL)'!Q$11:Q$87) * (J9='RISK BUDGETING (ETL)'!AB$11:AB$87) * (K9='RISK BUDGETING (ETL)'!AD$11:AD$87) * (L9='RISK BUDGETING (ETL)'!AF$11:AF$87), 0))} -> 28 | I9: Blackstone: Badgerstone Access | J9: 0.90210472 | K9: -0.18409756 | L9: -0.19751794 | M9: 1.0996227
A10: {=INDEX('RISK BUDGETING (ETL)'!P$11:P$87, MATCH(1, (B10='RISK BUDGETING (ETL)'!Q$11:Q$87) * (C10='RISK BUDGETING (ETL)'!AB$11:AB$87) * (D10='RISK BUDGETING (ETL)'!AD$11:AD$87) * (E10='RISK BUDGETING (ETL)'!AF$11:AF$87), 0))} -> 43 | B10: Specialty Finance | C10: 0.91070065 | D10: 1.0372366 | E10: 1.1128493 | F10: -0.20214869 | H10: {=INDEX('RISK BUDGETING (ETL)'!P$11:P$87, MATCH(1, (I10='RISK BUDGETING (ETL)'!Q$11:Q$87) * (J10='RISK BUDGETING (ETL)'!AB$11:AB$87) * (K10='RISK BUDGETING (ETL)'!AD$11:AD$87) * (L10='RISK BUDGETING (ETL)'!AF$11:AF$87), 0))} -> 6 | I10: Blue Owl: Blue Owl Funding Partners (CCLFX) | J10: 0.84892915 | K10: -0.21583426 | L10: -0.23156819 | M10: 1.0804973
A11: {=INDEX('RISK BUDGETING (ETL)'!P$11:P$87, MATCH(1, (B11='RISK BUDGETING (ETL)'!Q$11:Q$87) * (C11='RISK BUDGETING (ETL)'!AB$11:AB$87) * (D11='RISK BUDGETING (ETL)'!AD$11:AD$87) * (E11='RISK BUDGETING (ETL)'!AF$11:AF$87), 0))} | H11: {=INDEX('RISK BUDGETING (ETL)'!P$11:P$87, MATCH(1, (I11='RISK BUDGETING (ETL)'!Q$11:Q$87) * (J11='RISK BUDGETING (ETL)'!AB$11:AB$87) * (K11='RISK BUDGETING (ETL)'!AD$11:AD$87) * (L11='RISK BUDGETING (ETL)'!AF$11:AF$87), 0))} -> 2 | I11: Brevan Howard Coinvests (Aksia): Brevan Howard Special Opportunities SPC | J11: 0.23526582 | K11: -0.48610383 | L11: -0.52153993 | M11: 0.75680575
A12: {=INDEX('RISK BUDGETING (ETL)'!P$11:P$87, MATCH(1, (B12='RISK BUDGETING (ETL)'!Q$11:Q$87) * (C12='RISK BUDGETING (ETL)'!AB$11:AB$87) * (D12='RISK BUDGETING (ETL)'!AD$11:AD$87) * (E12='RISK BUDGETING (ETL)'!AF$11:AF$87), 0))} | H12: {=INDEX('RISK BUDGETING (ETL)'!P$11:P$87, MATCH(1, (I12='RISK BUDGETING (ETL)'!Q$11:Q$87) * (J12='RISK BUDGETING (ETL)'!AB$11:AB$87) * (K12='RISK BUDGETING (ETL)'!AD$11:AD$87) * (L12='RISK BUDGETING (ETL)'!AF$11:AF$87), 0))} -> 22 | I12: Brevan Howard MB Macro Fund: Brevan Howard MB Macro Fund with proforma | J12: 0.89036567 | K12: -0.60281092 | L12: -0.64675475 | M12: 1.5371204
A13: {=INDEX('RISK BUDGETING (ETL)'!P$11:P$87, MATCH(1, (B13='RISK BUDGETING (ETL)'!Q$11:Q$87) * (C13='RISK BUDGETING (ETL)'!AB$11:AB$87) * (D13='RISK BUDGETING (ETL)'!AD$11:AD$87) * (E13='RISK BUDGETING (ETL)'!AF$11:AF$87), 0))} | H13: {=INDEX('RISK BUDGETING (ETL)'!P$11:P$87, MATCH(1, (I13='RISK BUDGETING (ETL)'!Q$11:Q$87) * (J13='RISK BUDGETING (ETL)'!AB$11:AB$87) * (K13='RISK BUDGETING (ETL)'!AD$11:AD$87) * (L13='RISK BUDGETING (ETL)'!AF$11:AF$87), 0))} -> 29 | I13: D. E. Shaw: Cogence | J13: 1.7007494 | K13: 2.2178291 | L13: 2.3795049 | M13: -0.67875552
A14: {=INDEX('RISK BUDGETING (ETL)'!P$11:P$87, MATCH(1, (B14='RISK BUDGETING (ETL)'!Q$11:Q$87) * (C14='RISK BUDGETING (ETL)'!AB$11:AB$87) * (D14='RISK BUDGETING (ETL)'!AD$11:AD$87) * (E14='RISK BUDGETING (ETL)'!AF$11:AF$87), 0))} | H14: {=INDEX('RISK BUDGETING (ETL)'!P$11:P$87, MATCH(1, (I14='RISK BUDGETING (ETL)'!Q$11:Q$87) * (J14='RISK BUDGETING (ETL)'!AB$11:AB$87) * (K14='RISK BUDGETING (ETL)'!AD$11:AD$87) * (L14='RISK BUDGETING (ETL)'!AF$11:AF$87), 0))} -> 30 | I14: DE Shaw Composite Fund LLC: DE Shaw Composite Fund LLC | J14: 1.4252162 | K14: -0.65923583 | L14: -0.70729294 | M14: 2.1325092
A15: {=INDEX('RISK BUDGETING (ETL)'!P$11:P$87, MATCH(1, (B15='RISK BUDGETING (ETL)'!Q$11:Q$87) * (C15='RISK BUDGETING (ETL)'!AB$11:AB$87) * (D15='RISK BUDGETING (ETL)'!AD$11:AD$87) * (E15='RISK BUDGETING (ETL)'!AF$11:AF$87), 0))} | H15: {=INDEX('RISK BUDGETING (ETL)'!P$11:P$87, MATCH(1, (I15='RISK BUDGETING (ETL)'!Q$11:Q$87) * (J15='RISK BUDGETING (ETL)'!AB$11:AB$87) * (K15='RISK BUDGETING (ETL)'!AD$11:AD$87) * (L15='RISK BUDGETING (ETL)'!AF$11:AF$87), 0))} -> 31 | I15: DYAL: DYAL II - Aksia | J15: 1.2936614 | K15: -2.2648796 | L15: -2.4299853 | M15: 3.7236467
A16: {=INDEX('RISK BUDGETING (ETL)'!P$11:P$87, MATCH(1, (B16='RISK BUDGETING (ETL)'!Q$11:Q$87) * (C16='RISK BUDGETING (ETL)'!AB$11:AB$87) * (D16='RISK BUDGETING (ETL)'!AD$11:AD$87) * (E16='RISK BUDGETING (ETL)'!AF$11:AF$87), 0))} | H16: {=INDEX('RISK BUDGETING (ETL)'!P$11:P$87, MATCH(1, (I16='RISK BUDGETING (ETL)'!Q$11:Q$87) * (J16='RISK BUDGETING (ETL)'!AB$11:AB$87) * (K16='RISK BUDGETING (ETL)'!AD$11:AD$87) * (L16='RISK BUDGETING (ETL)'!AF$11:AF$87), 0))} -> 14 | I16: Dockside: I-94 Minus Standalones | J16: 1.0463513 | K16: 2.4134516 | L16: 2.5893879 | M16: -1.5430366
A17: {=INDEX('RISK BUDGETING (ETL)'!P$11:P$87, MATCH(1, (B17='RISK BUDGETING (ETL)'!Q$11:Q$87) * (C17='RISK BUDGETING (ETL)'!AB$11:AB$87) * (D17='RISK BUDGETING (ETL)'!AD$11:AD$87) * (E17='RISK BUDGETING (ETL)'!AF$11:AF$87), 0))} | H17: {=INDEX('RISK BUDGETING (ETL)'!P$11:P$87, MATCH(1, (I17='RISK BUDGETING (ETL)'!Q$11:Q$87) * (J17='RISK BUDGETING (ETL)'!AB$11:AB$87) * (K17='RISK BUDGETING (ETL)'!AD$11:AD$87) * (L17='RISK BUDGETING (ETL)'!AF$11:AF$87), 0))} -> 15 | I17: Dorsal Capital Partners LP: Dorsal Capital Partners LP | J17: 0.57425515 | K17: 0.83931385 | L17: 0.90049833 | M17: -0.32624318
A18: {=INDEX('RISK BUDGETING (ETL)'!P$11:P$87, MATCH(1, (B18='RISK BUDGETING (ETL)'!Q$11:Q$87) * (C18='RISK BUDGETING (ETL)'!AB$11:AB$87) * (D18='RISK BUDGETING (ETL)'!AD$11:AD$87) * (E18='RISK BUDGETING (ETL)'!AF$11:AF$87), 0))} | H18: {=INDEX('RISK BUDGETING (ETL)'!P$11:P$87, MATCH(1, (I18='RISK BUDGETING (ETL)'!Q$11:Q$87) * (J18='RISK BUDGETING (ETL)'!AB$11:AB$87) * (K18='RISK BUDGETING (ETL)'!AD$11:AD$87) * (L18='RISK BUDGETING (ETL)'!AF$11:AF$87), 0))} -> 32 | I18: Elliott Associates LP: Elliott Associates LP | J18: 0.71204297 | K18: 0.16092826 | L18: 0.17265964 | M18: 0.53938333
A19: {=INDEX('RISK BUDGETING (ETL)'!P$11:P$87, MATCH(1, (B19='RISK BUDGETING (ETL)'!Q$11:Q$87) * (C19='RISK BUDGETING (ETL)'!AB$11:AB$87) * (D19='RISK BUDGETING (ETL)'!AD$11:AD$87) * (E19='RISK BUDGETING (ETL)'!AF$11:AF$87), 0))} | H19: {=INDEX('RISK BUDGETING (ETL)'!P$11:P$87, MATCH(1, (I19='RISK BUDGETING (ETL)'!Q$11:Q$87) * (J19='RISK BUDGETING (ETL)'!AB$11:AB$87) * (K19='RISK BUDGETING (ETL)'!AD$11:AD$87) * (L19='RISK BUDGETING (ETL)'!AF$11:AF$87), 0))} -> 18 | I19: Four World: FWGO | J19: 0.86964862 | K19: 0.054908594 | L19: 0.058911332 | M19: 0.81073729
A20: {=INDEX('RISK BUDGETING (ETL)'!P$11:P$87, MATCH(1, (B20='RISK BUDGETING (ETL)'!Q$11:Q$87) * (C20='RISK BUDGETING (ETL)'!AB$11:AB$87) * (D20='RISK BUDGETING (ETL)'!AD$11:AD$87) * (E20='RISK BUDGETING (ETL)'!AF$11:AF$87), 0))} | H20: {=INDEX('RISK BUDGETING (ETL)'!P$11:P$87, MATCH(1, (I20='RISK BUDGETING (ETL)'!Q$11:Q$87) * (J20='RISK BUDGETING (ETL)'!AB$11:AB$87) * (K20='RISK BUDGETING (ETL)'!AD$11:AD$87) * (L20='RISK BUDGETING (ETL)'!AF$11:AF$87), 0))} -> 19 | I20: Four World: FWGO Minority Descent | J20: 0.6302408 | K20: 0.87795682 | L20: 0.9419583 | M20: -0.3117175
A21: {=INDEX('RISK BUDGETING (ETL)'!P$11:P$87, MATCH(1, (B21='RISK BUDGETING (ETL)'!Q$11:Q$87) * (C21='RISK BUDGETING (ETL)'!AB$11:AB$87) * (D21='RISK BUDGETING (ETL)'!AD$11:AD$87) * (E21='RISK BUDGETING (ETL)'!AF$11:AF$87), 0))} | H21: {=INDEX('RISK BUDGETING (ETL)'!P$11:P$87, MATCH(1, (I21='RISK BUDGETING (ETL)'!Q$11:Q$87) * (J21='RISK BUDGETING (ETL)'!AB$11:AB$87) * (K21='RISK BUDGETING (ETL)'!AD$11:AD$87) * (L21='RISK BUDGETING (ETL)'!AF$11:AF$87), 0))} -> 23 | I21: Graham Absolute Return Ltd: Graham Absolute Return Ltd | J21: 0.73676293 | K21: 3.684631 | L21: 3.953234 | M21: -3.2164711
A22: {=INDEX('RISK BUDGETING (ETL)'!P$11:P$87, MATCH(1, (B22='RISK BUDGETING (ETL)'!Q$11:Q$87) * (C22='RISK BUDGETING (ETL)'!AB$11:AB$87) * (D22='RISK BUDGETING (ETL)'!AD$11:AD$87) * (E22='RISK BUDGETING (ETL)'!AF$11:AF$87), 0))} | H22: {=INDEX('RISK BUDGETING (ETL)'!P$11:P$87, MATCH(1, (I22='RISK BUDGETING (ETL)'!Q$11:Q$87) * (J22='RISK BUDGETING (ETL)'!AB$11:AB$87) * (K22='RISK BUDGETING (ETL)'!AD$11:AD$87) * (L22='RISK BUDGETING (ETL)'!AF$11:AF$87), 0))} -> 3 | I22: HF: Current Coinvests (Excluding BH Coinvests) | J22: 0.64839132 | K22: 1.2850481 | L22: 1.3787258 | M22: -0.73033453
... A33: {=INDEX('RISK BUDGETING (ETL)'!P$11:P$87, MATCH(1, (B33='RISK BUDGETING (ETL)'!Q$11:Q$87) * (C33='RISK BUDGETING (ETL)'!AB$11:AB$87) * (D33='RISK BUDGETING (ETL)'!AD$11:AD$87) * (E33='RISK BUDGETING (ETL)'!AF$11:AF$87), 0))} | H33: {=INDEX('RISK BUDGETING (ETL)'!P$11:P$87, MATCH(1, (I33='RISK BUDGETING (ETL)'!Q$11:Q$87) * (J33='RISK BUDGETING (ETL)'!AB$11:AB$87) * (K33='RISK BUDGETING (ETL)'!AD$11:AD$87) * (L33='RISK BUDGETING (ETL)'!AF$11:AF$87), 0))} -> 26 | I33: Rokos Global Macro Fund LP: Rokos Global Macro Fund LP | J33: 1.389199 | K33: 2.1110885 | L33: 2.2649831 | M33: -0.87578407
H34: {=INDEX('RISK BUDGETING (ETL)'!P$11:P$87, MATCH(1, (I34='RISK BUDGETING (ETL)'!Q$11:Q$87) * (J34='RISK BUDGETING (ETL)'!AB$11:AB$87) * (K34='RISK BUDGETING (ETL)'!AD$11:AD$87) * (L34='RISK BUDGETING (ETL)'!AF$11:AF$87), 0))} -> 16 | I34: Saba: CEF1 MN - 2.75x | J34: 1.3756037 | K34: 3.3337494 | L34: 3.5767738 | M34: -2.20117
H35: {=INDEX('RISK BUDGETING (ETL)'!P$11:P$87, MATCH(1, (I35='RISK BUDGETING (ETL)'!Q$11:Q$87) * (J35='RISK BUDGETING (ETL)'!AB$11:AB$87) * (K35='RISK BUDGETING (ETL)'!AD$11:AD$87) * (L35='RISK BUDGETING (ETL)'!AF$11:AF$87), 0))} -> 10 | I35: Silver Point Capital Fund II LP: Silver Point Capital Fund II LP | J35: 1.5690665 | K35: 0.14919505 | L35: 0.16007111 | M35: 1.4089953
H36: {=INDEX('RISK BUDGETING (ETL)'!P$11:P$87, MATCH(1, (I36='RISK BUDGETING (ETL)'!Q$11:Q$87) * (J36='RISK BUDGETING (ETL)'!AB$11:AB$87) * (K36='RISK BUDGETING (ETL)'!AD$11:AD$87) * (L36='RISK BUDGETING (ETL)'!AF$11:AF$87), 0))} -> 11 | I36: Silver Point Capital: Silver Point Distressed Opportunity Institutional Partners + Silver Point HF | J36: 1.1693907 | K36: 8.5089926 | L36: 9.1292829 | M36: -7.9598922
H37: {=INDEX('RISK BUDGETING (ETL)'!P$11:P$87, MATCH(1, (I37='RISK BUDGETING (ETL)'!Q$11:Q$87) * (J37='RISK BUDGETING (ETL)'!AB$11:AB$87) * (K37='RISK BUDGETING (ETL)'!AD$11:AD$87) * (L37='RISK BUDGETING (ETL)'!AF$11:AF$87), 0))} -> 41 | I37: Taula: SWIB-DM Taula | J37: 1.222481 | K37: -0.21440135 | L37: -0.23003082 | M37: 1.4525118
H38: {=INDEX('RISK BUDGETING (ETL)'!P$11:P$87, MATCH(1, (I38='RISK BUDGETING (ETL)'!Q$11:Q$87) * (J38='RISK BUDGETING (ETL)'!AB$11:AB$87) * (K38='RISK BUDGETING (ETL)'!AD$11:AD$87) * (L38='RISK BUDGETING (ETL)'!AF$11:AF$87), 0))} -> 42 | I38: Voleon Composition Domestic Fund LP: Voleon Composition Domestic Fund LP | J38: 0.7580382 | K38: 1.1825809 | L38: 1.268789 | M38: -0.51075076
H39: {=INDEX('RISK BUDGETING (ETL)'!P$11:P$87, MATCH(1, (I39='RISK BUDGETING (ETL)'!Q$11:Q$87) * (J39='RISK BUDGETING (ETL)'!AB$11:AB$87) * (K39='RISK BUDGETING (ETL)'!AD$11:AD$87) * (L39='RISK BUDGETING (ETL)'!AF$11:AF$87), 0))} -> 33 | I39: Walleye: Walleye Opportunities Fund | J39: 0.94527756 | K39: 2.7799233 | L39: 2.9825747 | M39: -2.0372972
H40: {=INDEX('RISK BUDGETING (ETL)'!P$11:P$87, MATCH(1, (I40='RISK BUDGETING (ETL)'!Q$11:Q$87) * (J40='RISK BUDGETING (ETL)'!AB$11:AB$87) * (K40='RISK BUDGETING (ETL)'!AD$11:AD$87) * (L40='RISK BUDGETING (ETL)'!AF$11:AF$87), 0))}
H41: {=INDEX('RISK BUDGETING (ETL)'!P$11:P$87, MATCH(1, (I41='RISK BUDGETING (ETL)'!Q$11:Q$87) * (J41='RISK BUDGETING (ETL)'!AB$11:AB$87) * (K41='RISK BUDGETING (ETL)'!AD$11:AD$87) * (L41='RISK BUDGETING (ETL)'!AF$11:AF$87), 0))}
H42: {=INDEX('RISK BUDGETING (ETL)'!P$11:P$87, MATCH(1, (I42='RISK BUDGETING (ETL)'!Q$11:Q$87) * (J42='RISK BUDGETING (ETL)'!AB$11:AB$87) * (K42='RISK BUDGETING (ETL)'!AD$11:AD$87) * (L42='RISK BUDGETING (ETL)'!AF$11:AF$87), 0))}
H43: {=INDEX('RISK BUDGETING (ETL)'!P$11:P$87, MATCH(1, (I43='RISK BUDGETING (ETL)'!Q$11:Q$87) * (J43='RISK BUDGETING (ETL)'!AB$11:AB$87) * (K43='RISK BUDGETING (ETL)'!AD$11:AD$87) * (L43='RISK BUDGETING (ETL)'!AF$11:AF$87), 0))}
H44: {=INDEX('RISK BUDGETING (ETL)'!P$11:P$87, MATCH(1, (I44='RISK BUDGETING (ETL)'!Q$11:Q$87) * (J44='RISK BUDGETING (ETL)'!AB$11:AB$87) * (K44='RISK BUDGETING (ETL)'!AD$11:AD$87) * (L44='RISK BUDGETING (ETL)'!AF$11:AF$87), 0))}
H45: {=INDEX('RISK BUDGETING (ETL)'!P$11:P$87, MATCH(1, (I45='RISK BUDGETING (ETL)'!Q$11:Q$87) * (J45='RISK BUDGETING (ETL)'!AB$11:AB$87) * (K45='RISK BUDGETING (ETL)'!AD$11:AD$87) * (L45='RISK BUDGETING (ETL)'!AF$11:AF$87), 0))}
H46: {=INDEX('RISK BUDGETING (ETL)'!P$11:P$87, MATCH(1, (I46='RISK BUDGETING (ETL)'!Q$11:Q$87) * (J46='RISK BUDGETING (ETL)'!AB$11:AB$87) * (K46='RISK BUDGETING (ETL)'!AD$11:AD$87) * (L46='RISK BUDGETING (ETL)'!AF$11:AF$87), 0))}
H47: {=INDEX('RISK BUDGETING (ETL)'!P$11:P$87, MATCH(1, (I47='RISK BUDGETING (ETL)'!Q$11:Q$87) * (J47='RISK BUDGETING (ETL)'!AB$11:AB$87) * (K47='RISK BUDGETING (ETL)'!AD$11:AD$87) * (L47='RISK BUDGETING (ETL)'!AF$11:AF$87), 0))}
H48: {=INDEX('RISK BUDGETING (ETL)'!P$11:P$87, MATCH(1, (I48='RISK BUDGETING (ETL)'!Q$11:Q$87) * (J48='RISK BUDGETING (ETL)'!AB$11:AB$87) * (K48='RISK BUDGETING (ETL)'!AD$11:AD$87) * (L48='RISK BUDGETING (ETL)'!AF$11:AF$87), 0))}
H49: {=INDEX('RISK BUDGETING (ETL)'!P$11:P$87, MATCH(1, (I49='RISK BUDGETING (ETL)'!Q$11:Q$87) * (J49='RISK BUDGETING (ETL)'!AB$11:AB$87) * (K49='RISK BUDGETING (ETL)'!AD$11:AD$87) * (L49='RISK BUDGETING (ETL)'!AF$11:AF$87), 0))}
H50: {=INDEX('RISK BUDGETING (ETL)'!P$11:P$87, MATCH(1, (I50='RISK BUDGETING (ETL)'!Q$11:Q$87) * (J50='RISK BUDGETING (ETL)'!AB$11:AB$87) * (K50='RISK BUDGETING (ETL)'!AD$11:AD$87) * (L50='RISK BUDGETING (ETL)'!AF$11:AF$87), 0))}
H51: {=INDEX('RISK BUDGETING (ETL)'!P$11:P$87, MATCH(1, (I51='RISK BUDGETING (ETL)'!Q$11:Q$87) * (J51='RISK BUDGETING (ETL)'!AB$11:AB$87) * (K51='RISK BUDGETING (ETL)'!AD$11:AD$87) * (L51='RISK BUDGETING (ETL)'!AF$11:AF$87), 0))}
... H103: {=INDEX('RISK BUDGETING (ETL)'!P$11:P$87, MATCH(1, (I103='RISK BUDGETING (ETL)'!Q$11:Q$87) * (J103='RISK BUDGETING (ETL)'!AB$11:AB$87) * (K103='RISK BUDGETING (ETL)'!AD$11:AD$87) * (L103='RISK BUDGETING (ETL)'!AF$11:AF$87), 0))}

Sheet RISK BUDGETING (StDev)
A4: RISK BUDGETING (StDev)
A5: Implied Return (IR) is the required return of the asset to justify its contribution to the portfolio risk assuming that the current portfolio has optimal performance ratio. To improve the risk-adjusted performance of the portfolio one should consider increasing the weights of the assets with IRs lower that the expected returns of those assets and lowering those with IRs higher than their expected retuns.
Z9: Weight (%) | AB9: Mean | AD9: MC to StDev | AF9: Implied Return (StDev) | AH9: Difference
Q10: Current 7.26 | Z10: 100 | AB10: 0.9376494
P11: =IF(ISBLANK(Q11)=TRUE,"",1) -> 1 | Q11: Coinvests | Z11: 2.1508199 | AB11: 0.5269658 | AD11: 0.62705206 | AF11: 0.78294268 | AH11: -0.25597687
P12: =IF(ISBLANK(Q12)=TRUE,"",2) -> 2 | Q12: Brevan Howard Coinvests (Aksia): Brevan Howard Special Opportunities SPC | Z12: 0.63216727 | AB12: 0.23526582 | AD12: 0.18108481 | AF12: 0.22610408 | AH12: 0.0091617409
P13: =IF(ISBLANK(Q13)=TRUE,"",3) -> 3 | Q13: HF: Current Coinvests (Excluding BH Coinvests) | Z13: 1.5186526 | AB13: 0.64839132 | AD13: 0.81269418 | AF13: 1.0147371 | AH13: -0.36634573
P14: =IF(ISBLANK(Q14)=TRUE,"",4) -> 4 | Q14: Credit | Z14: 6.6920936 | AB14: 0.71084487 | AD14: 1.1300131 | AF14: 1.4109442 | AH14: -0.70009935
P15: =IF(ISBLANK(Q15)=TRUE,"",5) -> 5 | Q15: Benefit Street Partners: Benefit Street Partners Origination Fund (CCFLX) | Z15: 0.074708538 | AB15: 0.87289776 | AD15: 0.14432684 | AF15: 0.18020775 | AH15: 0.69269001
P16: =IF(ISBLANK(Q16)=TRUE,"",6) -> 6 | Q16: Blue Owl: Blue Owl Funding Partners (CCLFX) | Z16: 0.31241515 | AB16: 0.84892915 | AD16: 0.27266888 | AF16: 0.34045675 | AH16: 0.5084724
P17: =IF(ISBLANK(Q17)=TRUE,"",7) -> 7 | Q17: King Street Capital LP: King Street Capital LP | Z17: 0.061233379 | AB17: -0.070365046 | AD17: 0.65353361 | AF17: 0.81600778 | AH17: -0.88637283
P18: =IF(ISBLANK(Q18)=TRUE,"",8) -> 8 | Q18: LibreMax CLO: LibreMax CLO | Z18: 2.0217776 | AB18: 0.34156768 | AD18: -0.13901257 | AF18: -0.17357231 | AH18: 0.51513999
P19: =IF(ISBLANK(Q19)=TRUE,"",9) -> 9 | Q19: LibreMax Partners LP: LibreMax Partners LP | Z19: 2.4519223 | AB19: 0.51903774 | AD19: 1.7618599 | AF19: 2.1998737 | AH19: -1.680836
P20: =IF(ISBLANK(Q20)=TRUE,"",10) -> 10 | Q20: Silver Point Capital Fund II LP: Silver Point Capital Fund II LP | Z20: 0.99540528 | AB20: 1.5690665 | AD20: 0.83188046 | AF20: 1.0386932 | AH20: 0.53037324
P21: =IF(ISBLANK(Q21)=TRUE,"",11) -> 11 | Q21: Silver Point Capital: Silver Point Distressed Opportunity Institutional Partners + Silver Point HF | Z21: 0.77463136 | AB21: 1.1693907 | AD21: 3.3037878 | AF21: 4.1251383 | AH21: -2.9557476
P22: =IF(ISBLANK(Q22)=TRUE,"",12) -> 12 | Q22: Dockside | Z22: 13.589956 | AB22: 0.97744842 | AD22: 1.0891745 | AF22: 1.3599528 | AH22: -0.38250443
P23: =IF(ISBLANK(Q23)=TRUE,"",13) -> 13 | Q23: 12267: Trexquant Onshore Fund LP | Z23: 3.1198357 | AB23: 1.070413 | AD23: 0.57713167 | AF23: 0.72061165 | AH23: 0.34980132
P24: =IF(ISBLANK(Q24)=TRUE,"",14) -> 14 | Q24: Dockside: I-94 Minus Standalones | Z24: 6.254264 | AB24: 1.0463513 | AD24: 1.4867382 | AF24: 1.8563543 | AH24: -0.81000294
P25: =IF(ISBLANK(Q25)=TRUE,"",15) -> 15 | Q25: Dorsal Capital Partners LP: Dorsal Capital Partners LP | Z25: 2.9943734 | AB25: 0.57425515 | AD25: 0.58178342 | AF25: 0.72641986 | AH25: -0.15216471
P26: =IF(ISBLANK(Q26)=TRUE,"",16) -> 16 | Q26: Saba: CEF1 MN - 2.75x | Z26: 1.2214834 | AB26: 1.3756037 | AD26: 1.6052194 | AF26: 2.004291 | AH26: -0.62868729
P27: =IF(ISBLANK(Q27)=TRUE,"",17) -> 17 | Q27: Equity Long Short | Z27: 8.6928088 | AB27: 0.82495862 | AD27: 0.3454518 | AF27: 0.43133414 | AH27: 0.39362448
P28: =IF(ISBLANK(Q28)=TRUE,"",18) -> 18 | Q28: Four World: FWGO | Z28: 2.1319734 | AB28: 0.86964862 | AD28: 0.42812486 | AF28: 0.53456045 | AH28: 0.33508818
P29: =IF(ISBLANK(Q29)=TRUE,"",19) -> 19 | Q29: Four World: FWGO Minority Descent | Z29: 1.7445328 | AB29: 0.6302408 | AD29: 0.4670845 | AF29: 0.58320579 | AH29: 0.047035018
P30: =IF(ISBLANK(Q30)=TRUE,"",20) -> 20 | Q30: Holocene: Holocene Advisors Master | Z30: 4.8163025 | AB30: 0.87570579 | AD30: 0.26479886 | AF30: 0.33063016 | AH30: 0.54507562
P31: =IF(ISBLANK(Q31)=TRUE,"",21) -> 21 | Q31: Global Macro | Z31: 14.563052 | AB31: 0.96297434 | AD31: 1.1537179 | AF31: 1.4405423 | AH31: -0.47756792
P32: =IF(ISBLANK(Q32)=TRUE,"",22) -> 22 | Q32: Brevan Howard MB Macro Fund: Brevan Howard MB Macro Fund with proforma | Z32: 2.6002026 | AB32: 0.89036567 | AD32: 0.26451556 | AF32: 0.33027644 | AH32: 0.56008923
P33: =IF(ISBLANK(Q33)=TRUE,"",23) -> 23 | Q33: Graham Absolute Return Ltd: Graham Absolute Return Ltd | Z33: 2.953922 | AB33: 0.73676293 | AD33: 1.6418692 | AF33: 2.0500523 | AH33: -1.3132893
P34: =IF(ISBLANK(Q34)=TRUE,"",24) -> 24 | Q34: Mesarete: Prior TR+back with Pharo Macro+Mesarete Capital Fund | Z34: 2.6503264 | AB34: 0.5603043 | AD34: 1.1640466 | AF34: 1.4534388 | AH34: -0.89313445
P35: =IF(ISBLANK(Q35)=TRUE,"",25) -> 25 | Q35: PIMCO: PIMCO Commodity Alpha Fund | Z35: 0.86866099 | AB35: 0.48438409 | AD35: 1.3853514 | AF35: 1.7297618 | AH35: -1.2453777
P36: =IF(ISBLANK(Q36)=TRUE,"",26) -> 26 | Q36: Rokos Global Macro Fund LP: Rokos Global Macro Fund LP | Z36: 5.4899402 | AB36: 1.389199 | AD36: 1.2705789 | AF36: 1.5864559 | AH36: -0.19725695
P37: =IF(ISBLANK(Q37)=TRUE,"",27) -> 27 | Q37: Multi Strategy | Z37: 29.910414 | AB37: 1.0985524 | AD37: 0.58772091 | AF37: 0.73383347 | AH37: 0.36471894
P38: =IF(ISBLANK(Q38)=TRUE,"",28) -> 28 | Q38: Blackstone: Badgerstone Access | Z38: 5.0884559 | AB38: 0.90210472 | AD38: 0.41263938 | AF38: 0.51522514 | AH38: 0.38687958
P39: =IF(ISBLANK(Q39)=TRUE,"",29) -> 29 | Q39: D. E. Shaw: Cogence | Z39: 1.9781362 | AB39: 1.7007494 | AD39: 1.3654622 | AF39: 1.704928 | AH39: -0.0041786509
P40: =IF(ISBLANK(Q40)=TRUE,"",30) -> 30 | Q40: DE Shaw Composite Fund LLC: DE Shaw Composite Fund LLC | Z40: 9.3802815 | AB40: 1.4252162 | AD40: 0.44421708 | AF40: 0.55465333 | AH40: 0.87056291
P41: =IF(ISBLANK(Q41)=TRUE,"",31) -> 31 | Q41: DYAL: DYAL II - Aksia | Z41: 1.9130169 | AB41: 1.2936614 | AD41: 0.20032401 | AF41: 0.2501263 | AH41: 1.043535
P42: =IF(ISBLANK(Q42)=TRUE,"",32) -> 32 | Q42: Elliott Associates LP: Elliott Associates LP | Z42: 7.9690284 | AB42: 0.71204297 | AD42: 0.33876465 | AF42: 0.4229845 | AH42: 0.28905847
P43: =IF(ISBLANK(Q43)=TRUE,"",33) -> 33 | Q43: Walleye: Walleye Opportunities Fund | Z43: 3.5814946 | AB43: 0.94527756 | AD43: 1.5436233 | AF43: 1.9273816 | AH43: -0.982104
P44: =IF(ISBLANK(Q44)=TRUE,"",34) -> 34 | Q44: Relative Value | Z44: 19.285614 | AB44: 0.82337777 | AD44: 0.52088268 | AF44: 0.65037867 | AH44: 0.1729991
P45: =IF(ISBLANK(Q45)=TRUE,"",35) -> 35 | Q45: Aquatic: Aquatic - Nautilus CFM (Net) | Z45: 0.38382851 | AB45: -0.59150315 | AD45: 0.67609513 | AF45: 0.84417829 | AH45: -1.4356814
F46: • Implied Return (St.Dev.) • Mean Return (%) | P46: =IF(ISBLANK(Q46)=TRUE,"",36) -> 36 | Q46: Bayview Asset Management: MSR Fund | Z46: 2.2527339 | AB46: 0.76373881 | AD46: 0.43620113 | AF46: 0.54464454 | AH46: 0.21909428
P47: =IF(ISBLANK(Q47)=TRUE,"",37) -> 37 | Q47: BlackRock: GAO | Z47: 2.3161392 | AB47: 1.2240246 | AD47: 0.81853225 | AF47: 1.0220265 | AH47: 0.20199807
P48: =IF(ISBLANK(Q48)=TRUE,"",38) -> 38 | Q48: Hudson Structured: HSCM w MFC | Z48: 0.70577308 | AB48: 0.096190573 | AD48: 0.26970978 | AF48: 0.33676199 | AH48: -0.24057142
P49: =IF(ISBLANK(Q49)=TRUE,"",39) -> 39 | Q49: PIMCO Global Credit Opportunity Onshore Fund LLC: PIMCO Global Credit Opportunity Onshore Fund LLC | Z49: 3.7762459 | AB49: 0.8145471 | AD49: 0.52597056 | AF49: 0.65673143 | AH49: 0.15781567
P50: =IF(ISBLANK(Q50)=TRUE,"",40) -> 40 | Q50: Reflow Full Track: ReFlow LO Excess Plus Market Neutral | Z50: 2.4542568 | AB50: 0.47235154 | AD50: 0.082224699 | AF50: 0.10266648 | AH50: 0.36968506
P51: =IF(ISBLANK(Q51)=TRUE,"",41) -> 41 | Q51: Taula: SWIB-DM Taula | Z51: 3.5329348 | AB51: 1.222481 | AD51: 0.40116845 | AF51: 0.50090244 | AH51: 0.72157854
P52: =IF(ISBLANK(Q52)=TRUE,"",42) -> 42 | Q52: Voleon Composition Domestic Fund LP: Voleon Composition Domestic Fund LP | Z52: 3.8637021 | AB52: 0.7580382 | AD52: 0.8054212 | AF52: 1.0056559 | AH52: -0.24761774
P53: =IF(ISBLANK(Q53)=TRUE,"",43) -> 43 | Q53: Specialty Finance | Z53: 5.1152413 | AB53: 0.91070065 | AD53: 0.77293544 | AF53: 0.96509394 | AH53: -0.054393291
P54: =IF(ISBLANK(Q54)=TRUE,"",44) -> 44 | Q54: Ares: Ares Pathfinder II | Z54: 1.6485661 | AB54: 0.98209792 | AD54: 0.31635738 | AF54: 0.39500658 | AH54: 0.58709133
P55: =IF(ISBLANK(Q55)=TRUE,"",45) -> 45 | Q55: HF: Current Specialty Finance (Excluding Pathfinder) | Z55: 3.4666752 | AB55: 0.87674791 | AD55: 0.99005965 | AF55: 1.2361971 | AH55: -0.35944922
P56: =IF(ISBLANK(Q56)=TRUE,"",46)
P57: =IF(ISBLANK(Q57)=TRUE,"",47)
P58: =IF(ISBLANK(Q58)=TRUE,"",48)
P59: =IF(ISBLANK(Q59)=TRUE,"",49)
P60: =IF(ISBLANK(Q60)=TRUE,"",50)
P61: =IF(ISBLANK(Q61)=TRUE,"",51)
P62: =IF(ISBLANK(Q62)=TRUE,"",52)
P63: =IF(ISBLANK(Q63)=TRUE,"",53)
P64: =IF(ISBLANK(Q64)=TRUE,"",54)
P65: =IF(ISBLANK(Q65)=TRUE,"",55)
P66: =IF(ISBLANK(Q66)=TRUE,"",56)
P67: =IF(ISBLANK(Q67)=TRUE,"",57)
P68: =IF(ISBLANK(Q68)=TRUE,"",58)
P69: =IF(ISBLANK(Q69)=TRUE,"",59)
P70: =IF(ISBLANK(Q70)=TRUE,"",60)
P71: =IF(ISBLANK(Q71)=TRUE,"",61)
P72: =IF(ISBLANK(Q72)=TRUE,"",62)
P73: =IF(ISBLANK(Q73)=TRUE,"",63)
P74: =IF(ISBLANK(Q74)=TRUE,"",64)
P75: =IF(ISBLANK(Q75)=TRUE,"",65)
P76: =IF(ISBLANK(Q76)=TRUE,"",66)
P77: =IF(ISBLANK(Q77)=TRUE,"",67)
P78: =IF(ISBLANK(Q78)=TRUE,"",68)
P79: =IF(ISBLANK(Q79)=TRUE,"",69)
P80: =IF(ISBLANK(Q80)=TRUE,"",70)
P81: =IF(ISBLANK(Q81)=TRUE,"",71)
P82: =IF(ISBLANK(Q82)=TRUE,"",72)
P83: =IF(ISBLANK(Q83)=TRUE,"",73)

Sheet RB_STDEV
B1: Portfolio/Groups | C1: Mean | D1: MC to ETL | E1: Impl.Return | F1: diff | I1: Assets | J1: Mean | K1: MC to ETL | L1: Impl.Return | M1: diff
B2: Current 7.26 | C2: 0.9376494 | I2: Current 7.26 | J2: 0.9376494
A3: {=INDEX('RISK BUDGETING (StDev)'!P$11:P$87, MATCH(1, (B3='RISK BUDGETING (StDev)'!Q$11:Q$87) * (C3='RISK BUDGETING (StDev)'!AB$11:AB$87) * (D3='RISK BUDGETING (StDev)'!AD$11:AD$87) * (E3='RISK BUDGETING (StDev)'!AF$11:AF$87), 0))} -> 1 | B3: Coinvests | C3: 0.5269658 | D3: 0.62705206 | E3: 0.78294268 | F3: -0.25597687 | H3: {=INDEX('RISK BUDGETING (StDev)'!P$11:P$87, MATCH(1, (I3='RISK BUDGETING (StDev)'!Q$11:Q$87) * (J3='RISK BUDGETING (StDev)'!AB$11:AB$87) * (K3='RISK BUDGETING (StDev)'!AD$11:AD$87) * (L3='RISK BUDGETING (StDev)'!AF$11:AF$87), 0))} -> 13 | I3: 12267: Trexquant Onshore Fund LP | J3: 1.070413 | K3: 0.57713167 | L3: 0.72061165 | M3: 0.34980132
A4: {=INDEX('RISK BUDGETING (StDev)'!P$11:P$87, MATCH(1, (B4='RISK BUDGETING (StDev)'!Q$11:Q$87) * (C4='RISK BUDGETING (StDev)'!AB$11:AB$87) * (D4='RISK BUDGETING (StDev)'!AD$11:AD$87) * (E4='RISK BUDGETING (StDev)'!AF$11:AF$87), 0))} -> 4 | B4: Credit | C4: 0.71084487 | D4: 1.1300131 | E4: 1.4109442 | F4: -0.70009935 | H4: {=INDEX('RISK BUDGETING (StDev)'!P$11:P$87, MATCH(1, (I4='RISK BUDGETING (StDev)'!Q$11:Q$87) * (J4='RISK BUDGETING (StDev)'!AB$11:AB$87) * (K4='RISK BUDGETING (StDev)'!AD$11:AD$87) * (L4='RISK BUDGETING (StDev)'!AF$11:AF$87), 0))} -> 35 | I4: Aquatic: Aquatic - Nautilus CFM (Net) | J4: -0.59150315 | K4: 0.67609513 | L4: 0.84417829 | M4: -1.4356814
A5: {=INDEX('RISK BUDGETING (StDev)'!P$11:P$87, MATCH(1, (B5='RISK BUDGETING (StDev)'!Q$11:Q$87) * (C5='RISK BUDGETING (StDev)'!AB$11:AB$87) * (D5='RISK BUDGETING (StDev)'!AD$11:AD$87) * (E5='RISK BUDGETING (StDev)'!AF$11:AF$87), 0))} -> 12 | B5: Dockside | C5: 0.97744842 | D5: 1.0891745 | E5: 1.3599528 | F5: -0.38250443 | H5: {=INDEX('RISK BUDGETING (StDev)'!P$11:P$87, MATCH(1, (I5='RISK BUDGETING (StDev)'!Q$11:Q$87) * (J5='RISK BUDGETING (StDev)'!AB$11:AB$87) * (K5='RISK BUDGETING (StDev)'!AD$11:AD$87) * (L5='RISK BUDGETING (StDev)'!AF$11:AF$87), 0))} -> 44 | I5: Ares: Ares Pathfinder II | J5: 0.98209792 | K5: 0.31635738 | L5: 0.39500658 | M5: 0.58709133
A6: {=INDEX('RISK BUDGETING (StDev)'!P$11:P$87, MATCH(1, (B6='RISK BUDGETING (StDev)'!Q$11:Q$87) * (C6='RISK BUDGETING (StDev)'!AB$11:AB$87) * (D6='RISK BUDGETING (StDev)'!AD$11:AD$87) * (E6='RISK BUDGETING (StDev)'!AF$11:AF$87), 0))} -> 17 | B6: Equity Long Short | C6: 0.82495862 | D6: 0.3454518 | E6: 0.43133414 | F6: 0.39362448 | H6: {=INDEX('RISK BUDGETING (StDev)'!P$11:P$87, MATCH(1, (I6='RISK BUDGETING (StDev)'!Q$11:Q$87) * (J6='RISK BUDGETING (StDev)'!AB$11:AB$87) * (K6='RISK BUDGETING (StDev)'!AD$11:AD$87) * (L6='RISK BUDGETING (StDev)'!AF$11:AF$87), 0))} -> 36 | I6: Bayview Asset Management: MSR Fund | J6: 0.76373881 | K6: 0.43620113 | L6: 0.54464454 | M6: 0.21909428
A7: {=INDEX('RISK BUDGETING (StDev)'!P$11:P$87, MATCH(1, (B7='RISK BUDGETING (StDev)'!Q$11:Q$87) * (C7='RISK BUDGETING (StDev)'!AB$11:AB$87) * (D7='RISK BUDGETING (StDev)'!AD$11:AD$87) * (E7='RISK BUDGETING (StDev)'!AF$11:AF$87), 0))} -> 21 | B7: Global Macro | C7: 0.96297434 | D7: 1.1537179 | E7: 1.4405423 | F7: -0.47756792 | H7: {=INDEX('RISK BUDGETING (StDev)'!P$11:P$87, MATCH(1, (I7='RISK BUDGETING (StDev)'!Q$11:Q$87) * (J7='RISK BUDGETING (StDev)'!AB$11:AB$87) * (K7='RISK BUDGETING (StDev)'!AD$11:AD$87) * (L7='RISK BUDGETING (StDev)'!AF$11:AF$87), 0))} -> 5 | I7: Benefit Street Partners: Benefit Street Partners Origination Fund (CCFLX) | J7: 0.87289776 | K7: 0.14432684 | L7: 0.18020775 | M7: 0.69269001
A8: {=INDEX('RISK BUDGETING (StDev)'!P$11:P$87, MATCH(1, (B8='RISK BUDGETING (StDev)'!Q$11:Q$87) * (C8='RISK BUDGETING (StDev)'!AB$11:AB$87) * (D8='RISK BUDGETING (StDev)'!AD$11:AD$87) * (E8='RISK BUDGETING (StDev)'!AF$11:AF$87), 0))} -> 27 | B8: Multi Strategy | C8: 1.0985524 | D8: 0.58772091 | E8: 0.73383347 | F8: 0.36471894 | H8: {=INDEX('RISK BUDGETING (StDev)'!P$11:P$87, MATCH(1, (I8='RISK BUDGETING (StDev)'!Q$11:Q$87) * (J8='RISK BUDGETING (StDev)'!AB$11:AB$87) * (K8='RISK BUDGETING (StDev)'!AD$11:AD$87) * (L8='RISK BUDGETING (StDev)'!AF$11:AF$87), 0))} -> 37 | I8: BlackRock: GAO | J8: 1.2240246 | K8: 0.81853225 | L8: 1.0220265 | M8: 0.20199807
A9: {=INDEX('RISK BUDGETING (StDev)'!P$11:P$87, MATCH(1, (B9='RISK BUDGETING (StDev)'!Q$11:Q$87) * (C9='RISK BUDGETING (StDev)'!AB$11:AB$87) * (D9='RISK BUDGETING (StDev)'!AD$11:AD$87) * (E9='RISK BUDGETING (StDev)'!AF$11:AF$87), 0))} -> 34 | B9: Relative Value | C9: 0.82337777 | D9: 0.52088268 | E9: 0.65037867 | F9: 0.1729991 | H9: {=INDEX('RISK BUDGETING (StDev)'!P$11:P$87, MATCH(1, (I9='RISK BUDGETING (StDev)'!Q$11:Q$87) * (J9='RISK BUDGETING (StDev)'!AB$11:AB$87) * (K9='RISK BUDGETING (StDev)'!AD$11:AD$87) * (L9='RISK BUDGETING (StDev)'!AF$11:AF$87), 0))} -> 28 | I9: Blackstone: Badgerstone Access | J9: 0.90210472 | K9: 0.41263938 | L9: 0.51522514 | M9: 0.38687958
A10: {=INDEX('RISK BUDGETING (StDev)'!P$11:P$87, MATCH(1, (B10='RISK BUDGETING (StDev)'!Q$11:Q$87) * (C10='RISK BUDGETING (StDev)'!AB$11:AB$87) * (D10='RISK BUDGETING (StDev)'!AD$11:AD$87) * (E10='RISK BUDGETING (StDev)'!AF$11:AF$87), 0))} -> 43 | B10: Specialty Finance | C10: 0.91070065 | D10: 0.77293544 | E10: 0.96509394 | F10: -0.054393291 | H10: {=INDEX('RISK BUDGETING (StDev)'!P$11:P$87, MATCH(1, (I10='RISK BUDGETING (StDev)'!Q$11:Q$87) * (J10='RISK BUDGETING (StDev)'!AB$11:AB$87) * (K10='RISK BUDGETING (StDev)'!AD$11:AD$87) * (L10='RISK BUDGETING (StDev)'!AF$11:AF$87), 0))} -> 6 | I10: Blue Owl: Blue Owl Funding Partners (CCLFX) | J10: 0.84892915 | K10: 0.27266888 | L10: 0.34045675 | M10: 0.5084724
A11: {=INDEX('RISK BUDGETING (StDev)'!P$11:P$87, MATCH(1, (B11='RISK BUDGETING (StDev)'!Q$11:Q$87) * (C11='RISK BUDGETING (StDev)'!AB$11:AB$87) * (D11='RISK BUDGETING (StDev)'!AD$11:AD$87) * (E11='RISK BUDGETING (StDev)'!AF$11:AF$87), 0))} | H11: {=INDEX('RISK BUDGETING (StDev)'!P$11:P$87, MATCH(1, (I11='RISK BUDGETING (StDev)'!Q$11:Q$87) * (J11='RISK BUDGETING (StDev)'!AB$11:AB$87) * (K11='RISK BUDGETING (StDev)'!AD$11:AD$87) * (L11='RISK BUDGETING (StDev)'!AF$11:AF$87), 0))} -> 2 | I11: Brevan Howard Coinvests (Aksia): Brevan Howard Special Opportunities SPC | J11: 0.23526582 | K11: 0.18108481 | L11: 0.22610408 | M11: 0.0091617409
A12: {=INDEX('RISK BUDGETING (StDev)'!P$11:P$87, MATCH(1, (B12='RISK BUDGETING (StDev)'!Q$11:Q$87) * (C12='RISK BUDGETING (StDev)'!AB$11:AB$87) * (D12='RISK BUDGETING (StDev)'!AD$11:AD$87) * (E12='RISK BUDGETING (StDev)'!AF$11:AF$87), 0))} | H12: {=INDEX('RISK BUDGETING (StDev)'!P$11:P$87, MATCH(1, (I12='RISK BUDGETING (StDev)'!Q$11:Q$87) * (J12='RISK BUDGETING (StDev)'!AB$11:AB$87) * (K12='RISK BUDGETING (StDev)'!AD$11:AD$87) * (L12='RISK BUDGETING (StDev)'!AF$11:AF$87), 0))} -> 22 | I12: Brevan Howard MB Macro Fund: Brevan Howard MB Macro Fund with proforma | J12: 0.89036567 | K12: 0.26451556 | L12: 0.33027644 | M12: 0.56008923
A13: {=INDEX('RISK BUDGETING (StDev)'!P$11:P$87, MATCH(1, (B13='RISK BUDGETING (StDev)'!Q$11:Q$87) * (C13='RISK BUDGETING (StDev)'!AB$11:AB$87) * (D13='RISK BUDGETING (StDev)'!AD$11:AD$87) * (E13='RISK BUDGETING (StDev)'!AF$11:AF$87), 0))} | H13: {=INDEX('RISK BUDGETING (StDev)'!P$11:P$87, MATCH(1, (I13='RISK BUDGETING (StDev)'!Q$11:Q$87) * (J13='RISK BUDGETING (StDev)'!AB$11:AB$87) * (K13='RISK BUDGETING (StDev)'!AD$11:AD$87) * (L13='RISK BUDGETING (StDev)'!AF$11:AF$87), 0))} -> 29 | I13: D. E. Shaw: Cogence | J13: 1.7007494 | K13: 1.3654622 | L13: 1.704928 | M13: -0.0041786509
A14: {=INDEX('RISK BUDGETING (StDev)'!P$11:P$87, MATCH(1, (B14='RISK BUDGETING (StDev)'!Q$11:Q$87) * (C14='RISK BUDGETING (StDev)'!AB$11:AB$87) * (D14='RISK BUDGETING (StDev)'!AD$11:AD$87) * (E14='RISK BUDGETING (StDev)'!AF$11:AF$87), 0))} | H14: {=INDEX('RISK BUDGETING (StDev)'!P$11:P$87, MATCH(1, (I14='RISK BUDGETING (StDev)'!Q$11:Q$87) * (J14='RISK BUDGETING (StDev)'!AB$11:AB$87) * (K14='RISK BUDGETING (StDev)'!AD$11:AD$87) * (L14='RISK BUDGETING (StDev)'!AF$11:AF$87), 0))} -> 30 | I14: DE Shaw Composite Fund LLC: DE Shaw Composite Fund LLC | J14: 1.4252162 | K14: 0.44421708 | L14: 0.55465333 | M14: 0.87056291
A15: {=INDEX('RISK BUDGETING (StDev)'!P$11:P$87, MATCH(1, (B15='RISK BUDGETING (StDev)'!Q$11:Q$87) * (C15='RISK BUDGETING (StDev)'!AB$11:AB$87) * (D15='RISK BUDGETING (StDev)'!AD$11:AD$87) * (E15='RISK BUDGETING (StDev)'!AF$11:AF$87), 0))} | H15: {=INDEX('RISK BUDGETING (StDev)'!P$11:P$87, MATCH(1, (I15='RISK BUDGETING (StDev)'!Q$11:Q$87) * (J15='RISK BUDGETING (StDev)'!AB$11:AB$87) * (K15='RISK BUDGETING (StDev)'!AD$11:AD$87) * (L15='RISK BUDGETING (StDev)'!AF$11:AF$87), 0))} -> 31 | I15: DYAL: DYAL II - Aksia | J15: 1.2936614 | K15: 0.20032401 | L15: 0.2501263 | M15: 1.043535
A16: {=INDEX('RISK BUDGETING (StDev)'!P$11:P$87, MATCH(1, (B16='RISK BUDGETING (StDev)'!Q$11:Q$87) * (C16='RISK BUDGETING (StDev)'!AB$11:AB$87) * (D16='RISK BUDGETING (StDev)'!AD$11:AD$87) * (E16='RISK BUDGETING (StDev)'!AF$11:AF$87), 0))} | H16: {=INDEX('RISK BUDGETING (StDev)'!P$11:P$87, MATCH(1, (I16='RISK BUDGETING (StDev)'!Q$11:Q$87) * (J16='RISK BUDGETING (StDev)'!AB$11:AB$87) * (K16='RISK BUDGETING (StDev)'!AD$11:AD$87) * (L16='RISK BUDGETING (StDev)'!AF$11:AF$87), 0))} -> 14 | I16: Dockside: I-94 Minus Standalones | J16: 1.0463513 | K16: 1.4867382 | L16: 1.8563543 | M16: -0.81000294
A17: {=INDEX('RISK BUDGETING (StDev)'!P$11:P$87, MATCH(1, (B17='RISK BUDGETING (StDev)'!Q$11:Q$87) * (C17='RISK BUDGETING (StDev)'!AB$11:AB$87) * (D17='RISK BUDGETING (StDev)'!AD$11:AD$87) * (E17='RISK BUDGETING (StDev)'!AF$11:AF$87), 0))} | H17: {=INDEX('RISK BUDGETING (StDev)'!P$11:P$87, MATCH(1, (I17='RISK BUDGETING (StDev)'!Q$11:Q$87) * (J17='RISK BUDGETING (StDev)'!AB$11:AB$87) * (K17='RISK BUDGETING (StDev)'!AD$11:AD$87) * (L17='RISK BUDGETING (StDev)'!AF$11:AF$87), 0))} -> 15 | I17: Dorsal Capital Partners LP: Dorsal Capital Partners LP | J17: 0.57425515 | K17: 0.58178342 | L17: 0.72641986 | M17: -0.15216471
A18: {=INDEX('RISK BUDGETING (StDev)'!P$11:P$87, MATCH(1, (B18='RISK BUDGETING (StDev)'!Q$11:Q$87) * (C18='RISK BUDGETING (StDev)'!AB$11:AB$87) * (D18='RISK BUDGETING (StDev)'!AD$11:AD$87) * (E18='RISK BUDGETING (StDev)'!AF$11:AF$87), 0))} | H18: {=INDEX('RISK BUDGETING (StDev)'!P$11:P$87, MATCH(1, (I18='RISK BUDGETING (StDev)'!Q$11:Q$87) * (J18='RISK BUDGETING (StDev)'!AB$11:AB$87) * (K18='RISK BUDGETING (StDev)'!AD$11:AD$87) * (L18='RISK BUDGETING (StDev)'!AF$11:AF$87), 0))} -> 32 | I18: Elliott Associates LP: Elliott Associates LP | J18: 0.71204297 | K18: 0.33876465 | L18: 0.4229845 | M18: 0.28905847
A19: {=INDEX('RISK BUDGETING (StDev)'!P$11:P$87, MATCH(1, (B19='RISK BUDGETING (StDev)'!Q$11:Q$87) * (C19='RISK BUDGETING (StDev)'!AB$11:AB$87) * (D19='RISK BUDGETING (StDev)'!AD$11:AD$87) * (E19='RISK BUDGETING (StDev)'!AF$11:AF$87), 0))} | H19: {=INDEX('RISK BUDGETING (StDev)'!P$11:P$87, MATCH(1, (I19='RISK BUDGETING (StDev)'!Q$11:Q$87) * (J19='RISK BUDGETING (StDev)'!AB$11:AB$87) * (K19='RISK BUDGETING (StDev)'!AD$11:AD$87) * (L19='RISK BUDGETING (StDev)'!AF$11:AF$87), 0))} -> 18 | I19: Four World: FWGO | J19: 0.86964862 | K19: 0.42812486 | L19: 0.53456045 | M19: 0.33508818
A20: {=INDEX('RISK BUDGETING (StDev)'!P$11:P$87, MATCH(1, (B20='RISK BUDGETING (StDev)'!Q$11:Q$87) * (C20='RISK BUDGETING (StDev)'!AB$11:AB$87) * (D20='RISK BUDGETING (StDev)'!AD$11:AD$87) * (E20='RISK BUDGETING (StDev)'!AF$11:AF$87), 0))} | H20: {=INDEX('RISK BUDGETING (StDev)'!P$11:P$87, MATCH(1, (I20='RISK BUDGETING (StDev)'!Q$11:Q$87) * (J20='RISK BUDGETING (StDev)'!AB$11:AB$87) * (K20='RISK BUDGETING (StDev)'!AD$11:AD$87) * (L20='RISK BUDGETING (StDev)'!AF$11:AF$87), 0))} -> 19 | I20: Four World: FWGO Minority Descent | J20: 0.6302408 | K20: 0.4670845 | L20: 0.58320579 | M20: 0.047035018
A21: {=INDEX('RISK BUDGETING (StDev)'!P$11:P$87, MATCH(1, (B21='RISK BUDGETING (StDev)'!Q$11:Q$87) * (C21='RISK BUDGETING (StDev)'!AB$11:AB$87) * (D21='RISK BUDGETING (StDev)'!AD$11:AD$87) * (E21='RISK BUDGETING (StDev)'!AF$11:AF$87), 0))} | H21: {=INDEX('RISK BUDGETING (StDev)'!P$11:P$87, MATCH(1, (I21='RISK BUDGETING (StDev)'!Q$11:Q$87) * (J21='RISK BUDGETING (StDev)'!AB$11:AB$87) * (K21='RISK BUDGETING (StDev)'!AD$11:AD$87) * (L21='RISK BUDGETING (StDev)'!AF$11:AF$87), 0))} -> 23 | I21: Graham Absolute Return Ltd: Graham Absolute Return Ltd | J21: 0.73676293 | K21: 1.6418692 | L21: 2.0500523 | M21: -1.3132893
A22: {=INDEX('RISK BUDGETING (StDev)'!P$11:P$87, MATCH(1, (B22='RISK BUDGETING (StDev)'!Q$11:Q$87) * (C22='RISK BUDGETING (StDev)'!AB$11:AB$87) * (D22='RISK BUDGETING (StDev)'!AD$11:AD$87) * (E22='RISK BUDGETING (StDev)'!AF$11:AF$87), 0))} | H22: {=INDEX('RISK BUDGETING (StDev)'!P$11:P$87, MATCH(1, (I22='RISK BUDGETING (StDev)'!Q$11:Q$87) * (J22='RISK BUDGETING (StDev)'!AB$11:AB$87) * (K22='RISK BUDGETING (StDev)'!AD$11:AD$87) * (L22='RISK BUDGETING (StDev)'!AF$11:AF$87), 0))} -> 3 | I22: HF: Current Coinvests (Excluding BH Coinvests) | J22: 0.64839132 | K22: 0.81269418 | L22: 1.0147371 | M22: -0.36634573
... A33: {=INDEX('RISK BUDGETING (StDev)'!P$11:P$87, MATCH(1, (B33='RISK BUDGETING (StDev)'!Q$11:Q$87) * (C33='RISK BUDGETING (StDev)'!AB$11:AB$87) * (D33='RISK BUDGETING (StDev)'!AD$11:AD$87) * (E33='RISK BUDGETING (StDev)'!AF$11:AF$87), 0))} | H33: {=INDEX('RISK BUDGETING (StDev)'!P$11:P$87, MATCH(1, (I33='RISK BUDGETING (StDev)'!Q$11:Q$87) * (J33='RISK BUDGETING (StDev)'!AB$11:AB$87) * (K33='RISK BUDGETING (StDev)'!AD$11:AD$87) * (L33='RISK BUDGETING (StDev)'!AF$11:AF$87), 0))} -> 26 | I33: Rokos Global Macro Fund LP: Rokos Global Macro Fund LP | J33: 1.389199 | K33: 1.2705789 | L33: 1.5864559 | M33: -0.19725695
H34: {=INDEX('RISK BUDGETING (StDev)'!P$11:P$87, MATCH(1, (I34='RISK BUDGETING (StDev)'!Q$11:Q$87) * (J34='RISK BUDGETING (StDev)'!AB$11:AB$87) * (K34='RISK BUDGETING (StDev)'!AD$11:AD$87) * (L34='RISK BUDGETING (StDev)'!AF$11:AF$87), 0))} -> 16 | I34: Saba: CEF1 MN - 2.75x | J34: 1.3756037 | K34: 1.6052194 | L34: 2.004291 | M34: -0.62868729
H35: {=INDEX('RISK BUDGETING (StDev)'!P$11:P$87, MATCH(1, (I35='RISK BUDGETING (StDev)'!Q$11:Q$87) * (J35='RISK BUDGETING (StDev)'!AB$11:AB$87) * (K35='RISK BUDGETING (StDev)'!AD$11:AD$87) * (L35='RISK BUDGETING (StDev)'!AF$11:AF$87), 0))} -> 10 | I35: Silver Point Capital Fund II LP: Silver Point Capital Fund II LP | J35: 1.5690665 | K35: 0.83188046 | L35: 1.0386932 | M35: 0.53037324
H36: {=INDEX('RISK BUDGETING (StDev)'!P$11:P$87, MATCH(1, (I36='RISK BUDGETING (StDev)'!Q$11:Q$87) * (J36='RISK BUDGETING (StDev)'!AB$11:AB$87) * (K36='RISK BUDGETING (StDev)'!AD$11:AD$87) * (L36='RISK BUDGETING (StDev)'!AF$11:AF$87), 0))} -> 11 | I36: Silver Point Capital: Silver Point Distressed Opportunity Institutional Partners + Silver Point HF | J36: 1.1693907 | K36: 3.3037878 | L36: 4.1251383 | M36: -2.9557476
H37: {=INDEX('RISK BUDGETING (StDev)'!P$11:P$87, MATCH(1, (I37='RISK BUDGETING (StDev)'!Q$11:Q$87) * (J37='RISK BUDGETING (StDev)'!AB$11:AB$87) * (K37='RISK BUDGETING (StDev)'!AD$11:AD$87) * (L37='RISK BUDGETING (StDev)'!AF$11:AF$87), 0))} -> 41 | I37: Taula: SWIB-DM Taula | J37: 1.222481 | K37: 0.40116845 | L37: 0.50090244 | M37: 0.72157854
H38: {=INDEX('RISK BUDGETING (StDev)'!P$11:P$87, MATCH(1, (I38='RISK BUDGETING (StDev)'!Q$11:Q$87) * (J38='RISK BUDGETING (StDev)'!AB$11:AB$87) * (K38='RISK BUDGETING (StDev)'!AD$11:AD$87) * (L38='RISK BUDGETING (StDev)'!AF$11:AF$87), 0))} -> 42 | I38: Voleon Composition Domestic Fund LP: Voleon Composition Domestic Fund LP | J38: 0.7580382 | K38: 0.8054212 | L38: 1.0056559 | M38: -0.24761774
H39: {=INDEX('RISK BUDGETING (StDev)'!P$11:P$87, MATCH(1, (I39='RISK BUDGETING (StDev)'!Q$11:Q$87) * (J39='RISK BUDGETING (StDev)'!AB$11:AB$87) * (K39='RISK BUDGETING (StDev)'!AD$11:AD$87) * (L39='RISK BUDGETING (StDev)'!AF$11:AF$87), 0))} -> 33 | I39: Walleye: Walleye Opportunities Fund | J39: 0.94527756 | K39: 1.5436233 | L39: 1.9273816 | M39: -0.982104
H40: {=INDEX('RISK BUDGETING (StDev)'!P$11:P$87, MATCH(1, (I40='RISK BUDGETING (StDev)'!Q$11:Q$87) * (J40='RISK BUDGETING (StDev)'!AB$11:AB$87) * (K40='RISK BUDGETING (StDev)'!AD$11:AD$87) * (L40='RISK BUDGETING (StDev)'!AF$11:AF$87), 0))}
H41: {=INDEX('RISK BUDGETING (StDev)'!P$11:P$87, MATCH(1, (I41='RISK BUDGETING (StDev)'!Q$11:Q$87) * (J41='RISK BUDGETING (StDev)'!AB$11:AB$87) * (K41='RISK BUDGETING (StDev)'!AD$11:AD$87) * (L41='RISK BUDGETING (StDev)'!AF$11:AF$87), 0))}
H42: {=INDEX('RISK BUDGETING (StDev)'!P$11:P$87, MATCH(1, (I42='RISK BUDGETING (StDev)'!Q$11:Q$87) * (J42='RISK BUDGETING (StDev)'!AB$11:AB$87) * (K42='RISK BUDGETING (StDev)'!AD$11:AD$87) * (L42='RISK BUDGETING (StDev)'!AF$11:AF$87), 0))}
H43: {=INDEX('RISK BUDGETING (StDev)'!P$11:P$87, MATCH(1, (I43='RISK BUDGETING (StDev)'!Q$11:Q$87) * (J43='RISK BUDGETING (StDev)'!AB$11:AB$87) * (K43='RISK BUDGETING (StDev)'!AD$11:AD$87) * (L43='RISK BUDGETING (StDev)'!AF$11:AF$87), 0))}
H44: {=INDEX('RISK BUDGETING (StDev)'!P$11:P$87, MATCH(1, (I44='RISK BUDGETING (StDev)'!Q$11:Q$87) * (J44='RISK BUDGETING (StDev)'!AB$11:AB$87) * (K44='RISK BUDGETING (StDev)'!AD$11:AD$87) * (L44='RISK BUDGETING (StDev)'!AF$11:AF$87), 0))}
H45: {=INDEX('RISK BUDGETING (StDev)'!P$11:P$87, MATCH(1, (I45='RISK BUDGETING (StDev)'!Q$11:Q$87) * (J45='RISK BUDGETING (StDev)'!AB$11:AB$87) * (K45='RISK BUDGETING (StDev)'!AD$11:AD$87) * (L45='RISK BUDGETING (StDev)'!AF$11:AF$87), 0))}
H46: {=INDEX('RISK BUDGETING (StDev)'!P$11:P$87, MATCH(1, (I46='RISK BUDGETING (StDev)'!Q$11:Q$87) * (J46='RISK BUDGETING (StDev)'!AB$11:AB$87) * (K46='RISK BUDGETING (StDev)'!AD$11:AD$87) * (L46='RISK BUDGETING (StDev)'!AF$11:AF$87), 0))}
H47: {=INDEX('RISK BUDGETING (StDev)'!P$11:P$87, MATCH(1, (I47='RISK BUDGETING (StDev)'!Q$11:Q$87) * (J47='RISK BUDGETING (StDev)'!AB$11:AB$87) * (K47='RISK BUDGETING (StDev)'!AD$11:AD$87) * (L47='RISK BUDGETING (StDev)'!AF$11:AF$87), 0))}
H48: {=INDEX('RISK BUDGETING (StDev)'!P$11:P$87, MATCH(1, (I48='RISK BUDGETING (StDev)'!Q$11:Q$87) * (J48='RISK BUDGETING (StDev)'!AB$11:AB$87) * (K48='RISK BUDGETING (StDev)'!AD$11:AD$87) * (L48='RISK BUDGETING (StDev)'!AF$11:AF$87), 0))}
H49: {=INDEX('RISK BUDGETING (StDev)'!P$11:P$87, MATCH(1, (I49='RISK BUDGETING (StDev)'!Q$11:Q$87) * (J49='RISK BUDGETING (StDev)'!AB$11:AB$87) * (K49='RISK BUDGETING (StDev)'!AD$11:AD$87) * (L49='RISK BUDGETING (StDev)'!AF$11:AF$87), 0))}
H50: {=INDEX('RISK BUDGETING (StDev)'!P$11:P$87, MATCH(1, (I50='RISK BUDGETING (StDev)'!Q$11:Q$87) * (J50='RISK BUDGETING (StDev)'!AB$11:AB$87) * (K50='RISK BUDGETING (StDev)'!AD$11:AD$87) * (L50='RISK BUDGETING (StDev)'!AF$11:AF$87), 0))}
H51: {=INDEX('RISK BUDGETING (StDev)'!P$11:P$87, MATCH(1, (I51='RISK BUDGETING (StDev)'!Q$11:Q$87) * (J51='RISK BUDGETING (StDev)'!AB$11:AB$87) * (K51='RISK BUDGETING (StDev)'!AD$11:AD$87) * (L51='RISK BUDGETING (StDev)'!AF$11:AF$87), 0))}
... H103: {=INDEX('RISK BUDGETING (StDev)'!P$11:P$87, MATCH(1, (I103='RISK BUDGETING (StDev)'!Q$11:Q$87) * (J103='RISK BUDGETING (StDev)'!AB$11:AB$87) * (K103='RISK BUDGETING (StDev)'!AD$11:AD$87) * (L103='RISK BUDGETING (StDev)'!AF$11:AF$87), 0))}

Sheet FACTOR CONTRIBUTION
A4: FACTOR CONTRIBUTION BY FACTOR BUCKET
A5: Percentage Contribution to Risk (PCTR) by Factor Bucket shows how a given factor bucket contributes to the overall risk of the portfolio.
AB9: Factor PC to StDev (%) • | AD9: Factor PC to ETL (%) •
S10: SYSTEMATIC RISK | AB10: =SUMMARY!W13 -> 47.149713 | AD10: =SUMMARY!AF13 -> 115.77315
S11: SPECIFIC RISK | AB11: =SUMMARY!W24 -> 52.850287 | AD11: =SUMMARY!AF24 -> -15.773153
S12: Commodity Risk | AB12: -4.0265997 | AD12: -8.4279646
S13: Equity Risk | AB13: 7.7657969 | AD13: 19.073921
S14: FX Risk | AB14: -0.20667012 | AD14: -0.5659147
S15: Fixed Income Risk | AB15: 42.751742 | AD15: 103.89462
S16: Interest Rate Risk | AB16: 0.061423329 | AD16: 0.12630521
S17: Volatility Risk | AB17: 0.80402133 | AD17: 1.6721821
A23: FACTOR CONTRIBUTION BY FACTOR
A24: Percentage Contribution to Risk (PCTR) shows how a given factor contributes to the overall risk of the portfolio. For a long-only portfolio risk is reduced by decreasing the exposure to factors that have PCTR lower than the factor exposure and increasing those with PCTR higher than its exposure.
Z27: Portfolio Exposure (%) | AB27: Factor MC to StDev (bps) | AD27: Factor PC to StDev (%) • | AF27: Factor MC to ETL (bps) | AH27: Factor PC to ETL (%) •
S28: Specific Risk | AD28: 52.850287 | AH28: -15.773153
S29: Total Systematic Risk | Z29: 0.18544526 | AB29: 1.9093144 | AD29: 47.149713 | AF29: 5.4559966 | AH29: 115.77315
S30: Residual Risk
S31: Factor Risk | Z31: 0.18544526 | AB31: 1.9093144 | AD31: 47.149713 | AF31: 5.4559966 | AH31: 115.77315
S32: Commodity Risk | Z32: -0.011900747 | AB32: 2.5408459 | AD32: -4.0265997 | AF32: 6.1891416 | AH32: -8.4279646
S33: S&P GSCI Index | Z33: -0.011900747 | AB33: 2.5408459 | AD33: -4.0265997 | AF33: 6.1891416 | AH33: -8.4279646
S34: Equity Risk | Z34: 0.038725346 | AB34: 1.5059302 | AD34: 7.7657969 | AF34: 4.3045389 | AH34: 19.073921
S35: MSCI Small Minus Large World USD | Z35: 0.037744728 | AB35: 0.92771053 | AD35: 4.6628847 | AF35: 2.8807951 | AH35: 12.4419
S36: MSCI The World USD | Z36: 0.014730596 | AB36: 1.6779847 | AD36: 3.2915027 | AF36: 4.0412801 | AH36: 6.8117282
S37: MSCI Value Minus Growth World USD | Z37: -0.013749978 | AB37: 0.10299873 | AD37: -0.18859047 | AF37: 0.11422066 | AH37: -0.17970689
S38: FX Risk | Z38: 0.004376476 | AB38: -0.35462328 | AD38: -0.20667012 | AF38: -1.1300779 | AH38: -0.5659147
S39: Trade Weighted Exchange Index: Broad | Z39: 0.004376476 | AB39: -0.35462328 | AD39: -0.20667012 | AF39: -1.1300779 | AH39: -0.5659147
S40: Fixed Income Risk | Z40: 0.15837662 | AB40: 2.0271078 | AD40: 42.751742 | AF40: 5.7330265 | AH40: 103.89462
S41: Corporate Risk | Z41: 0.20128462 | AB41: 1.5212307 | AD41: 40.774773 | AF41: 4.408947 | AH41: 101.54616
S42: ML Global High Yield - AAA Spread USD | Z42: 0.20128462 | AB42: 1.5212307 | AD42: 40.774773 | AF42: 4.408947 | AH42: 101.54616
... S48: CBOE Volatility Index as Difference USD | Z48: -0.0048516357 | AB48: -1.244496 | AD48: 0.80402133 | AF48: -3.0121552 | AH48: 1.6721821

Sheet FCTR_DATA
A1: ML Global High Yield - AAA Spread USD | B1: 40.774773 | C1: 101.54616
A2: MSCI Small Minus Large World USD | B2: 4.6628847 | C2: 12.4419
A3: MSCI The World USD | B3: 3.2915027 | C3: 6.8117282
A4: ML Global Govt Bond II USD | B4: 1.9769688 | C4: 2.3484622
A5: CBOE Volatility Index as Difference USD | B5: 0.80402133 | C5: 1.6721821
A6: US Treasury 10Yr - 2Yr Spread USD | B6: 0.061423329 | C6: 0.12630521
A7: MSCI Value Minus Growth World USD | B7: -0.18859047 | C7: -0.17970689
A8: Trade Weighted Exchange Index: Broad | B8: -0.20667012 | C8: -0.5659147
A9: S&P GSCI Index | B9: -4.0265997 | C9: -8.4279646

Sheet EXPOSURE BY FACTOR BUCKET
A4: DETAILED EXPOSURE BY FACTOR BUCKET
A5: The sensitivity of each position toward the respective market segment
A8: Name | J8: Commodity Risk Sensitivity | L8: Corporate Risk Sensitivity | N8: Equity Risk Sensitivity | P8: FX Risk Sensitivity | R8: Interest Rate Risk Sensitivity | T8: Sovereign Risk Sensitivity | V8: Volatility Risk Sensitivity | X8: %rhNode | Z8: %rhNode | AB8: %rhNode | AD8: %rhNode | AF8: %rhNode | AH8: %rhNode
A9: Current 7.26 | J9: -1.1900747 | L9: 20.128462 | N9: 3.8725346 | P9: 0.4376476 | R9: 0.071919361 | T9: -4.2907993 | V9: -0.48516357
A10: Coinvests | J10: -0.084235699 | N10: 0.33576026 | V10: 0.072605118
A11: Brevan Howard Coinvests (Aksia): Brevan Howard Special Opportunities SPC | J11: -0.084235699 | V11: 0.072605118
A12: HF: Current Coinvests (Excluding BH Coinvests) | N12: 0.33576026
A13: Credit | J13: 0.80158949 | L13: 2.8620487 | N13: 0.63859544 | P13: 1.7822001 | T13: 1.3263631 | V13: -0.0049028401
A14: Benefit Street Partners: Benefit Street Partners Origination Fund (CCFLX) | N14: 0.00434676
A15: Blue Owl: Blue Owl Funding Partners (CCLFX) | J15: 0.020567852 | N15: -0.020848302
A16: King Street Capital LP: King Street Capital LP | L16: 0.019489493 | V16: -0.0049028401
A17: LibreMax CLO: LibreMax CLO | P17: 0.4285892
A18: LibreMax Partners LP: LibreMax Partners LP | J18: 0.36811724 | L18: 1.3250582 | N18: 0.65509698
A19: Silver Point Capital Fund II LP: Silver Point Capital Fund II LP | J19: 0.15328136
A20: Silver Point Capital: Silver Point Distressed Opportunity Institutional Partners + Silver Point HF | J20: 0.25962303 | L20: 1.5175011 | P20: 1.3536109 | T20: 1.3263631
A21: Dockside | L21: 3.6496266 | N21: 0.74795085 | P21: 1.3803409 | R21: 0.066735255 | V21: -0.35216343
A22: 12267: Trexquant Onshore Fund LP | L22: 0.80681303 | N22: -1.0187255 | P22: 1.3803409 | R22: 0.03495848 | V22: -0.35216343
A23: Dockside: I-94 Minus Standalones | L23: 2.0058739 | N23: 1.6780291
A24: Dorsal Capital Partners LP: Dorsal Capital Partners LP | L24: 0.3997606 | N24: -0.67131679 | R24: 0.046568535
A25: Saba: CEF1 MN - 2.75x | L25: 0.43717905 | N25: 0.759964 | R25: -0.01479176
A26: Equity Long Short | L26: 0.48848844 | N26: -0.063728978 | T26: 0.2160157
A27: Four World: FWGO | N27: 0.37930731
A28: Four World: FWGO Minority Descent | L28: 0.48848844 | T28: 0.2160157
A29: Holocene: Holocene Advisors Master | N29: -0.44303629
A30: Global Macro | J30: -2.1537554 | L30: 7.3505316 | N30: 1.3607386 | P30: -1.248947 | R30: 0.0051841054 | T30: -2.6515633 | V30: -0.15892768
A31: Brevan Howard MB Macro Fund: Brevan Howard MB Macro Fund with proforma | J31: -0.25946488 | N31: 0.32268822
A32: Graham Absolute Return Ltd: Graham Absolute Return Ltd | L32: 1.6714591 | N32: 0.42188189 | V32: -0.15892768
A33: Mesarete: Prior TR+back with Pharo Macro+Mesarete Capital Fund | L33: 0.71114263 | N33: 0.29739873 | P33: -1.248947 | R33: -0.025526653
A34: PIMCO: PIMCO Commodity Alpha Fund | J34: -0.15986777 | L34: 0.63060337 | N34: 0.31876981 | R34: 0.030710759
A35: Rokos Global Macro Fund LP: Rokos Global Macro Fund LP | J35: -1.7344228 | L35: 4.3373265 | T35: -2.6515633
A36: Multi Strategy | L36: 2.9387985 | N36: 0.65774553 | T36: -2.3933405 | V36: -0.24696051
A37: Blackstone: Badgerstone Access | T37: -0.48555663 | V37: -0.24499346
A38: D. E. Shaw: Cogence | L38: 1.0726189 | N38: -0.13602129 | V38: 0.20644299
A39: DE Shaw Composite Fund LLC: DE Shaw Composite Fund LLC | T39: -1.7315241 | V39: -0.4182644
A40: DYAL: DYAL II - Aksia | L40: -0.66184744 | T40: -0.88819914
A41: Elliott Associates LP: Elliott Associates LP | L41: 1.0823222 | N41: 0.27256864 | T41: 0.71193941 | V41: 0.20985435
A42: Walleye: Walleye Opportunities Fund | L42: 1.4457049 | N42: 0.52119817
A43: Relative Value | J43: -0.14953565 | L43: 2.1389258 | N43: 0.16251892 | P43: -1.4759464 | T43: -0.78827428 | V43: 0.20518577
A44: Aquatic: Aquatic - Nautilus CFM (Net) | V44: -0.042169034
A45: Bayview Asset Management: MSR Fund | J45: 0.095685633 | L45: 0.24139411 | N45: 0.099985507
A46: BlackRock: GAO | N46: 0.21738175
A47: Hudson Structured: HSCM w MFC | T47: 0.11297134
A48: PIMCO Global Credit Opportunity Onshore Fund LLC: PIMCO Global Credit Opportunity Onshore Fund LLC | J48: 0.3283782 | T48: -0.90124563 | V48: 0.48959565
A49: Reflow Full Track: ReFlow LO Excess Plus Market Neutral | P49: -0.31941191
A50: Taula: SWIB-DM Taula | J50: -0.57359949 | L50: 0.93561814 | N50: 0.42722836 | P50: -1.1565344
A51: Voleon Composition Domestic Fund LP: Voleon Composition Domestic Fund LP | L51: 0.9619135 | N51: -0.58207669 | V51: -0.24224084
A52: Specialty Finance | J52: 0.39586253 | L52: 0.70004194 | N52: 0.032953966
A53: Ares: Ares Pathfinder II | J53: 0.14642212 | N53: -0.34564047
A54: HF: Current Specialty Finance (Excluding Pathfinder) | J54: 0.24944042 | L54: 0.70004194 | N54: 0.37859443

Sheet PORTFOLIO STRESS TEST
A4: PORTFOLIO VALUE STRESS TEST
A5: Stress testing provides intuitive first glance assessment of the possible losses to portfolio value under different extreme scenarios and facilitates the understanding of more advanced risk statistics. It provides indication how the current level of portfolio risk, measured by VaR and ETL stands among historically observed extremes. The stress test scenarios are ordered by most negative impact on the portfolio value.
A9: Highest Gain Scenario(%) | G9: Highest Loss Scenario (%)
A10: =PORTFOLIO_STRESS_TEST_LOSS_GAIN!Q6 -> 0.011043836 | G10: =PORTFOLIO_STRESS_TEST_LOSS_GAIN!A6 -> -0.035256818
A11: =PORTFOLIO_STRESS_TEST_LOSS_GAIN!X8 -> 2005 Katrina | F11: =PORTFOLIO_STRESS_TEST_LOSS_GAIN!I8 -> 2008 Lehman Blow-Up
A13: Name | K13: Initial Value | N13: Weight (%) | O13: 2008 Lehman Blow-Up | Q13: 2002 Market Downturn | S13: 2001 WTC Attack | U13: 1987 Black Monday | W13: 1998 Russian Crisis | Y13: 2008 January Crisis | AA13: 2007 August Crisis | AC13: 2001 Nasdaq | AE13: 1997 - 1998 Asian Crisis | AG13: 1990 Kuwait Invasion | AI13: 2005 Katrina
A14: Current 7.26 | K14: 1000000 | O14: -3.5256818 | Q14: -1.7508844 | S14: -1.1625695 | U14: -0.6952119 | W14: -0.68043189 | Y14: -0.30050481 | AA14: -0.024435815 | AC14: 0.072055902 | AE14: 0.1020368 | AG14: 0.29266168 | AI14: 1.1043836
A15: Coinvests | K15: 21508.199 | N15: =IF(ISBLANK(K15)=TRUE,"",K15/$K$14*100) -> 2.1508199 | O15: -3.0304689 | Q15: -4.5535932 | S15: -1.8064292 | U15: 0.37379162 | W15: -0.81242294 | Y15: -2.107786 | AA15: -0.87056696 | AC15: -1.1641465 | AE15: -0.33385603 | AG15: -1.5045087 | AI15: -0.51260942
A16: Brevan Howard Coinvests (Aksia): Brevan Howard Special Opportunities SPC | K16: 6321.6727 | N16: =IF(ISBLANK(K16)=TRUE,"",K16/$K$14*100) -> 0.63216727 | O16: 16.585314 | Q16: 1.8251413 | S16: 2.7598746 | U16: 9.2817981 | W16: 4.7450895 | Y16: 0.69173986 | AA16: 2.2939355 | AC16: 1.7454554 | AE16: 0.71072679 | AG16: -1.5587523 | AI16: 0.44879549
A17: HF: Current Coinvests (Excluding BH Coinvests) | K17: 15186.526 | N17: =IF(ISBLANK(K17)=TRUE,"",K17/$K$14*100) -> 1.5186526 | O17: -11.195902 | Q17: -7.2088595 | S17: -3.7072377 | U17: -3.334331 | W17: -3.1258404 | Y17: -3.2731405 | AA17: -2.1878497 | AC17: -2.3753222 | AE17: -0.76868296 | AG17: -1.4819289 | AI17: -0.912812
A18: Credit | K18: 66920.936 | N18: =IF(ISBLANK(K18)=TRUE,"",K18/$K$14*100) -> 6.6920936 | O18: -14.021846 | Q18: -5.6672872 | S18: -3.1225342 | U18: -4.9992902 | W18: -3.2157741 | Y18: -1.3244441 | AA18: -0.79539604 | AC18: -1.4412039 | AE18: 0.39359243 | AG18: 2.6530233 | AI18: 0.10244669
A19: Benefit Street Partners: Benefit Street Partners Origination Fund (CCFLX) | K19: 747.08538 | N19: =IF(ISBLANK(K19)=TRUE,"",K19/$K$14*100) -> 0.074708538 | O19: -1.0174038 | Q19: 1.8464347 | S19: -0.43999281 | U19: -0.26513664 | W19: 0.34499083 | Y19: 0.23085966 | AA19: 0.11862182 | AC19: 0.10499804 | AE19: 0.31372909 | AG19: 0.60465088 | AI19: 0.6458553
A20: Blue Owl: Blue Owl Funding Partners (CCLFX) | K20: 3124.1515 | N20: =IF(ISBLANK(K20)=TRUE,"",K20/$K$14*100) -> 0.31241515 | O20: -2.5271579 | Q20: 4.7879736 | S20: 0.24266898 | U20: 0.55152882 | W20: 0.66232717 | Y20: 1.0966305 | AA20: 0.46065694 | AC20: 0.18319437 | AE20: 0.64448858 | AG20: 2.8480922 | AI20: 0.8740043
A21: King Street Capital LP: King Street Capital LP | K21: 612.33379 | N21: =IF(ISBLANK(K21)=TRUE,"",K21/$K$14*100) -> 0.061233379 | O21: -12.537968 | Q21: -9.1200007 | S21: -3.5747142 | U21: -7.6120141 | W21: -4.299804 | Y21: -2.1208446 | AA21: -1.8782169 | AC21: -1.9508288 | AE21: -1.2404076 | AG21: -1.6355198 | AI21: -0.15866769
A22: LibreMax CLO: LibreMax CLO | K22: 20217.776 | N22: =IF(ISBLANK(K22)=TRUE,"",K22/$K$14*100) -> 2.0217776 | O22: 2.4805566 | Q22: 0.13329429 | S22: 0.18812062 | U22: -0.38216062 | W22: 0.5567726 | Y22: -0.012249588 | AA22: 0.33062415 | AC22: 0.42006492 | AE22: 0.29586122 | AG22: -0.61323164 | AI22: 0.43980234
A23: LibreMax Partners LP: LibreMax Partners LP | K23: 24519.223 | N23: =IF(ISBLANK(K23)=TRUE,"",K23/$K$14*100) -> 2.4519223 | O23: -23.790872 | Q23: -11.817708 | S23: -5.0703637 | U23: -4.6811004 | W23: -7.0528825 | Y23: -3.1157384 | AA23: -2.5716398 | AC23: -1.7613745 | AE23: -0.22818451 | AG23: 3.0979989 | AI23: 0.028230379
A24: Silver Point Capital Fund II LP: Silver Point Capital Fund II LP | K24: 9954.0528 | N24: =IF(ISBLANK(K24)=TRUE,"",K24/$K$14*100) -> 0.99540528 | O24: -6.1536363 | Q24: 7.8979345 | S24: 0.147678 | U24: 1.1257225 | W24: 0.36980658 | Y24: 2.0880997 | AA24: 0.61985574 | AC24: 0.57483155 | AE24: 1.5068268 | AG24: 6.3148854 | AI24: 1.5937565
A25: Silver Point Capital: Silver Point Distressed Opportunity Institutional Partners + Silver Point HF | K25: 7746.3136 | N25: =IF(ISBLANK(K25)=TRUE,"",K25/$K$14*100) -> 0.77463136 | O25: -42.289325 | Q25: -23.43874 | S25: -11.380305 | U25: -28.416508 | W25: -7.345846 | Y25: -4.527934 | AA25: -0.43973023 | AC25: -8.6402481 | AE25: 1.2219324 | AG25: 5.5218059 | AI25: -2.802416
A26: Dockside | K26: 135899.56 | N26: =IF(ISBLANK(K26)=TRUE,"",K26/$K$14*100) -> 13.589956 | O26: -6.9848055 | Q26: -3.4221883 | S26: -1.8777069 | U26: -3.75992 | W26: -1.7272987 | Y26: -0.71495087 | AA26: -0.4094611 | AC26: -0.24320112 | AE26: -0.12558292 | AG26: -0.12181493 | AI26: 0.97493226
... A59: HF: Current Specialty Finance (Excluding Pathfinder) | K59: 34666.752 | N59: =IF(ISBLANK(K59)=TRUE,"",K59/$K$14*100) -> 3.4666752 | O59: -10.304767 | Q59: -0.3730369 | S59: -1.683842 | U59: -2.1335229 | W59: -2.2704967 | Y59: -0.48510619 | AA59: -0.70417991 | AC59: -0.012494808 | AE59: 0.2096101 | AG59: 2.011361 | AI59: 0.68918311
N60: =IF(ISBLANK(K60)=TRUE,"",K60/$K$14*100)
N61: =IF(ISBLANK(K61)=TRUE,"",K61/$K$14*100)
N62: =IF(ISBLANK(K62)=TRUE,"",K62/$K$14*100)
N63: =IF(ISBLANK(K63)=TRUE,"",K63/$K$14*100)
N64: =IF(ISBLANK(K64)=TRUE,"",K64/$K$14*100)
N65: =IF(ISBLANK(K65)=TRUE,"",K65/$K$14*100)
N66: =IF(ISBLANK(K66)=TRUE,"",K66/$K$14*100)
N67: =IF(ISBLANK(K67)=TRUE,"",K67/$K$14*100)
N68: =IF(ISBLANK(K68)=TRUE,"",K68/$K$14*100)
N69: =IF(ISBLANK(K69)=TRUE,"",K69/$K$14*100)
N70: =IF(ISBLANK(K70)=TRUE,"",K70/$K$14*100)
N71: =IF(ISBLANK(K71)=TRUE,"",K71/$K$14*100)
... N83: =IF(ISBLANK(K83)=TRUE,"",K83/$K$14*100)

Sheet ONE FACTOR REGRESSION
A1: ONE FACTOR REGRESSION
A7: If you wish to see this result, please specify One Factor Regression calculation.
A50: Disclaimer:

Sheet PORTFOLIO_STRESS_TEST_LOSS_GAIN
A4: HIGHLIGHTS
A5: Highest Loss Scenario (%) | I5: Highest Loss Scenario (Amount) | Q5: Highest Gain Scenario (%) | X5: Highest Gain Scenario(Amount)
A6: =F18/100 -> -0.035256818 | I6: =F20 -> 964743.18 | Q6: =F36/100 -> 0.011043836 | X6: =F38 -> 1011043.8
I8: =A18 -> 2008 Lehman Blow-Up | X8: =A36 -> 2005 Katrina
A10: PREDEFINED SCENARIO
A11: STRESS TEST SCENARIOS
F13: Contribution Total Loss/Gain
A16: TOP 5 HIGHEST LOSS STRESS TEST SCENARIOS
A17: STRESS TEST SCENARIOS | F17: 00000MP87KPZC-3AM47H-TTQARV | J17: Strategy - Multi Strategy | L17: Strategy - Relative Value | N17: Strategy - Global Macro | P17: Strategy - Dockside | R17: Strategy - Equity Long Short | T17: Strategy - Credit | V17: Strategy - Specialty Finance | X17: Strategy - Coinvests
A18: 2008 Lehman Blow-Up | F18: -3.5256818 | J18: -0.81583041 | L18: -1.0299168 | N18: -5.5487565 | P18: -6.9848055 | R18: 0.6717952 | T18: -14.021846 | V18: -7.4405157 | X18: -3.0304689
F19: Contribution Total Loss/Gain | J19: 6.9211648 | L19: 5.633684 | N19: 22.91949 | P19: 26.923361 | R19: -1.6563568 | T19: 26.614854 | V19: 10.795085 | X19: 1.8487184
F20: 964743.18
F22: Contribution Total Loss/Gain
F25: Contribution Total Loss/Gain
F28: Contribution Total Loss/Gain
F31: Contribution Total Loss/Gain
A34: TOP 5 HIGHEST GAIN STRESS TEST SCENARIOS
A35: STRESS TEST SCENARIOS | F35: 00000MP87KPZC-3AM47H-TTQARV | J35: Strategy - Multi Strategy | L35: Strategy - Relative Value | N35: Strategy - Global Macro | P35: Strategy - Dockside | R35: Strategy - Equity Long Short | T35: Strategy - Credit | V35: Strategy - Specialty Finance | X35: Strategy - Coinvests
A36: 2005 Katrina | F36: 1.1043836 | J36: 1.4958422 | L36: 0.96051263 | N36: 1.5710065 | P36: 0.97493226 | R36: 0.80544506 | T36: 0.10244669 | V36: 0.87199275 | X36: -0.51260942
F37: Contribution Total Loss/Gain | J37: 40.512427 | L37: 16.773227 | N37: 20.716217 | P37: 11.996998 | R37: 6.3398081 | T37: 0.62078328 | V37: 4.0388625 | X37: -0.99832211
F38: 1011043.8
F40: Contribution Total Loss/Gain
F43: Contribution Total Loss/Gain
F46: Contribution Total Loss/Gain
F49: Contribution Total Loss/Gain

Sheet SCENARIOS_ORDERED_BY_PF_VALUE
A1: Name | B1: Initial Value | D1: 2008 Lehman Blow-Up | E1: 2002 Market Downturn | F1: 2001 WTC Attack | G1: 1987 Black Monday | H1: 1998 Russian Crisis | I1: 2008 January Crisis | J1: 2007 August Crisis | K1: 2001 Nasdaq | L1: 1997 - 1998 Asian Crisis | M1: 1990 Kuwait Invasion | N1: 2005 Katrina
A2: 12267: Trexquant Onshore Fund LP | B2: 31198.357 | D2: -2.3162115 | E2: -3.6575162 | F2: -1.3704075 | G2: -7.3918503 | H2: 0.10378864 | I2: 0.35222973 | J2: 0.55247466 | K2: -1.1322261 | L2: -0.13101093 | M2: -0.61921468 | N2: 1.9629194
A3: Aquatic: Aquatic - Nautilus CFM (Net) | B3: 3838.2851 | D3: -7.8368495 | E3: -5.5819151 | F3: -2.3661469 | G3: -8.6444407 | H3: -3.9520856 | I3: -1.6919121 | J3: -2.235365 | K3: -1.6731249 | L3: -1.5928982 | M3: -2.9249691 | N3: -1.199001
A4: Ares: Ares Pathfinder II | B4: 16485.661 | D4: -1.4174462 | E4: 5.2678978 | F4: 0.62660598 | G4: 2.2365513 | H4: 1.8978828 | I4: 1.8105258 | J4: 1.1152232 | K4: -0.33130674 | L4: 1.0313222 | M4: 4.5725568 | N4: 1.2564127
A5: Bayview Asset Management: MSR Fund | B5: 22527.339 | D5: -4.7360983 | E5: 1.1386759 | F5: -0.65511645 | G5: -0.64863475 | H5: -0.64830029 | I5: 0.2484402 | J5: -0.033699687 | K5: 0.19872329 | L5: 0.37184321 | M5: 1.7075245 | N5: 0.73858071
A6: Benefit Street Partners: Benefit Street Partners Origination Fund (CCFLX) | B6: 747.08538 | D6: -1.0174038 | E6: 1.8464347 | F6: -0.43999281 | G6: -0.26513664 | H6: 0.34499083 | I6: 0.23085966 | J6: 0.11862182 | K6: 0.10499804 | L6: 0.31372909 | M6: 0.60465088 | N6: 0.6458553
A7: BlackRock: GAO | B7: 23161.392 | D7: -2.1831333 | E7: 1.9625124 | F7: -0.85442118 | G7: -0.59283786 | H7: 0.24273166 | I7: 0.078460622 | J7: 0.0053263406 | K7: -0.026407122 | L7: 0.36897891 | M7: 0.71075526 | N7: 0.80688756
A8: Blackstone: Badgerstone Access | B8: 50884.559 | D8: -0.51919864 | E8: 2.0928679 | F8: -0.34441474 | G8: -1.9223184 | H8: -0.31047241 | I8: 0.60227288 | J8: -0.094085841 | K8: 0.54290594 | L8: 0.057438687 | M8: 0.07453246 | N8: 1.2003748
A9: Blue Owl: Blue Owl Funding Partners (CCLFX) | B9: 3124.1515 | D9: -2.5271579 | E9: 4.7879736 | F9: 0.24266898 | G9: 0.55152882 | H9: 0.66232717 | I9: 1.0966305 | J9: 0.46065694 | K9: 0.18319437 | L9: 0.64448858 | M9: 2.8480922 | N9: 0.8740043
A10: Brevan Howard Coinvests (Aksia): Brevan Howard Special Opportunities SPC | B10: 6321.6727 | D10: 16.585314 | E10: 1.8251413 | F10: 2.7598746 | G10: 9.2817981 | H10: 4.7450895 | I10: 0.69173986 | J10: 2.2939355 | K10: 1.7454554 | L10: 0.71072679 | M10: -1.5587523 | N10: 0.44879549
A11: Brevan Howard MB Macro Fund: Brevan Howard MB Macro Fund with proforma | B11: 26002.026 | D11: 8.1157106 | E11: 3.7540404 | F11: 0.90776497 | G11: -0.15788223 | H11: 1.5997602 | I11: 0.94603543 | J11: 0.82777612 | K11: 1.7948098 | L11: 0.16499677 | M11: -2.1274732 | N11: 0.88992654
A12: D. E. Shaw: Cogence | B12: 19781.362 | D12: -8.2073801 | E12: -1.4177735 | F12: -1.2213437 | G12: 4.4549492 | H12: 0.73368969 | I12: -0.61580068 | J12: 1.1624338 | K12: 0.14829269 | L12: 0.77394104 | M12: 2.67355 | N12: 2.1209853
A13: DE Shaw Composite Fund LLC: DE Shaw Composite Fund LLC | B13: 93802.815 | D13: 1.0175125 | E13: 3.7457406 | F13: -0.026860977 | G13: -0.23266343 | H13: 0.28982904 | I13: 1.0862479 | J13: 0.28834849 | K13: 1.243839 | L13: 0.43179556 | M13: 0.70671218 | N13: 2.1968804
... A38: Walleye: Walleye Opportunities Fund | B38: 35814.946 | D38: -11.034805 | E38: -5.402721 | F38: -2.7098064 | G38: -3.2854849 | H38: -2.9557736 | I38: -1.4867501 | J38: -0.86936772 | K38: -0.24581457 | L38: -0.26100396 | M38: -0.113609 | N38: 0.83630146

Sheet BOTTOM 10 MANAGERS
A6: =IF(ISBLANK(BottomManagersPerScenario_Data!A$1), "", BottomManagersPerScenario_Data!A$1) -> 2008 Lehman Blow-Up | H6: =IF(ISBLANK(BottomManagersPerScenario_Data!C$1), "", BottomManagersPerScenario_Data!C$1) -> 2002 Market Downturn
A8: =IF(ISBLANK(BottomManagersPerScenario_Data!A2), "", BottomManagersPerScenario_Data!A2) -> Silver Point Capital: Silver Point Distressed Opportunity Institutional Partners + Silver Point HF | D8: =IF(ISBLANK(BottomManagersPerScenario_Data!B2), "", BottomManagersPerScenario_Data!B2) -> -42.289325 | H8: =IF(ISBLANK(BottomManagersPerScenario_Data!C2), "", BottomManagersPerScenario_Data!C2) -> PIMCO: PIMCO Commodity Alpha Fund | K8: =IF(ISBLANK(BottomManagersPerScenario_Data!D2), "", BottomManagersPerScenario_Data!D2) -> -26.684504
A9: =IF(ISBLANK(BottomManagersPerScenario_Data!A3), "", BottomManagersPerScenario_Data!A3) -> LibreMax Partners LP: LibreMax Partners LP | D9: =IF(ISBLANK(BottomManagersPerScenario_Data!B3), "", BottomManagersPerScenario_Data!B3) -> -23.790872 | H9: =IF(ISBLANK(BottomManagersPerScenario_Data!C3), "", BottomManagersPerScenario_Data!C3) -> Silver Point Capital: Silver Point Distressed Opportunity Institutional Partners + Silver Point HF | K9: =IF(ISBLANK(BottomManagersPerScenario_Data!D3), "", BottomManagersPerScenario_Data!D3) -> -23.43874
A10: =IF(ISBLANK(BottomManagersPerScenario_Data!A4), "", BottomManagersPerScenario_Data!A4) -> PIMCO: PIMCO Commodity Alpha Fund | D10: =IF(ISBLANK(BottomManagersPerScenario_Data!B4), "", BottomManagersPerScenario_Data!B4) -> -22.480782 | H10: =IF(ISBLANK(BottomManagersPerScenario_Data!C4), "", BottomManagersPerScenario_Data!C4) -> Rokos Global Macro Fund LP: Rokos Global Macro Fund LP | K10: =IF(ISBLANK(BottomManagersPerScenario_Data!D4), "", BottomManagersPerScenario_Data!D4) -> -17.907609
A11: =IF(ISBLANK(BottomManagersPerScenario_Data!A5), "", BottomManagersPerScenario_Data!A5) -> Saba: CEF1 MN - 2.75x | D11: =IF(ISBLANK(BottomManagersPerScenario_Data!B5), "", BottomManagersPerScenario_Data!B5) -> -22.023037 | H11: =IF(ISBLANK(BottomManagersPerScenario_Data!C5), "", BottomManagersPerScenario_Data!C5) -> Saba: CEF1 MN - 2.75x | K11: =IF(ISBLANK(BottomManagersPerScenario_Data!D5), "", BottomManagersPerScenario_Data!D5) -> -12.305299
A12: =IF(ISBLANK(BottomManagersPerScenario_Data!A6), "", BottomManagersPerScenario_Data!A6) -> Graham Absolute Return Ltd: Graham Absolute Return Ltd | D12: =IF(ISBLANK(BottomManagersPerScenario_Data!B6), "", BottomManagersPerScenario_Data!B6) -> -16.97762 | H12: =IF(ISBLANK(BottomManagersPerScenario_Data!C6), "", BottomManagersPerScenario_Data!C6) -> Graham Absolute Return Ltd: Graham Absolute Return Ltd | K12: =IF(ISBLANK(BottomManagersPerScenario_Data!D6), "", BottomManagersPerScenario_Data!D6) -> -11.838912
A13: =IF(ISBLANK(BottomManagersPerScenario_Data!A7), "", BottomManagersPerScenario_Data!A7) -> Mesarete: Prior TR+back with Pharo Macro+Mesarete Capital Fund | D13: =IF(ISBLANK(BottomManagersPerScenario_Data!B7), "", BottomManagersPerScenario_Data!B7) -> -16.879503 | H13: =IF(ISBLANK(BottomManagersPerScenario_Data!C7), "", BottomManagersPerScenario_Data!C7) -> LibreMax Partners LP: LibreMax Partners LP | K13: =IF(ISBLANK(BottomManagersPerScenario_Data!D7), "", BottomManagersPerScenario_Data!D7) -> -11.817708
A14: =IF(ISBLANK(BottomManagersPerScenario_Data!A8), "", BottomManagersPerScenario_Data!A8) -> King Street Capital LP: King Street Capital LP | D14: =IF(ISBLANK(BottomManagersPerScenario_Data!B8), "", BottomManagersPerScenario_Data!B8) -> -12.537968 | H14: =IF(ISBLANK(BottomManagersPerScenario_Data!C8), "", BottomManagersPerScenario_Data!C8) -> King Street Capital LP: King Street Capital LP | K14: =IF(ISBLANK(BottomManagersPerScenario_Data!D8), "", BottomManagersPerScenario_Data!D8) -> -9.1200007
A15: =IF(ISBLANK(BottomManagersPerScenario_Data!A9), "", BottomManagersPerScenario_Data!A9) -> HF: Current Coinvests (Excluding BH Coinvests) | D15: =IF(ISBLANK(BottomManagersPerScenario_Data!B9), "", BottomManagersPerScenario_Data!B9) -> -11.195902 | H15: =IF(ISBLANK(BottomManagersPerScenario_Data!C9), "", BottomManagersPerScenario_Data!C9) -> Mesarete: Prior TR+back with Pharo Macro+Mesarete Capital Fund | K15: =IF(ISBLANK(BottomManagersPerScenario_Data!D9), "", BottomManagersPerScenario_Data!D9) -> -8.5193266
A16: =IF(ISBLANK(BottomManagersPerScenario_Data!A10), "", BottomManagersPerScenario_Data!A10) -> Walleye: Walleye Opportunities Fund | D16: =IF(ISBLANK(BottomManagersPerScenario_Data!B10), "", BottomManagersPerScenario_Data!B10) -> -11.034805 | H16: =IF(ISBLANK(BottomManagersPerScenario_Data!C10), "", BottomManagersPerScenario_Data!C10) -> HF: Current Coinvests (Excluding BH Coinvests) | K16: =IF(ISBLANK(BottomManagersPerScenario_Data!D10), "", BottomManagersPerScenario_Data!D10) -> -7.2088595
A17: =IF(ISBLANK(BottomManagersPerScenario_Data!A11), "", BottomManagersPerScenario_Data!A11) -> HF: Current Specialty Finance (Excluding Pathfinder) | D17: =IF(ISBLANK(BottomManagersPerScenario_Data!B11), "", BottomManagersPerScenario_Data!B11) -> -10.304767 | H17: =IF(ISBLANK(BottomManagersPerScenario_Data!C11), "", BottomManagersPerScenario_Data!C11) -> Aquatic: Aquatic - Nautilus CFM (Net) | K17: =IF(ISBLANK(BottomManagersPerScenario_Data!D11), "", BottomManagersPerScenario_Data!D11) -> -5.5819151
A20: =IF(ISBLANK(BottomManagersPerScenario_Data!E$1), "", BottomManagersPerScenario_Data!E$1) -> 2001 WTC Attack | H20: =IF(ISBLANK(BottomManagersPerScenario_Data!G$1), "", BottomManagersPerScenario_Data!G$1) -> 1987 Black Monday
A22: =IF(ISBLANK(BottomManagersPerScenario_Data!E2), "", BottomManagersPerScenario_Data!E2) -> Silver Point Capital: Silver Point Distressed Opportunity Institutional Partners + Silver Point HF | D22: =IF(ISBLANK(BottomManagersPerScenario_Data!F2), "", BottomManagersPerScenario_Data!F2) -> -11.380305 | H22: =IF(ISBLANK(BottomManagersPerScenario_Data!G2), "", BottomManagersPerScenario_Data!G2) -> Silver Point Capital: Silver Point Distressed Opportunity Institutional Partners + Silver Point HF | K22: =IF(ISBLANK(BottomManagersPerScenario_Data!H2), "", BottomManagersPerScenario_Data!H2) -> -28.416508
A23: =IF(ISBLANK(BottomManagersPerScenario_Data!E3), "", BottomManagersPerScenario_Data!E3) -> PIMCO: PIMCO Commodity Alpha Fund | D23: =IF(ISBLANK(BottomManagersPerScenario_Data!F3), "", BottomManagersPerScenario_Data!F3) -> -7.9984564 | H23: =IF(ISBLANK(BottomManagersPerScenario_Data!G3), "", BottomManagersPerScenario_Data!G3) -> Aquatic: Aquatic - Nautilus CFM (Net) | K23: =IF(ISBLANK(BottomManagersPerScenario_Data!H3), "", BottomManagersPerScenario_Data!H3) -> -8.6444407
A24: =IF(ISBLANK(BottomManagersPerScenario_Data!E4), "", BottomManagersPerScenario_Data!E4) -> Saba: CEF1 MN - 2.75x | D24: =IF(ISBLANK(BottomManagersPerScenario_Data!F4), "", BottomManagersPerScenario_Data!F4) -> -7.3312916 | H24: =IF(ISBLANK(BottomManagersPerScenario_Data!G4), "", BottomManagersPerScenario_Data!G4) -> PIMCO: PIMCO Commodity Alpha Fund | K24: =IF(ISBLANK(BottomManagersPerScenario_Data!H4), "", BottomManagersPerScenario_Data!H4) -> -8.5078155
A25: =IF(ISBLANK(BottomManagersPerScenario_Data!E5), "", BottomManagersPerScenario_Data!E5) -> LibreMax Partners LP: LibreMax Partners LP | D25: =IF(ISBLANK(BottomManagersPerScenario_Data!F5), "", BottomManagersPerScenario_Data!F5) -> -5.0703637 | H25: =IF(ISBLANK(BottomManagersPerScenario_Data!G5), "", BottomManagersPerScenario_Data!G5) -> King Street Capital LP: King Street Capital LP | K25: =IF(ISBLANK(BottomManagersPerScenario_Data!H5), "", BottomManagersPerScenario_Data!H5) -> -7.6120141
A26: =IF(ISBLANK(BottomManagersPerScenario_Data!E6), "", BottomManagersPerScenario_Data!E6) -> Graham Absolute Return Ltd: Graham Absolute Return Ltd | D26: =IF(ISBLANK(BottomManagersPerScenario_Data!F6), "", BottomManagersPerScenario_Data!F6) -> -4.7514883 | H26: =IF(ISBLANK(BottomManagersPerScenario_Data!G6), "", BottomManagersPerScenario_Data!G6) -> Saba: CEF1 MN - 2.75x | K26: =IF(ISBLANK(BottomManagersPerScenario_Data!H6), "", BottomManagersPerScenario_Data!H6) -> -7.5699809
A27: =IF(ISBLANK(BottomManagersPerScenario_Data!E7), "", BottomManagersPerScenario_Data!E7) -> Mesarete: Prior TR+back with Pharo Macro+Mesarete Capital Fund | D27: =IF(ISBLANK(BottomManagersPerScenario_Data!F7), "", BottomManagersPerScenario_Data!F7) -> -4.4265951 | H27: =IF(ISBLANK(BottomManagersPerScenario_Data!G7), "", BottomManagersPerScenario_Data!G7) -> Graham Absolute Return Ltd: Graham Absolute Return Ltd | K27: =IF(ISBLANK(BottomManagersPerScenario_Data!H7), "", BottomManagersPerScenario_Data!H7) -> -7.5121473
A28: =IF(ISBLANK(BottomManagersPerScenario_Data!E8), "", BottomManagersPerScenario_Data!E8) -> HF: Current Coinvests (Excluding BH Coinvests) | D28: =IF(ISBLANK(BottomManagersPerScenario_Data!F8), "", BottomManagersPerScenario_Data!F8) -> -3.7072377 | H28: =IF(ISBLANK(BottomManagersPerScenario_Data!G8), "", BottomManagersPerScenario_Data!G8) -> 12267: Trexquant Onshore Fund LP | K28: =IF(ISBLANK(BottomManagersPerScenario_Data!H8), "", BottomManagersPerScenario_Data!H8) -> -7.3918503
A29: =IF(ISBLANK(BottomManagersPerScenario_Data!E9), "", BottomManagersPerScenario_Data!E9) -> King Street Capital LP: King Street Capital LP | D29: =IF(ISBLANK(BottomManagersPerScenario_Data!F9), "", BottomManagersPerScenario_Data!F9) -> -3.5747142 | H29: =IF(ISBLANK(BottomManagersPerScenario_Data!G9), "", BottomManagersPerScenario_Data!G9) -> LibreMax Partners LP: LibreMax Partners LP | K29: =IF(ISBLANK(BottomManagersPerScenario_Data!H9), "", BottomManagersPerScenario_Data!H9) -> -4.6811004
A30: =IF(ISBLANK(BottomManagersPerScenario_Data!E10), "", BottomManagersPerScenario_Data!E10) -> Rokos Global Macro Fund LP: Rokos Global Macro Fund LP | D30: =IF(ISBLANK(BottomManagersPerScenario_Data!F10), "", BottomManagersPerScenario_Data!F10) -> -3.4222911 | H30: =IF(ISBLANK(BottomManagersPerScenario_Data!G10), "", BottomManagersPerScenario_Data!G10) -> Voleon Composition Domestic Fund LP: Voleon Composition Domestic Fund LP | K30: =IF(ISBLANK(BottomManagersPerScenario_Data!H10), "", BottomManagersPerScenario_Data!H10) -> -4.5053066
A31: =IF(ISBLANK(BottomManagersPerScenario_Data!E11), "", BottomManagersPerScenario_Data!E11) -> Walleye: Walleye Opportunities Fund | D31: =IF(ISBLANK(BottomManagersPerScenario_Data!F11), "", BottomManagersPerScenario_Data!F11) -> -2.7098064 | H31: =IF(ISBLANK(BottomManagersPerScenario_Data!G11), "", BottomManagersPerScenario_Data!G11) -> HF: Current Coinvests (Excluding BH Coinvests) | K31: =IF(ISBLANK(BottomManagersPerScenario_Data!H11), "", BottomManagersPerScenario_Data!H11) -> -3.334331
A35: =IF(ISBLANK(BottomManagersPerScenario_Data!I$1), "", BottomManagersPerScenario_Data!I$1) -> 1998 Russian Crisis | H35: =IF(ISBLANK(BottomManagersPerScenario_Data!K$1), "", BottomManagersPerScenario_Data!K$1) -> 2008 January Crisis
A37: =IF(ISBLANK(BottomManagersPerScenario_Data!I2), "", BottomManagersPerScenario_Data!I2) -> PIMCO: PIMCO Commodity Alpha Fund | D37: =IF(ISBLANK(BottomManagersPerScenario_Data!J2), "", BottomManagersPerScenario_Data!J2) -> -7.5970198 | H37: =IF(ISBLANK(BottomManagersPerScenario_Data!K2), "", BottomManagersPerScenario_Data!K2) -> PIMCO: PIMCO Commodity Alpha Fund | K37: =IF(ISBLANK(BottomManagersPerScenario_Data!L2), "", BottomManagersPerScenario_Data!L2) -> -7.5670559
A38: =IF(ISBLANK(BottomManagersPerScenario_Data!I3), "", BottomManagersPerScenario_Data!I3) -> Silver Point Capital: Silver Point Distressed Opportunity Institutional Partners + Silver Point HF | D38: =IF(ISBLANK(BottomManagersPerScenario_Data!J3), "", BottomManagersPerScenario_Data!J3) -> -7.345846 | H38: =IF(ISBLANK(BottomManagersPerScenario_Data!K3), "", BottomManagersPerScenario_Data!K3) -> Saba: CEF1 MN - 2.75x | K38: =IF(ISBLANK(BottomManagersPerScenario_Data!L3), "", BottomManagersPerScenario_Data!L3) -> -5.3643522
A39: =IF(ISBLANK(BottomManagersPerScenario_Data!I4), "", BottomManagersPerScenario_Data!I4) -> Saba: CEF1 MN - 2.75x | D39: =IF(ISBLANK(BottomManagersPerScenario_Data!J4), "", BottomManagersPerScenario_Data!J4) -> -7.1881349 | H39: =IF(ISBLANK(BottomManagersPerScenario_Data!K4), "", BottomManagersPerScenario_Data!K4) -> Silver Point Capital: Silver Point Distressed Opportunity Institutional Partners + Silver Point HF | K39: =IF(ISBLANK(BottomManagersPerScenario_Data!L4), "", BottomManagersPerScenario_Data!L4) -> -4.527934
A40: =IF(ISBLANK(BottomManagersPerScenario_Data!I5), "", BottomManagersPerScenario_Data!I5) -> LibreMax Partners LP: LibreMax Partners LP | D40: =IF(ISBLANK(BottomManagersPerScenario_Data!J5), "", BottomManagersPerScenario_Data!J5) -> -7.0528825 | H40: =IF(ISBLANK(BottomManagersPerScenario_Data!K5), "", BottomManagersPerScenario_Data!K5) -> Rokos Global Macro Fund LP: Rokos Global Macro Fund LP | K40: =IF(ISBLANK(BottomManagersPerScenario_Data!L5), "", BottomManagersPerScenario_Data!L5) -> -3.6627768
A41: =IF(ISBLANK(BottomManagersPerScenario_Data!I6), "", BottomManagersPerScenario_Data!I6) -> Graham Absolute Return Ltd: Graham Absolute Return Ltd | D41: =IF(ISBLANK(BottomManagersPerScenario_Data!J6), "", BottomManagersPerScenario_Data!J6) -> -5.4571408 | H41: =IF(ISBLANK(BottomManagersPerScenario_Data!K6), "", BottomManagersPerScenario_Data!K6) -> HF: Current Coinvests (Excluding BH Coinvests) | K41: =IF(ISBLANK(BottomManagersPerScenario_Data!L6), "", BottomManagersPerScenario_Data!L6) -> -3.2731405
A42: =IF(ISBLANK(BottomManagersPerScenario_Data!I7), "", BottomManagersPerScenario_Data!I7) -> King Street Capital LP: King Street Capital LP | D42: =IF(ISBLANK(BottomManagersPerScenario_Data!J7), "", BottomManagersPerScenario_Data!J7) -> -4.299804 | H42: =IF(ISBLANK(BottomManagersPerScenario_Data!K7), "", BottomManagersPerScenario_Data!K7) -> LibreMax Partners LP: LibreMax Partners LP | K42: =IF(ISBLANK(BottomManagersPerScenario_Data!L7), "", BottomManagersPerScenario_Data!L7) -> -3.1157384
A43: =IF(ISBLANK(BottomManagersPerScenario_Data!I8), "", BottomManagersPerScenario_Data!I8) -> Mesarete: Prior TR+back with Pharo Macro+Mesarete Capital Fund | D43: =IF(ISBLANK(BottomManagersPerScenario_Data!J8), "", BottomManagersPerScenario_Data!J8) -> -4.14923 | H43: =IF(ISBLANK(BottomManagersPerScenario_Data!K8), "", BottomManagersPerScenario_Data!K8) -> Mesarete: Prior TR+back with Pharo Macro+Mesarete Capital Fund | K43: =IF(ISBLANK(BottomManagersPerScenario_Data!L8), "", BottomManagersPerScenario_Data!L8) -> -2.8373037
A44: =IF(ISBLANK(BottomManagersPerScenario_Data!I9), "", BottomManagersPerScenario_Data!I9) -> Aquatic: Aquatic - Nautilus CFM (Net) | D44: =IF(ISBLANK(BottomManagersPerScenario_Data!J9), "", BottomManagersPerScenario_Data!J9) -> -3.9520856 | H44: =IF(ISBLANK(BottomManagersPerScenario_Data!K9), "", BottomManagersPerScenario_Data!K9) -> Graham Absolute Return Ltd: Graham Absolute Return Ltd | K44: =IF(ISBLANK(BottomManagersPerScenario_Data!L9), "", BottomManagersPerScenario_Data!L9) -> -2.7260681
A45: =IF(ISBLANK(BottomManagersPerScenario_Data!I10), "", BottomManagersPerScenario_Data!I10) -> HF: Current Coinvests (Excluding BH Coinvests) | D45: =IF(ISBLANK(BottomManagersPerScenario_Data!J10), "", BottomManagersPerScenario_Data!J10) -> -3.1258404 | H45: =IF(ISBLANK(BottomManagersPerScenario_Data!K10), "", BottomManagersPerScenario_Data!K10) -> King Street Capital LP: King Street Capital LP | K45: =IF(ISBLANK(BottomManagersPerScenario_Data!L10), "", BottomManagersPerScenario_Data!L10) -> -2.1208446
A46: =IF(ISBLANK(BottomManagersPerScenario_Data!I11), "", BottomManagersPerScenario_Data!I11) -> Walleye: Walleye Opportunities Fund | D46: =IF(ISBLANK(BottomManagersPerScenario_Data!J11), "", BottomManagersPerScenario_Data!J11) -> -2.9557736 | H46: =IF(ISBLANK(BottomManagersPerScenario_Data!K11), "", BottomManagersPerScenario_Data!K11) -> Aquatic: Aquatic - Nautilus CFM (Net) | K46: =IF(ISBLANK(BottomManagersPerScenario_Data!L11), "", BottomManagersPerScenario_Data!L11) -> -1.6919121
A67: =IF(ISBLANK(BottomManagersPerScenario_Data!M$1), "", BottomManagersPerScenario_Data!M$1) -> 2007 August Crisis | H67: =IF(ISBLANK(BottomManagersPerScenario_Data!O$1), "", BottomManagersPerScenario_Data!O$1) -> 2001 Nasdaq
A69: =IF(ISBLANK(BottomManagersPerScenario_Data!M2), "", BottomManagersPerScenario_Data!M2) -> Saba: CEF1 MN - 2.75x | D69: =IF(ISBLANK(BottomManagersPerScenario_Data!N2), "", BottomManagersPerScenario_Data!N2) -> -3.8341475 | H69: =IF(ISBLANK(BottomManagersPerScenario_Data!O2), "", BottomManagersPerScenario_Data!O2) -> Silver Point Capital: Silver Point Distressed Opportunity Institutional Partners + Silver Point HF | K69: =IF(ISBLANK(BottomManagersPerScenario_Data!P2), "", BottomManagersPerScenario_Data!P2) -> -8.6402481
A70: =IF(ISBLANK(BottomManagersPerScenario_Data!M3), "", BottomManagersPerScenario_Data!M3) -> PIMCO: PIMCO Commodity Alpha Fund | D70: =IF(ISBLANK(BottomManagersPerScenario_Data!N3), "", BottomManagersPerScenario_Data!N3) -> -3.5451571 | H70: =IF(ISBLANK(BottomManagersPerScenario_Data!O3), "", BottomManagersPerScenario_Data!O3) -> PIMCO: PIMCO Commodity Alpha Fund | K70: =IF(ISBLANK(BottomManagersPerScenario_Data!P3), "", BottomManagersPerScenario_Data!P3) -> -4.5800419
A71: =IF(ISBLANK(BottomManagersPerScenario_Data!M4), "", BottomManagersPerScenario_Data!M4) -> LibreMax Partners LP: LibreMax Partners LP | D71: =IF(ISBLANK(BottomManagersPerScenario_Data!N4), "", BottomManagersPerScenario_Data!N4) -> -2.5716398 | H71: =IF(ISBLANK(BottomManagersPerScenario_Data!O4), "", BottomManagersPerScenario_Data!O4) -> Mesarete: Prior TR+back with Pharo Macro+Mesarete Capital Fund | K71: =IF(ISBLANK(BottomManagersPerScenario_Data!P4), "", BottomManagersPerScenario_Data!P4) -> -3.0934759
A72: =IF(ISBLANK(BottomManagersPerScenario_Data!M5), "", BottomManagersPerScenario_Data!M5) -> Mesarete: Prior TR+back with Pharo Macro+Mesarete Capital Fund | D72: =IF(ISBLANK(BottomManagersPerScenario_Data!N5), "", BottomManagersPerScenario_Data!N5) -> -2.3252195 | H72: =IF(ISBLANK(BottomManagersPerScenario_Data!O5), "", BottomManagersPerScenario_Data!O5) -> HF: Current Coinvests (Excluding BH Coinvests) | K72: =IF(ISBLANK(BottomManagersPerScenario_Data!P5), "", BottomManagersPerScenario_Data!P5) -> -2.3753222
A73: =IF(ISBLANK(BottomManagersPerScenario_Data!M6), "", BottomManagersPerScenario_Data!M6) -> Aquatic: Aquatic - Nautilus CFM (Net) | D73: =IF(ISBLANK(BottomManagersPerScenario_Data!N6), "", BottomManagersPerScenario_Data!N6) -> -2.235365 | H73: =IF(ISBLANK(BottomManagersPerScenario_Data!O6), "", BottomManagersPerScenario_Data!O6) -> Saba: CEF1 MN - 2.75x | K73: =IF(ISBLANK(BottomManagersPerScenario_Data!P6), "", BottomManagersPerScenario_Data!P6) -> -2.1782199
A74: =IF(ISBLANK(BottomManagersPerScenario_Data!M7), "", BottomManagersPerScenario_Data!M7) -> HF: Current Coinvests (Excluding BH Coinvests) | D74: =IF(ISBLANK(BottomManagersPerScenario_Data!N7), "", BottomManagersPerScenario_Data!N7) -> -2.1878497 | H74: =IF(ISBLANK(BottomManagersPerScenario_Data!O7), "", BottomManagersPerScenario_Data!O7) -> King Street Capital LP: King Street Capital LP | K74: =IF(ISBLANK(BottomManagersPerScenario_Data!P7), "", BottomManagersPerScenario_Data!P7) -> -1.9508288
A75: =IF(ISBLANK(BottomManagersPerScenario_Data!M8), "", BottomManagersPerScenario_Data!M8) -> Graham Absolute Return Ltd: Graham Absolute Return Ltd | D75: =IF(ISBLANK(BottomManagersPerScenario_Data!N8), "", BottomManagersPerScenario_Data!N8) -> -1.9894529 | H75: =IF(ISBLANK(BottomManagersPerScenario_Data!O8), "", BottomManagersPerScenario_Data!O8) -> LibreMax Partners LP: LibreMax Partners LP | K75: =IF(ISBLANK(BottomManagersPerScenario_Data!P8), "", BottomManagersPerScenario_Data!P8) -> -1.7613745
A76: =IF(ISBLANK(BottomManagersPerScenario_Data!M9), "", BottomManagersPerScenario_Data!M9) -> King Street Capital LP: King Street Capital LP | D76: =IF(ISBLANK(BottomManagersPerScenario_Data!N9), "", BottomManagersPerScenario_Data!N9) -> -1.8782169 | H76: =IF(ISBLANK(BottomManagersPerScenario_Data!O9), "", BottomManagersPerScenario_Data!O9) -> Aquatic: Aquatic - Nautilus CFM (Net) | K76: =IF(ISBLANK(BottomManagersPerScenario_Data!P9), "", BottomManagersPerScenario_Data!P9) -> -1.6731249
A77: =IF(ISBLANK(BottomManagersPerScenario_Data!M10), "", BottomManagersPerScenario_Data!M10) -> Walleye: Walleye Opportunities Fund | D77: =IF(ISBLANK(BottomManagersPerScenario_Data!N10), "", BottomManagersPerScenario_Data!N10) -> -0.86936772 | H77: =IF(ISBLANK(BottomManagersPerScenario_Data!O10), "", BottomManagersPerScenario_Data!O10) -> Graham Absolute Return Ltd: Graham Absolute Return Ltd | K77: =IF(ISBLANK(BottomManagersPerScenario_Data!P10), "", BottomManagersPerScenario_Data!P10) -> -1.6232624
A78: =IF(ISBLANK(BottomManagersPerScenario_Data!M11), "", BottomManagersPerScenario_Data!M11) -> Dockside: I-94 Minus Standalones | D78: =IF(ISBLANK(BottomManagersPerScenario_Data!N11), "", BottomManagersPerScenario_Data!N11) -> -0.73111112 | H78: =IF(ISBLANK(BottomManagersPerScenario_Data!O11), "", BottomManagersPerScenario_Data!O11) -> Voleon Composition Domestic Fund LP: Voleon Composition Domestic Fund LP | K78: =IF(ISBLANK(BottomManagersPerScenario_Data!P11), "", BottomManagersPerScenario_Data!P11) -> -1.4624458
A81: =IF(ISBLANK(BottomManagersPerScenario_Data!Q$1), "", BottomManagersPerScenario_Data!Q$1) -> 1997 - 1998 Asian Crisis | H81: =IF(ISBLANK(BottomManagersPerScenario_Data!S$1), "", BottomManagersPerScenario_Data!S$1) -> 1990 Kuwait Invasion
A83: =IF(ISBLANK(BottomManagersPerScenario_Data!Q2), "", BottomManagersPerScenario_Data!Q2) -> PIMCO: PIMCO Commodity Alpha Fund | D83: =IF(ISBLANK(BottomManagersPerScenario_Data!R2), "", BottomManagersPerScenario_Data!R2) -> -2.779568 | H83: =IF(ISBLANK(BottomManagersPerScenario_Data!S2), "", BottomManagersPerScenario_Data!S2) -> Rokos Global Macro Fund LP: Rokos Global Macro Fund LP | K83: =IF(ISBLANK(BottomManagersPerScenario_Data!T2), "", BottomManagersPerScenario_Data!T2) -> -7.6864085
A84: =IF(ISBLANK(BottomManagersPerScenario_Data!Q3), "", BottomManagersPerScenario_Data!Q3) -> Aquatic: Aquatic - Nautilus CFM (Net) | D84: =IF(ISBLANK(BottomManagersPerScenario_Data!R3), "", BottomManagersPerScenario_Data!R3) -> -1.5928982 | H84: =IF(ISBLANK(BottomManagersPerScenario_Data!S3), "", BottomManagersPerScenario_Data!S3) -> PIMCO: PIMCO Commodity Alpha Fund | K84: =IF(ISBLANK(BottomManagersPerScenario_Data!T3), "", BottomManagersPerScenario_Data!T3) -> -6.1479654
A85: =IF(ISBLANK(BottomManagersPerScenario_Data!Q4), "", BottomManagersPerScenario_Data!Q4) -> Rokos Global Macro Fund LP: Rokos Global Macro Fund LP | D85: =IF(ISBLANK(BottomManagersPerScenario_Data!R4), "", BottomManagersPerScenario_Data!R4) -> -1.3056845 | H85: =IF(ISBLANK(BottomManagersPerScenario_Data!S4), "", BottomManagersPerScenario_Data!S4) -> Aquatic: Aquatic - Nautilus CFM (Net) | K85: =IF(ISBLANK(BottomManagersPerScenario_Data!T4), "", BottomManagersPerScenario_Data!T4) -> -2.9249691
A86: =IF(ISBLANK(BottomManagersPerScenario_Data!Q5), "", BottomManagersPerScenario_Data!Q5) -> King Street Capital LP: King Street Capital LP | D86: =IF(ISBLANK(BottomManagersPerScenario_Data!R5), "", BottomManagersPerScenario_Data!R5) -> -1.2404076 | H86: =IF(ISBLANK(BottomManagersPerScenario_Data!S5), "", BottomManagersPerScenario_Data!S5) -> Saba: CEF1 MN - 2.75x | K86: =IF(ISBLANK(BottomManagersPerScenario_Data!T5), "", BottomManagersPerScenario_Data!T5) -> -2.5962676
A87: =IF(ISBLANK(BottomManagersPerScenario_Data!Q6), "", BottomManagersPerScenario_Data!Q6) -> Mesarete: Prior TR+back with Pharo Macro+Mesarete Capital Fund | D87: =IF(ISBLANK(BottomManagersPerScenario_Data!R6), "", BottomManagersPerScenario_Data!R6) -> -1.1603701 | H87: =IF(ISBLANK(BottomManagersPerScenario_Data!S6), "", BottomManagersPerScenario_Data!S6) -> Brevan Howard MB Macro Fund: Brevan Howard MB Macro Fund with proforma | K87: =IF(ISBLANK(BottomManagersPerScenario_Data!T6), "", BottomManagersPerScenario_Data!T6) -> -2.1274732
A88: =IF(ISBLANK(BottomManagersPerScenario_Data!Q7), "", BottomManagersPerScenario_Data!Q7) -> Graham Absolute Return Ltd: Graham Absolute Return Ltd | D88: =IF(ISBLANK(BottomManagersPerScenario_Data!R7), "", BottomManagersPerScenario_Data!R7) -> -0.99289454 | H88: =IF(ISBLANK(BottomManagersPerScenario_Data!S7), "", BottomManagersPerScenario_Data!S7) -> Taula: SWIB-DM Taula | K88: =IF(ISBLANK(BottomManagersPerScenario_Data!T7), "", BottomManagersPerScenario_Data!T7) -> -2.0773847
A89: =IF(ISBLANK(BottomManagersPerScenario_Data!Q8), "", BottomManagersPerScenario_Data!Q8) -> Saba: CEF1 MN - 2.75x | D89: =IF(ISBLANK(BottomManagersPerScenario_Data!R8), "", BottomManagersPerScenario_Data!R8) -> -0.90446584 | H89: =IF(ISBLANK(BottomManagersPerScenario_Data!S8), "", BottomManagersPerScenario_Data!S8) -> King Street Capital LP: King Street Capital LP | K89: =IF(ISBLANK(BottomManagersPerScenario_Data!T8), "", BottomManagersPerScenario_Data!T8) -> -1.6355198
A90: =IF(ISBLANK(BottomManagersPerScenario_Data!Q9), "", BottomManagersPerScenario_Data!Q9) -> HF: Current Coinvests (Excluding BH Coinvests) | D90: =IF(ISBLANK(BottomManagersPerScenario_Data!R9), "", BottomManagersPerScenario_Data!R9) -> -0.76868296 | H90: =IF(ISBLANK(BottomManagersPerScenario_Data!S9), "", BottomManagersPerScenario_Data!S9) -> Brevan Howard Coinvests (Aksia): Brevan Howard Special Opportunities SPC | K90: =IF(ISBLANK(BottomManagersPerScenario_Data!T9), "", BottomManagersPerScenario_Data!T9) -> -1.5587523
A91: =IF(ISBLANK(BottomManagersPerScenario_Data!Q10), "", BottomManagersPerScenario_Data!Q10) -> Voleon Composition Domestic Fund LP: Voleon Composition Domestic Fund LP | D91: =IF(ISBLANK(BottomManagersPerScenario_Data!R10), "", BottomManagersPerScenario_Data!R10) -> -0.47735816 | H91: =IF(ISBLANK(BottomManagersPerScenario_Data!S10), "", BottomManagersPerScenario_Data!S10) -> HF: Current Coinvests (Excluding BH Coinvests) | K91: =IF(ISBLANK(BottomManagersPerScenario_Data!T10), "", BottomManagersPerScenario_Data!T10) -> -1.4819289
A92: =IF(ISBLANK(BottomManagersPerScenario_Data!Q11), "", BottomManagersPerScenario_Data!Q11) -> Taula: SWIB-DM Taula | D92: =IF(ISBLANK(BottomManagersPerScenario_Data!R11), "", BottomManagersPerScenario_Data!R11) -> -0.37912509 | H92: =IF(ISBLANK(BottomManagersPerScenario_Data!S11), "", BottomManagersPerScenario_Data!S11) -> Graham Absolute Return Ltd: Graham Absolute Return Ltd | K92: =IF(ISBLANK(BottomManagersPerScenario_Data!T11), "", BottomManagersPerScenario_Data!T11) -> -1.0988993
A96: =IF(ISBLANK(BottomManagersPerScenario_Data!U$1), "", BottomManagersPerScenario_Data!U$1) -> 2005 Katrina
A98: =IF(ISBLANK(BottomManagersPerScenario_Data!U2), "", BottomManagersPerScenario_Data!U2) -> Silver Point Capital: Silver Point Distressed Opportunity Institutional Partners + Silver Point HF | D98: =IF(ISBLANK(BottomManagersPerScenario_Data!V2), "", BottomManagersPerScenario_Data!V2) -> -2.802416
A99: =IF(ISBLANK(BottomManagersPerScenario_Data!U3), "", BottomManagersPerScenario_Data!U3) -> PIMCO: PIMCO Commodity Alpha Fund | D99: =IF(ISBLANK(BottomManagersPerScenario_Data!V3), "", BottomManagersPerScenario_Data!V3) -> -1.2212106
A100: =IF(ISBLANK(BottomManagersPerScenario_Data!U4), "", BottomManagersPerScenario_Data!U4) -> Aquatic: Aquatic - Nautilus CFM (Net) | D100: =IF(ISBLANK(BottomManagersPerScenario_Data!V4), "", BottomManagersPerScenario_Data!V4) -> -1.199001
A101: =IF(ISBLANK(BottomManagersPerScenario_Data!U5), "", BottomManagersPerScenario_Data!U5) -> HF: Current Coinvests (Excluding BH Coinvests) | D101: =IF(ISBLANK(BottomManagersPerScenario_Data!V5), "", BottomManagersPerScenario_Data!V5) -> -0.912812
A102: =IF(ISBLANK(BottomManagersPerScenario_Data!U6), "", BottomManagersPerScenario_Data!U6) -> Mesarete: Prior TR+back with Pharo Macro+Mesarete Capital Fund | D102: =IF(ISBLANK(BottomManagersPerScenario_Data!V6), "", BottomManagersPerScenario_Data!V6) -> -0.86863254
A103: =IF(ISBLANK(BottomManagersPerScenario_Data!U7), "", BottomManagersPerScenario_Data!U7) -> Hudson Structured: HSCM w MFC | D103: =IF(ISBLANK(BottomManagersPerScenario_Data!V7), "", BottomManagersPerScenario_Data!V7) -> -0.73264088
A104: =IF(ISBLANK(BottomManagersPerScenario_Data!U8), "", BottomManagersPerScenario_Data!U8) -> Saba: CEF1 MN - 2.75x | D104: =IF(ISBLANK(BottomManagersPerScenario_Data!V8), "", BottomManagersPerScenario_Data!V8) -> -0.18303598
A105: =IF(ISBLANK(BottomManagersPerScenario_Data!U9), "", BottomManagersPerScenario_Data!U9) -> King Street Capital LP: King Street Capital LP | D105: =IF(ISBLANK(BottomManagersPerScenario_Data!V9), "", BottomManagersPerScenario_Data!V9) -> -0.15866769
A106: =IF(ISBLANK(BottomManagersPerScenario_Data!U10), "", BottomManagersPerScenario_Data!U10) -> LibreMax Partners LP: LibreMax Partners LP | D106: =IF(ISBLANK(BottomManagersPerScenario_Data!V10), "", BottomManagersPerScenario_Data!V10) -> 0.028230379
A107: =IF(ISBLANK(BottomManagersPerScenario_Data!U11), "", BottomManagersPerScenario_Data!U11) -> Four World: FWGO Minority Descent | D107: =IF(ISBLANK(BottomManagersPerScenario_Data!V11), "", BottomManagersPerScenario_Data!V11) -> 0.20936444

Sheet BOTTOM 10 MANAGERS_OLD
A6: =IF(ISBLANK(BottomManagersPerScenario_Data!A$1), "", BottomManagersPerScenario_Data!A$1) -> 2008 Lehman Blow-Up | H6: =IF(ISBLANK(BottomManagersPerScenario_Data!C$1), "", BottomManagersPerScenario_Data!C$1) -> 2002 Market Downturn
A20: =IF(ISBLANK(BottomManagersPerScenario_Data!E$1), "", BottomManagersPerScenario_Data!E$1) -> 2001 WTC Attack | H20: =IF(ISBLANK(BottomManagersPerScenario_Data!G$1), "", BottomManagersPerScenario_Data!G$1) -> 1987 Black Monday
A35: =IF(ISBLANK(BottomManagersPerScenario_Data!I$1), "", BottomManagersPerScenario_Data!I$1) -> 1998 Russian Crisis | H35: =IF(ISBLANK(BottomManagersPerScenario_Data!K$1), "", BottomManagersPerScenario_Data!K$1) -> 2008 January Crisis
A67: =IF(ISBLANK(BottomManagersPerScenario_Data!M$1), "", BottomManagersPerScenario_Data!M$1) -> 2007 August Crisis | H67: =IF(ISBLANK(BottomManagersPerScenario_Data!O$1), "", BottomManagersPerScenario_Data!O$1) -> 2001 Nasdaq
A81: =IF(ISBLANK(BottomManagersPerScenario_Data!Q$1), "", BottomManagersPerScenario_Data!Q$1) -> 1997 - 1998 Asian Crisis | H81: =IF(ISBLANK(BottomManagersPerScenario_Data!S$1), "", BottomManagersPerScenario_Data!S$1) -> 1990 Kuwait Invasion
A96: =IF(ISBLANK(BottomManagersPerScenario_Data!U$1), "", BottomManagersPerScenario_Data!U$1) -> 2005 Katrina

Sheet STRESSED FACTOR VALUES
A4: STRESSED FACTOR VALUES
A5: The table shows the return of each factor under each of the stress scenarios. The stress test scenarios are ordered by most negative impact on the portfolio value.
A8: Factor Name | J8: First Date | L8: Last Date | N8: 2008 Lehman Blow-Up | P8: 2002 Market Downturn | R8: 2001 WTC Attack | T8: 1987 Black Monday | V8: 1998 Russian Crisis | X8: 2008 January Crisis | Z8: 2007 August Crisis | AB8: 2001 Nasdaq | AD8: 1997 - 1998 Asian Crisis | AF8: 1990 Kuwait Invasion | AH8: 2005 Katrina
A9: CBOE Volatility Index as Difference USD | J9: 01/02/1990 | L9: 06/24/2026 | N9: 80.164475 | P9: 27.672729 | R9: 19.410864 | T9: 117.48666 | V9: 32.379154 | X9: 7.7022188 | Z9: 16.695758 | AB9: 10.461847 | AD9: 11.438201 | AF9: 21.798761 | AH9: 4.5923262
A10: ML Global Govt Bond II USD | J10: 12/31/1985 | L10: 06/24/2026 | N10: -0.08 | P10: 10.12 | R10: 1.03 | T10: -11 | V10: 2.71 | X10: 2.72 | Z10: 1.26 | AB10: -2.19 | AD10: -0.13 | AF10: 0.72 | AH10: -4.49
A11: ML Global High Yield - AAA Spread USD | J11: 12/31/1997 | L11: 06/24/2026 | N11: -23.875963 | P11: -21.258553 | R11: -6.73656 | T11: -5.19 | V11: -6.5291933 | X11: -4.7518757 | Z11: -2.0517506 | AB11: -3.61963 | AD11: -1.19 | AF11: -0.22 | AH11: 0.63260296
A12: MSCI Small Minus Large World USD | J12: 12/31/1998 | L12: 06/24/2026 | N12: -9.7951091 | P12: -2.8914275 | R12: -2.4496216 | T12: -7.1 | V12: -7.46 | X12: -2.650743 | Z12: -3.4120755 | AB12: 3.3385106 | AD12: -0.69 | AF12: -4.22 | AH12: -1.4456326
A13: MSCI The World USD | J13: 12/31/1969 | L13: 06/24/2026 | N13: -41.553149 | P13: -28.709594 | R13: -15.706591 | T13: -14.22 | V13: -13.38 | X13: -13.974127 | Z13: -9.5212887 | AB13: -10.303014 | AD13: -3.43 | AF13: -6.53 | AH13: -4.0627948
A14: MSCI Value Minus Growth World USD | J14: 12/31/1974 | L14: 06/24/2026 | N14: 4.2827831 | P14: -9.1450871 | R14: -0.96450934 | T14: 0.88 | V14: -3.79 | X14: 0.33155771 | Z14: -0.75002096 | AB14: 3.2717714 | AD14: 1.57 | AF14: 0.24 | AH14: -0.16211163
A15: S&P GSCI Index | J15: 12/31/1969 | L15: 06/24/2026 | N15: -47.49224 | P15: 7.7702908 | R15: -5.0109745 | T15: 0.35779315 | V15: -10.070598 | X15: 1.2295472 | Z15: -3.6446628 | AB15: -4.3141756 | AD15: 4.1016092 | AF15: 33.35891 | AH15: 0.51079802
A16: Trade Weighted Exchange Index: Broad | J16: 01/04/1995 | L16: 06/24/2026 | N16: 12.253238 | P16: 0.6303469 | R16: 0.89052681 | T16: -1.79 | V16: 2.6537724 | X16: -0.057771648 | Z16: 1.5692615 | AB16: 1.9970962 | AD16: 1.4033572 | AF16: -2.86 | AH16: 2.0917
A17: US Treasury 10Yr - 2Yr Spread USD | J17: 06/01/1976 | L17: 06/24/2026 | N17: 0.62 | P17: 0.03 | R17: 0.58 | T17: 0.19 | V17: 0.09 | X17: 0.4 | Z17: 0.25 | AB17: 0.33 | AD17: 0.02 | AF17: 0.45 | AH17: -0.02

Sheet FACTOR ANALYSIS
A4: MULTIFACTOR REGRESSION
A5: The Stepwise Selection Method runs a stepwise regression (forward and backward). The process automatically selects a subset of factors in your model for each asset that provides the highest explanatory power with respect to the assets in your portfolio with the smallest number of factors permissible.
A8: BETA | D8: P-VALUE | G8: Current 7.26 | I8: 12267: Trexquant Onshore Fund LP | K8: Aquatic: Aquatic - Nautilus CFM (Net) | M8: Ares: Ares Pathfinder II | O8: Bayview Asset Management: MSR Fund | Q8: Benefit Street Partners: Benefit Street Partners Origination Fund (CCFLX) | S8: BlackRock: GAO | U8: Blackstone: Badgerstone Access | W8: Blue Owl: Blue Owl Funding Partners (CCLFX) | Y8: Brevan Howard Coinvests (Aksia): Brevan Howard Special Opportunities SPC | AA8: Brevan Howard MB Macro Fund: Brevan Howard MB Macro Fund with proforma | AC8: D. E. Shaw: Cogence | AE8: DE Shaw Composite Fund LLC: DE Shaw Composite Fund LLC | AG8: DYAL: DYAL II - Aksia
A10: R2 | G10: 0.41378505 | I10: 0.20840771 | K10: 0.042751854 | M10: 0.075344681 | O10: 0.43107912 | Q10: 0.057216329 | S10: 0.030866626 | U10: 0.13272928 | W10: 0.18758193 | Y10: 0.10272776 | AA10: 0.16189766 | AC10: 0.27264158 | AE10: 0.18703903 | AG10: 0.080299424
A11: Residual Standard Error | I11: 0.025361626 | K11: 0.032872586 | M11: 0.023300406 | O11: 0.0065648524 | Q11: 0.011305304 | S11: 0.025173662 | U11: 0.008416506 | W11: 0.0094566005 | Y11: 0.040176379 | AA11: 0.015326195 | AC11: 0.023845298 | AE11: 0.0092204551 | AG11: 0.034597367
A12: @Intercept | G12: 0.0081733237 | I12: 0.0083265545 | J12: 0.0053970508 | K12: -0.0064620852 | L12: 0.080717208 | M12: 0.0081395288 | N12: 0.0030178498 | O12: 0.0068821039 | P12: 9.2121474e-14 | Q12: 0.0080223561 | R12: 2.2081391e-08 | S12: 0.010812431 | T12: 0.00031852483 | U12: 0.0088013021 | V12: 1.9101539e-14 | W12: 0.0074852124 | X12: 9.036307e-10 | AA12: 0.01012919 | AB12: 1.3902573e-07 | AC12: 0.014304991 | AD12: 1.5097852e-06 | AE12: 0.013825025 | AF12: 4.8984773e-22 | AG12: 0.012811322 | AH12: 0.0014813852
A13: CBOE Volatility Index as Difference USD | G13: -0.0048516357 | I13: -0.11287884 | J13: 0.026720537 | K13: -0.10986426 | L13: 0.064021319 | U13: -0.048146916 | V13: 0.0025122669 | Y13: 0.11485112 | Z13: 0.12693183 | AC13: 0.10436238 | AD13: 0.022221133 | AE13: -0.044589749 | AF13: 0.010007209
A14: ML Global Govt Bond II USD | G14: -0.042907993 | U14: -0.095423177 | V14: 0.032447602 | AE14: -0.18459191 | AF14: 0.000244276 | AG14: -0.46429235 | AH14: 0.016858421
A15: ML Global High Yield - AAA Spread USD | G15: 0.20128462 | I15: 0.25860753 | J15: 0.081138101 | O15: 0.10715607 | P15: 0.024147825 | AC15: 0.54223712 | AD15: 0.00021757966 | AG15: -0.3459705 | AH15: 0.075463677
A16: MSCI Small Minus Large World USD | G16: 0.037744728 | I16: -0.32653177 | J16: 0.018622044 | M16: -0.20966127 | N16: 0.069776138 | O16: 0.081490673 | P16: 0.02477932 | AA16: 0.12410118 | AB16: 0.10203384 | AC16: 0.23272791 | AD16: 0.078414726
A17: MSCI The World USD | G17: 0.014730596 | Q17: 0.058182908 | R17: 0.031503109 | S17: 0.093855218 | T17: 0.11668187
A18: MSCI Value Minus Growth World USD | G18: -0.013749978 | O18: -0.037106599 | P18: 0.10750128 | W18: -0.066732685 | X18: 0.032367466 | AC18: -0.30149026 | AD18: 0.00049546268
A19: S&P GSCI Index | G19: -0.011900747 | M19: 0.088817862 | N19: 0.026232091 | O19: 0.042475338 | P19: 0.0034495104 | W19: 0.065835003 | X19: 7.9713398e-05 | Y19: -0.13324907 | Z19: 0.043941826 | AA19: -0.099786411 | AB19: 0.00022435873
A20: Trade Weighted Exchange Index: Broad | G20: 0.004376476 | I20: 0.44244025 | J20: 0.036674749
A21: US Treasury 10Yr - 2Yr Spread USD | G21: 0.00071919361 | I21: 0.011205231 | J21: 0.12686712
A41: BETA | D41: P-VALUE | G41: Dockside: I-94 Minus Standalones | I41: Dorsal Capital Partners LP: Dorsal Capital Partners LP | K41: Elliott Associates LP: Elliott Associates LP | M41: Four World: FWGO | O41: Four World: FWGO Minority Descent | Q41: Graham Absolute Return Ltd: Graham Absolute Return Ltd | S41: HF: Current Coinvests (Excluding BH Coinvests) | U41: HF: Current Specialty Finance (Excluding Pathfinder) | W41: Holocene: Holocene Advisors Master | Y41: Hudson Structured: HSCM w MFC | AA41: King Street Capital LP: King Street Capital LP | AC41: LibreMax CLO: LibreMax CLO | AE41: LibreMax Partners LP: LibreMax Partners LP | AG41: Mesarete: Prior TR+back with Pharo Macro+Mesarete Capital Fund
A43: R2 | G43: 0.2859666 | I43: 0.25145522 | K43: 0.1767807 | M43: 0.046681493 | O43: 0.16813729 | Q43: 0.42465465 | S43: 0.077443379 | U43: 0.51144671 | W43: 0.012178216 | Y43: 0.011230513 | AA43: 0.29548286 | AC43: 0.0091580468 | AE43: 0.50118968 | AG43: 0.4873213
A44: Residual Standard Error | G44: 0.018360597 | I44: 0.017021766 | K44: 0.006918881 | M44: 0.019775424 | O44: 0.012728748 | Q44: 0.018361286 | S44: 0.037265718 | U44: 0.010802863 | W44: 0.020377117 | Y44: 0.033284565 | AA44: 0.014962448 | AC44: 0.034977557 | AE44: 0.024465667 | AG44: 0.016063138
A45: @Intercept | G45: 0.009875161 | H45: 1.1149778e-05 | I45: 0.0042838943 | J45: 0.02959123 | K45: 0.0068687692 | L45: 4.380325e-13 | M45: 0.0089617334 | N45: 0.00011805908 | O45: 0.0054510281 | P45: 0.00027492388 | Q45: 0.0056107856 | R45: 0.0093092421 | U45: 0.0074367317 | V45: 7.2277671e-08 | W45: 0.0082866063 | X45: 0.0004915225 | AG45: 0.0034446771 | AH45: 0.071364302
A46: CBOE Volatility Index as Difference USD | K46: 0.026333743 | L46: 0.060419756 | Q46: -0.05380226 | R46: 0.11654137 | AA46: -0.080068095 | AB46: 0.0046730014
A47: ML Global Govt Bond II USD | K47: 0.089338294 | L47: 0.033153621 | O47: 0.12382438 | P47: 0.080573599 | Y47: 0.16006752 | Z47: 0.34334538
A48: ML Global High Yield - AAA Spread USD | G48: 0.32072102 | H48: 0.0027615231 | I48: 0.13350392 | J48: 0.14739736 | K48: 0.13581608 | L48: 0.0023419477 | O48: 0.28001103 | P48: 0.0001625225 | Q48: 0.56584402 | R48: 8.893999e-07 | U48: 0.20193468 | V48: 0.010197087 | AA48: 0.31828217 | AB48: 0.00010796317 | AE48: 0.54041606 | AF48: 0.0024127483 | AG48: 0.26832265 | AH48: 0.0027081769
A49: MSCI Small Minus Large World USD | G49: 0.26830161 | H49: 0.0050142084 | M49: 0.17791371 | N49: 0.052714106 | Q49: 0.14282093 | R49: 0.12965048 | U49: 0.21635712 | V49: 0.00041213713 | W49: -0.091986807 | X49: 0.32671253 | AE49: 0.2671769 | AF49: 0.031493976
A50: MSCI The World USD | S50: 0.22109088 | T50: 0.011356788 | AG50: 0.11221211 | AH50: 0.028485825
A51: MSCI Value Minus Growth World USD | I51: -0.22419274 | J51: 9.6112744e-05 | K51: 0.034203498 | L51: 0.13029465 | U51: -0.10714745 | V51: 0.0054966265
A52: S&P GSCI Index | U52: 0.071953789 | V52: 0.0026490073 | AE52: 0.15013414 | AF52: 0.0046325512
A53: Trade Weighted Exchange Index: Broad | AC53: 0.21198632 | AD53: 0.39241779 | AG53: -0.47124272 | AH53: 0.002043036
A54: US Treasury 10Yr - 2Yr Spread USD | I54: 0.015552013 | J54: 0.0019927362 | AG54: -0.0096315129 | AH54: 0.039675714
A81: MULTIFACTOR REGRESSION
A82: The Stepwise Selection Method runs a stepwise regression (forward and backward). The process automatically selects a subset of factors in your model for each fund that provides the highest explanatory power with respect to the funds in your portfolio with the smallest number of factors permissible.
A85: BETA | D85: P-VALUE | G85: PIMCO Global Credit Opportunity Onshore Fund LLC: PIMCO Global Credit Opportunity Onshore Fund LLC | I85: PIMCO: PIMCO Commodity Alpha Fund | K85: Reflow Full Track: ReFlow LO Excess Plus Market Neutral | M85: Rokos Global Macro Fund LP: Rokos Global Macro Fund LP | O85: Saba: CEF1 MN - 2.75x | Q85: Silver Point Capital Fund II LP: Silver Point Capital Fund II LP | S85: Silver Point Capital: Silver Point Distressed Opportunity Institutional Partners + Silver Point HF | U85: Taula: SWIB-DM Taula | W85: Voleon Composition Domestic Fund LP: Voleon Composition Domestic Fund LP | Y85: Walleye: Walleye Opportunities Fund
A87: R2 | G87: 0.1796989 | I87: 0.47635428 | K87: 0.061927047 | M87: 0.23687392 | O87: 0.40352794 | Q87: 0.052491644 | S87: 0.48728169 | U87: 0.21642289 | W87: 0.1144059 | Y87: 0.36088827
A88: Residual Standard Error | G88: 0.02536554 | I88: 0.027590325 | K88: 0.0080838757 | M88: 0.039414831 | O88: 0.027997185 | Q88: 0.04681275 | S88: 0.04808396 | U88: 0.017569028 | W88: 0.019490989 | Y88: 0.015586873
A89: @Intercept | G89: 0.0064818484 | H89: 0.025913269 | K89: 0.0047225151 | L89: 1.2183148e-06 | M89: 0.013030517 | N89: 0.0043880352 | O89: 0.010265403 | P89: 0.0026174233 | Q89: 0.013620446 | R89: 0.011419785 | U89: 0.013326072 | V89: 4.3821515e-09 | W89: 0.0061255644 | X89: 0.0075576693 | Y89: 0.0082466185 | Z89: 1.5919539e-05
A90: CBOE Volatility Index as Difference USD | G90: 0.12965142 | H90: 0.0104327 | W90: -0.062696563 | X90: 0.08541309
A91: ML Global Govt Bond II USD | G91: -0.2386618 | H91: 0.08477408 | M91: -0.48298583 | N91: 0.029894676 | S91: 1.7122507 | T91: 0.00015435751
A92: ML Global High Yield - AAA Spread USD | I92: 0.72594876 | J92: 0.00026843808 | M92: 0.79004987 | N92: 0.0079835349 | O92: 0.35790831 | P92: 0.029634544 | S92: 1.9589977 | T92: 4.0738386e-06 | U92: 0.26482746 | V92: 0.031179498 | W92: 0.24896161 | X92: 0.029653733 | Y92: 0.40365966 | Z92: 2.0654866e-05
A93: MSCI Small Minus Large World USD | O93: 0.37705113 | P93: 0.011395594 | W93: -0.15065258 | X93: 0.13204922 | Y93: 0.23800186 | Z93: 0.0061109928
A94: MSCI The World USD | I94: 0.36696687 | J94: 8.6325193e-07 | O94: 0.2451137 | P94: 0.0009665714
A95: MSCI Value Minus Growth World USD | U95: 0.12092733 | V95: 0.038299893 | Y95: -0.092476535 | Z95: 0.086807309
A96: S&P GSCI Index | G96: 0.086958903 | H96: 0.046810767 | I96: -0.18403932 | J96: 0.0026953245 | M96: -0.31592744 | N96: 0.0003007646 | Q96: 0.1539889 | R96: 0.039647887 | S96: 0.33515688 | T96: 0.0020899648 | U96: -0.16235779 | V96: 8.4292665e-05
A97: Trade Weighted Exchange Index: Broad | K97: -0.13014609 | L97: 0.025076649 | S97: 1.7474259 | T97: 0.0037417017 | U97: -0.327358 | V97: 0.016005145
A98: US Treasury 10Yr - 2Yr Spread USD | I98: 0.035354136 | J98: 2.84005e-05 | O98: -0.012109669 | P98: 0.13538621
A118: BETA | D118: P-VALUE
A119: ^REMOVE_PAGE
A120: R2
A121: Residual Standard Error

Sheet Sheet1

Sheet ASSET CORRELATIONS
A4: FUND CORRELATIONS
A5: Comparison with robust correlation over the selected time window. Robust correlation method computes the covariance matrix with the assumption that there may be outlier data points in the data that are not representative for future behavior.
A8: >0.3: Difference between Robust and EWMA | C8: EWMA Correlations
C9: Fund 1 | D9: Fund 2 | E9: Fund 3 | F9: Fund 4 | G9: Fund 5 | H9: Fund 6 | I9: Fund 7 | J9: Fund 8 | K9: Fund 9 | L9: Fund 10 | M9: Fund 11 | N9: Fund 12 | O9: Fund 13 | P9: Fund 14 | Q9: Fund 15 | R9: Fund 16 | S9: Fund 17 | T9: Fund 18 | U9: Fund 19 | V9: Fund 20 | W9: Fund 21 | X9: Fund 22 | Y9: Fund 23 | Z9: Fund 24 | AA9: Fund 25 | AB9: Fund 26 | AC9: Fund 27 | AD9: Fund 28 | AE9: Fund 29 | AF9: Fund 30 | AG9: Fund 31 | AH9: Fund 32 | AI9: Fund 33 | AJ9: Fund 34 | AK9: Fund 35 | AL9: Fund 36 | AM9: Fund 37
A10: Robust Correlations | B10: Fund 1 | C10: 1 | D10: 0.22857948 | E10: 0.11532706 | F10: 0.15546881 | G10: -0.20338839 | H10: 0.16425347 | I10: 0.26370464 | J10: 0.04822915 | K10: -0.14109863 | L10: -0.20627623 | M10: 0.021364898 | N10: 0.25985237 | O10: 0.26305259 | P10: -0.24528535 | Q10: 0.34225652 | R10: -0.12660869 | S10: -0.014042346 | T10: -0.045313408 | U10: -0.23416871 | V10: -0.33143245 | W10: 0.10586261 | X10: 0.28174584 | Y10: -0.068919485 | Z10: 0.1042928 | AA10: 0.1277432 | AB10: -0.30300715 | AC10: -0.31713423 | AD10: 0.17348777 | AE10: 0.053385283 | AF10: 0.14760899 | AG10: -0.10502158 | AH10: -0.15544198 | AI10: -0.10846512 | AJ10: 0.10013959 | AK10: -0.22100615 | AL10: 0.3953157 | AM10: 0.23798347
B11: Fund 2 | C11: 0.22563565 | D11: 1 | E11: 0.0026695188 | F11: 0.19594357 | G11: -0.09656346 | H11: 0.15829657 | I11: 0.14696072 | J11: 0.055287372 | K11: 0.09043509 | L11: 0.13214007 | M11: -0.075154795 | N11: 0.2420042 | O11: -0.0057893225 | P11: -0.041098337 | Q11: -0.11548935 | R11: 0.042405463 | S11: 0.12517713 | T11: 0.11177567 | U11: 0.080767546 | V11: -0.1236775 | W11: 0.15633021 | X11: 0.016212776 | Y11: 0.053456543 | Z11: 0.030398291 | AA11: 0.023357588 | AB11: 0.085427046 | AC11: 0.13168855 | AD11: -0.17913639 | AE11: -0.099692987 | AF11: -0.024310174 | AG11: 0.15877296 | AH11: 0.048408374 | AI11: -0.1058284 | AJ11: 0.057907444 | AK11: -0.033620651 | AL11: 0.42222262 | AM11: 0.14332962
B12: Fund 3 | C12: -0.0030395963 | D12: 0.033598223 | E12: 1 | F12: -0.0038156613 | G12: 0.1745068 | H12: 0.34627751 | I12: 0.0409501 | J12: 0.66816246 | K12: -0.08129111 | L12: -0.22401448 | M12: -0.054993861 | N12: 0.083373667 | O12: 0.25737374 | P12: -0.050337277 | Q12: -0.0087489166 | R12: 0.22396394 | S12: 0.31402681 | T12: 0.019421157 | U12: -0.18981644 | V12: -0.27946012 | W12: 0.21453778 | X12: -0.073980522 | Y12: 0.13354242 | Z12: -0.3664518 | AA12: -0.067448443 | AB12: -0.047908254 | AC12: 0.046521612 | AD12: 0.064331071 | AE12: -0.18027664 | AF12: -0.0062443302 | AG12: 0.046537189 | AH12: 0.0024850002 | AI12: 0.64498142 | AJ12: 0.43242813 | AK12: -0.30089864 | AL12: -0.018414567 | AM12: -0.12650014
B13: Fund 4 | C13: 0.095476779 | D13: -0.027582793 | E13: -0.17363593 | F13: 1 | G13: -0.05399874 | H13: 0.03944728 | I13: 0.24699443 | J13: 0.055245982 | K13: -0.30730416 | L13: -0.020461817 | M13: 0.076328825 | N13: 0.13807083 | O13: 0.055420911 | P13: 0.15305833 | Q13: 0.080229207 | R13: 0.057511988 | S13: -0.021204586 | T13: 0.15489096 | U13: 0.17952386 | V13: 0.0092201909 | W13: 0.28247282 | X13: -0.030658189 | Y13: 0.063585973 | Z13: 0.24493485 | AA13: 0.031097833 | AB13: 0.48985599 | AC13: 0.13570613 | AD13: -0.20142479 | AE13: 0.27658959 | AF13: -0.10280552 | AG13: -0.10502839 | AH13: 0.054759059 | AI13: -0.064762463 | AJ13: 0.31167623 | AK13: -0.026637189 | AL13: 0.14568655 | AM13: 0.15967516
B14: Fund 5 | C14: -0.077138718 | D14: 0.2261791 | E14: -0.042218149 | F14: 0.057121867 | G14: 1 | H14: -0.090466446 | I14: -0.015387697 | J14: 0.13357595 | K14: -0.1823755 | L14: -0.19747076 | M14: -0.025225834 | N14: -0.091490985 | O14: -0.12366271 | P14: 0.30583777 | Q14: -0.042741004 | R14: -0.10531539 | S14: -0.083218551 | T14: 0.083341158 | U14: -0.048736617 | V14: 0.46924999 | W14: 0.11220713 | X14: -0.13835578 | Y14: 0.015783251 | Z14: -0.42788996 | AA14: -0.16209538 | AB14: 0.23129978 | AC14: 0.068220753 | AD14: 0.073310109 | AE14: -0.007187048 | AF14: -0.18689143 | AG14: -0.080615757 | AH14: 0.071732876 | AI14: 0.71869118 | AJ14: -0.035648521 | AK14: 0.061835635 | AL14: -0.68101723 | AM14: -0.20045668
B15: Fund 6 | C15: 0.22095403 | D15: 0.4095419 | E15: 0.17073075 | F15: 0.13627511 | G15: 0.24189823 | H15: 1 | I15: 0.16414285 | J15: 0.39443589 | K15: 0.15753875 | L15: -0.023796932 | M15: -0.15278601 | N15: -0.0075701722 | O15: 0.28145311 | P15: -0.19138911 | Q15: 0.096440619 | R15: 0.18154125 | S15: 0.38580376 | T15: 0.016633436 | U15: -0.10431469 | V15: -0.1060639 | W15: 0.069801298 | X15: -0.20475552 | Y15: 0.33553578 | Z15: -0.26705148 | AA15: -0.18918325 | AB15: 0.01875775 | AC15: -0.20948297 | AD15: 0.19960972 | AE15: -0.17359626 | AF15: 0.37277197 | AG15: -0.035465886 | AH15: -0.033491793 | AI15: 0.051927056 | AJ15: 0.3359926 | AK15: -0.17883002 | AL15: 0.19875648 | AM15: -0.095387287
B16: Fund 7 | C16: 0.23305894 | D16: 0.10892481 | E16: 0.054139744 | F16: 0.26751219 | G16: 0.0011390281 | H16: 0.085074635 | I16: 1 | J16: -0.010202416 | K16: 0.10292337 | L16: 0.24361955 | M16: 0.099012624 | N16: 0.4705215 | O16: 0.10529405 | P16: 0.12718336 | Q16: 0.2219617 | R16: 0.041430405 | S16: -0.10682587 | T16: -0.25238882 | U16: 0.38598462 | V16: 0.16542036 | W16: -0.036076758 | X16: 0.094896143 | Y16: 0.068213429 | Z16: -0.02590207 | AA16: -0.073381312 | AB16: -0.013784298 | AC16: -0.089218905 | AD16: -0.16196106 | AE16: 0.41698687 | AF16: 0.10491095 | AG16: -0.056326787 | AH16: -0.135192 | AI16: 0.080620933 | AJ16: -0.099606985 | AK16: 0.33272609 | AL16: 0.18769044 | AM16: 0.36539736
B17: Fund 8 | C17: -0.16960776 | D17: 0.040412119 | E17: 0.59682005 | F17: 0.018315282 | G17: 0.36370348 | H17: 0.27269911 | I17: 0.063607748 | J17: 1 | K17: -0.17549903 | L17: -0.26526509 | M17: -0.14149201 | N17: 0.16516169 | O17: 0.35774712 | P17: -0.18675213 | Q17: 0.14390903 | R17: 0.1505434 | S17: 0.33075083 | T17: 0.10865897 | U17: -0.25567602 | V17: -0.24237659 | W17: 0.13925309 | X17: -0.078711399 | Y17: 0.37358156 | Z17: -0.36050541 | AA17: 0.042023898 | AB17: 0.0071486887 | AC17: -0.047811105 | AD17: 0.1439281 | AE17: -0.18900328 | AF17: 0.080028446 | AG17: 0.075681296 | AH17: 0.1687662 | AI17: 0.42840459 | AJ17: 0.68600746 | AK17: -0.31469422 | AL17: -0.022104329 | AM17: -0.091138572
B18: Fund 9 | C18: -0.074635571 | D18: 0.13186134 | E18: 0.049584568 | F18: -0.16282789 | G18: -0.031631862 | H18: 0.1899236 | I18: 0.006632031 | J18: 0.0066964968 | K18: 1 | L18: 0.26254059 | M18: -0.17966277 | N18: -0.0064009635 | O18: -0.26055943 | P18: -0.10610184 | Q18: -0.10138083 | R18: 0.0032367933 | S18: 0.14443422 | T18: -0.16219297 | U18: 0.18087503 | V18: 0.068558277 | W18: -0.19501268 | X18: -0.1370589 | Y18: 0.041801572 | Z18: 0.075447095 | AA18: -0.2060865 | AB18: -0.018246032 | AC18: -0.0052621163 | AD18: -0.13326049 | AE18: -0.039347418 | AF18: 0.089465917 | AG18: 0.11105462 | AH18: -0.23488581 | AI18: -0.1444882 | AJ18: -0.14791437 | AK18: 0.28896005 | AL18: 0.14972255 | AM18: 0.0028126078
B19: Fund 10 | C19: 0.12614097 | D19: 0.15176091 | E19: -0.13236855 | F19: -0.006309204 | G19: 0.035934957 | H19: 0.20732711 | I19: 0.15124264 | J19: -0.10845257 | K19: 0.30228297 | L19: 1 | M19: 0.13606263 | N19: -0.024720669 | O19: -0.14157677 | P19: 0.34329282 | Q19: 0.2471502 | R19: 0.17713667 | S19: -0.17099201 | T19: -0.17326986 | U19: 0.60467564 | V19: 0.25766221 | W19: -0.17307135 | X19: -0.040761502 | Y19: -0.036481984 | Z19: 0.19895812 | AA19: 0.031165321 | AB19: 0.12875121 | AC19: 0.30304454 | AD19: -0.0065938043 | AE19: 0.28110939 | AF19: 0.066549341 | AG19: 0.15201446 | AH19: 0.046031839 | AI19: -0.12046596 | AJ19: -0.24415497 | AK19: 0.63096277 | AL19: 0.12175065 | AM19: 0.26498215
B20: Fund 11 | C20: -0.082047346 | D20: 0.055060009 | E20: 0.030762879 | F20: 0.15490983 | G20: 0.17687363 | H20: 0.027126789 | I20: -0.033519877 | J20: 0.10662464 | K20: -0.19386228 | L20: -0.098360324 | M20: 1 | N20: 0.064534886 | O20: -0.12304208 | P20: 0.41815763 | Q20: 0.25750057 | R20: 0.0066509318 | S20: -0.085540185 | T20: -0.16763942 | U20: 0.40700963 | V20: 0.27514269 | W20: 0.12937795 | X20: 0.45948515 | Y20: -0.050168148 | Z20: 0.018212862 | AA20: 0.049473047 | AB20: 0.23834137 | AC20: 0.022154721 | AD20: -0.015518323 | AE20: 0.36781263 | AF20: 0.19577275 | AG20: 0.14042815 | AH20: -0.012897728 | AI20: 0.088289703 | AJ20: -0.12066154 | AK20: 0.25417795 | AL20: 0.080089404 | AM20: 0.53375675
B21: Fund 12 | C21: 0.15045875 | D21: 0.15094312 | E21: 0.13733549 | F21: 0.19977408 | G21: 0.00032240085 | H21: 0.11103069 | I21: 0.47791508 | J21: 0.10932364 | K21: -0.021229927 | L21: -0.050133926 | M21: 0.12666566 | N21: 1 | O21: 0.13340866 | P21: -0.11741611 | Q21: 0.11889108 | R21: -0.25640299 | S21: -0.1073124 | T21: -0.16396183 | U21: 0.068840297 | V21: -0.099392974 | W21: 0.16440047 | X21: 0.30411342 | Y21: -0.021735027 | Z21: -0.10072506 | AA21: 0.14111736 | AB21: -0.099656861 | AC21: 0.0014427295 | AD21: -0.058807885 | AE21: 0.063073131 | AF21: -0.072171272 | AG21: 0.26256817 | AH21: 0.01995302 | AI21: 0.047098008 | AJ21: 0.037886777 | AK21: -0.20291369 | AL21: 0.16745026 | AM21: 0.37998927
B22: Fund 13 | C22: 0.23253858 | D22: 0.028870366 | E22: 0.59157151 | F22: -0.06178745 | G22: -0.17797466 | H22: 0.077816321 | I22: 0.15638376 | J22: 0.12581585 | K22: -0.0078791484 | L22: 0.00044355759 | M22: 0.01212054 | N22: 0.1052566 | O22: 1 | P22: -0.18061986 | Q22: 0.082666122 | R22: 0.18206215 | S22: 0.058585403 | T22: 0.089736992 | U22: -0.11429455 | V22: -0.19365565 | W22: 0.12278397 | X22: -0.004500556 | Y22: 0.27107088 | Z22: -0.20509504 | AA22: 0.082665417 | AB22: -0.16599115 | AC22: -0.21627393 | AD22: 0.13732145 | AE22: -0.045401931 | AF22: 0.020013068 | AG22: -0.11873298 | AH22: 0.16145315 | AI22: -0.015591406 | AJ22: 0.3784168 | AK22: -0.17283742 | AL22: 0.17775102 | AM22: 0.048653533
... B46: Fund 37 | C46: 0.045006031 | D46: 0.14265411 | E46: 0.060496919 | F46: 0.16410817 | G46: 0.16419227 | H46: -0.030377338 | I46: 0.31977873 | J46: 0.094758708 | K46: -0.050093666 | L46: 0.03066814 | M46: 0.43311069 | N46: 0.33064211 | O46: 0.055426501 | P46: 0.65367368 | Q46: 0.24157246 | R46: 0.23999073 | S46: 0.19046238 | T46: 0.19032237 | U46: 0.43328084 | V46: 0.12581528 | W46: 0.46254553 | X46: 0.34064958 | Y46: 0.14183928 | Z46: 0.021905899 | AA46: 0.12988886 | AB46: 0.38554943 | AC46: 0.13952807 | AD46: 0.30497787 | AE46: 0.032343018 | AF46: 0.072203505 | AG46: 0.082412688 | AH46: 0.17606305 | AI46: 0.33340177 | AJ46: 0.087405327 | AK46: -0.054292198 | AL46: 0.14385827 | AM46: 1
A50: 1 | B50: 12267: Trexquant Onshore Fund LP | H50: 11 | I50: D. E. Shaw: Cogence | O50: 21 | P50: HF: Current Specialty Finance (Excluding Pathfinder) | V50: 31 | W50: Rokos Global Macro Fund LP: Rokos Global Macro Fund LP
A51: 2 | B51: Aquatic: Aquatic - Nautilus CFM (Net) | H51: 12 | I51: DE Shaw Composite Fund LLC: DE Shaw Composite Fund LLC | O51: 22 | P51: Holocene: Holocene Advisors Master | V51: 32 | W51: Saba: CEF1 MN - 2.75x
A52: 3 | B52: Ares: Ares Pathfinder II | H52: 13 | I52: DYAL: DYAL II - Aksia | O52: 23 | P52: Hudson Structured: HSCM w MFC | V52: 33 | W52: Silver Point Capital Fund II LP: Silver Point Capital Fund II LP
A53: 4 | B53: Bayview Asset Management: MSR Fund | H53: 14 | I53: Dockside: I-94 Minus Standalones | O53: 24 | P53: King Street Capital LP: King Street Capital LP | V53: 34 | W53: Silver Point Capital: Silver Point Distressed Opportunity Institutional Partners + Silver Point HF
A54: 5 | B54: Benefit Street Partners: Benefit Street Partners Origination Fund (CCFLX) | H54: 15 | I54: Dorsal Capital Partners LP: Dorsal Capital Partners LP | O54: 25 | P54: LibreMax CLO: LibreMax CLO | V54: 35 | W54: Taula: SWIB-DM Taula
A55: 6 | B55: BlackRock: GAO | H55: 16 | I55: Elliott Associates LP: Elliott Associates LP | O55: 26 | P55: LibreMax Partners LP: LibreMax Partners LP | V55: 36 | W55: Voleon Composition Domestic Fund LP: Voleon Composition Domestic Fund LP
A56: 7 | B56: Blackstone: Badgerstone Access | H56: 17 | I56: Four World: FWGO | O56: 27 | P56: Mesarete: Prior TR+back with Pharo Macro+Mesarete Capital Fund | V56: 37 | W56: Walleye: Walleye Opportunities Fund
A57: 8 | B57: Blue Owl: Blue Owl Funding Partners (CCLFX) | H57: 18 | I57: Four World: FWGO Minority Descent | O57: 28 | P57: PIMCO Global Credit Opportunity Onshore Fund LLC: PIMCO Global Credit Opportunity Onshore Fund LLC
A58: 9 | B58: Brevan Howard Coinvests (Aksia): Brevan Howard Special Opportunities SPC | H58: 19 | I58: Graham Absolute Return Ltd: Graham Absolute Return Ltd | O58: 29 | P58: PIMCO: PIMCO Commodity Alpha Fund
A59: 10 | B59: Brevan Howard MB Macro Fund: Brevan Howard MB Macro Fund with proforma | H59: 20 | I59: HF: Current Coinvests (Excluding BH Coinvests) | O59: 30 | P59: Reflow Full Track: ReFlow LO Excess Plus Market Neutral

Sheet FACTOR CORRELATIONS
A4: FACTOR CORRELATIONS
A5: Comparison with robust correlation over the selected time window. Robust correlation method computes the covariance matrix with the assumption that there may be outlier data points in the data that are not representative for future behavior.
A8: >0.3: Difference between Robust and EWMA | C8: EWMA Correlations
C9: Factor 1 | D9: Factor 2 | E9: Factor 3 | F9: Factor 4 | G9: Factor 5 | H9: Factor 6 | I9: Factor 7 | J9: Factor 8 | K9: Factor 9
A10: Robust Correlations | B10: Factor 1 | C10: 1 | D10: -0.32635909 | E10: -0.16456113 | F10: -0.049343079 | G10: -0.80068077 | H10: 0.34837552 | I10: 0.1165326 | J10: 0.44270777 | K10: 0.018704596
B11: Factor 2 | C11: -0.25606694 | D11: 1 | E11: -0.52142709 | F11: 0.38827376 | G11: 0.58249023 | H11: 0.073110853 | I11: -0.39228964 | J11: -0.75587701 | K11: 0.058102726
B12: Factor 3 | C12: -0.05649538 | D12: -0.54821535 | E12: 1 | F12: -0.11817118 | G12: 0.048730515 | H12: -0.15013436 | I12: 0.31421362 | J12: 0.069194887 | K12: -0.24562792
B13: Factor 4 | C13: -0.14292377 | D13: 0.20285483 | E13: 0.240141 | F13: 1 | G13: 0.18541139 | H13: 0.59330588 | I13: 0.003357709 | J13: -0.33492141 | K13: 0.023541646
B14: Factor 5 | C14: -0.76742598 | D14: 0.50489874 | E14: 0.018293753 | F14: 0.22537755 | G14: 1 | H14: -0.37260975 | I14: -0.18750978 | J14: -0.65163787 | K14: -0.079322819
B15: Factor 6 | C15: 0.072954754 | D15: -0.19217873 | E15: 0.22728523 | F15: 0.3585071 | G15: -0.26342114 | H15: 1 | I15: 0.16371393 | J15: -0.009711577 | K15: 0.004255772
B16: Factor 7 | C16: -0.21678818 | D16: -0.19337365 | E16: 0.45277391 | F16: 0.20366003 | G16: 0.2619107 | H16: 0.26962018 | I16: 1 | J16: 0.22811763 | K16: -0.20823051
B17: Factor 8 | C17: 0.3729578 | D17: -0.56133341 | E17: -0.077045304 | F17: -0.34079489 | G17: -0.56827596 | H17: -0.080018216 | I17: -0.33666143 | J17: 1 | K17: 0.14315222
B18: Factor 9 | C18: 0.16016982 | D18: 0.0069789399 | E18: 0.23960533 | F18: 0.15960465 | G18: -0.18472509 | H18: 0.20119615 | I18: -0.0076922566 | J18: -0.094677144 | K18: 1
A37: 1 | B37: CBOE Volatility Index as Difference USD
A38: 2 | B38: ML Global Govt Bond II USD
A39: 3 | B39: ML Global High Yield - AAA Spread USD
A40: 4 | B40: MSCI Small Minus Large World USD
A41: 5 | B41: MSCI The World USD
A42: 6 | B42: MSCI Value Minus Growth World USD
A43: 7 | B43: S&P GSCI Index
A44: 8 | B44: Trade Weighted Exchange Index: Broad
A45: 9 | B45: US Treasury 10Yr - 2Yr Spread USD

Sheet TIME SERIES
A4: BACKFILL INFORMATION
A5: Backfilling has to be used when you have missing data, short return histories or when your instruments’ time series do not have the same starting point.
A7: Name | J7: Backfill/Infill Instruments | T7: Beta | W7: Intercept | Z7: R2 | AB7: Adj R2 | AD7: Observations | AF7: Backfill/Infill Method
T8: Coeff | U8: p-value | V8: t-stat | W8: Coeff | X8: p-value | Y8: t-stat
A9: ^REMOVE_PAGE
A10: Only results for backfilled/infilled funds are displayed.
A11: If the p-value and t-statistic columns in the Beta section appear empty, it is due to non-positive degrees of freedom. Please, adjust your backfill/infill settings.
A13: HISTORICAL RETURNS
A14: This table shows you the historical and backfilled data of the funds in your portfolio.
B16: 12267: Trexquant Onshore Fund LP | C16: Aquatic: Aquatic - Nautilus CFM (Net) | D16: Ares: Ares Pathfinder II | E16: Bayview Asset Management: MSR Fund | F16: Benefit Street Partners: Benefit Street Partners Origination Fund (CCFLX) | G16: BlackRock: GAO | H16: Blackstone: Badgerstone Access | I16: Blue Owl: Blue Owl Funding Partners (CCLFX) | J16: Brevan Howard Coinvests (Aksia): Brevan Howard Special Opportunities SPC | K16: Brevan Howard MB Macro Fund: Brevan Howard MB Macro Fund with proforma | L16: D. E. Shaw: Cogence | M16: DE Shaw Composite Fund LLC: DE Shaw Composite Fund LLC | N16: DYAL: DYAL II - Aksia | O16: Dockside: I-94 Minus Standalones | P16: Dorsal Capital Partners LP: Dorsal Capital Partners LP | Q16: Elliott Associates LP: Elliott Associates LP | R16: Four World: FWGO | S16: Four World: FWGO Minority Descent | T16: Graham Absolute Return Ltd: Graham Absolute Return Ltd | U16: HF: Current Coinvests (Excluding BH Coinvests) | V16: HF: Current Specialty Finance (Excluding Pathfinder) | W16: Holocene: Holocene Advisors Master | X16: Hudson Structured: HSCM w MFC | Y16: King Street Capital LP: King Street Capital LP | Z16: LibreMax CLO: LibreMax CLO | AA16: LibreMax Partners LP: LibreMax Partners LP | AB16: Mesarete: Prior TR+back with Pharo Macro+Mesarete Capital Fund | AC16: PIMCO Global Credit Opportunity Onshore Fund LLC: PIMCO Global Credit Opportunity Onshore Fund LLC | AD16: PIMCO: PIMCO Commodity Alpha Fund | AE16: Reflow Full Track: ReFlow LO Excess Plus Market Neutral | AF16: Rokos Global Macro Fund LP: Rokos Global Macro Fund LP | AG16: Saba: CEF1 MN - 2.75x | AH16: Silver Point Capital Fund II LP: Silver Point Capital Fund II LP | AI16: Silver Point Capital: Silver Point Distressed Opportunity Institutional Partners + Silver Point HF | AJ16: Taula: SWIB-DM Taula | AK16: Voleon Composition Domestic Fund LP: Voleon Composition Domestic Fund LP | AL16: Walleye: Walleye Opportunities Fund
A17: Date
A18: 04/30/2026 | B18: 1.36 | C18: 1.8995 | D18: 0 | E18: 0.9272 | F18: -1.918 | G18: -1.05 | H18: 1.0448 | I18: 0 | J18: -0.2712 | K18: 2.0622 | L18: 3.8588 | M18: 3.0098 | N18: 0 | O18: 2.48 | P18: 0.86 | Q18: 0.8 | R18: -1.15 | S18: -0.08 | T18: 3.4133 | U18: 0.3373 | V18: 0.7402 | W18: 4.3785 | X18: 0.0234 | Y18: -0.4094 | Z18: 1.3875 | AA18: 0.0375 | AB18: 2.2648 | AC18: -3.9106 | AD18: 7.6433 | AE18: 0.1584 | AF18: 4.6858 | AG18: 0.6 | AH18: 0 | AI18: 0 | AJ18: 0.7099 | AK18: 2.917 | AL18: 3.9923
A19: 03/31/2026 | B19: 5.45 | C19: 0.8399 | D19: 4.53 | E19: 0.8161 | F19: -0.1637 | G19: 3.83 | H19: 0.07 | I19: 3.1521 | J19: -2.8449 | K19: -3.4273 | L19: -1.6966 | M19: 2.2137 | N19: 3.7482 | O19: -2.63 | P19: -0.4688 | Q19: 0.2 | R19: 2.661 | S19: 2.4437 | T19: -6.1786 | U19: -8.0587 | V19: 1.3226 | W19: -0.1087 | X19: -0.1605 | Y19: -0.1834 | Z19: 1.0935 | AA19: -0.7494 | AB19: 0.1637 | AC19: 7.5685 | AD19: -13.8495 | AE19: 0.224 | AF19: 1.932 | AG19: 0 | AH19: 0.6 | AI19: 6.8782 | AJ19: -8.7259 | AK19: 1.7343 | AL19: -1.2227
A20: 02/28/2026 | B20: -0.64 | C20: -0.412 | D20: 0 | E20: 1.03 | F20: 0.902 | G20: 1.5 | H20: 1.5883 | I20: 0 | J20: 1.4822 | K20: 1.0808 | L20: -0.0627 | M20: 1.8688 | N20: 0 | O20: 2.57 | P20: 0.9977 | Q20: -0.3 | R20: -3.5988 | S20: -1.187 | T20: -0.0863 | U20: 0.2858 | V20: 0.7873 | W20: -3.1765 | X20: -0.1069 | Y20: -0.1626 | Z20: -1.5068 | AA20: 0.7486 | AB20: -0.0498 | AC20: 1.2554 | AD20: 3.5427 | AE20: 0.0531 | AF20: -1.8322 | AG20: -2.59 | AH20: 0 | AI20: 0 | AJ20: 0.4811 | AK20: -1.9521 | AL20: -0.7696
A21: 01/31/2026 | B21: -5.7 | C21: 0.4498 | D21: 0 | E21: 0.4948 | F21: 1.2499 | G21: 0.09 | H21: -0.193 | I21: 0 | J21: 0.8869 | K21: 2.6307 | L21: 0.8168 | M21: 0.7406 | N21: 0 | O21: 3.84 | P21: -4.8664 | Q21: 1.3 | R21: 0.904 | S21: 0.4632 | T21: 1.7377 | U21: 0.3132 | V21: 0.829 | W21: -1.7094 | X21: 0.0054 | Y21: -0.1674 | Z21: 0.0424 | AA21: 1.7562 | AB21: 4.1427 | AC21: 3.6647 | AD21: -13.7208 | AE21: 0.0405 | AF21: 4.2121 | AG21: 3.56 | AH21: 0 | AI21: 0 | AJ21: 0.455 | AK21: -0.7986 | AL21: -0.5959
A22: 12/31/2025 | B22: 1.23 | C22: 0.8037 | D22: 2.365 | E22: 0.8265 | F22: 0.8952 | G22: 5.66 | H22: 1.3515 | I22: 3.115 | J22: -2.0387 | K22: 0.3266 | L22: 0.4471 | M22: 2.1287 | N22: 9.0743 | O22: 0.84 | P22: 1.23 | Q22: 1.4192 | R22: 1.6129 | S22: 1.9538 | T22: 1.6968 | U22: 0.8631 | V22: 0.8444 | W22: 1.1269 | X22: 7.1093 | Y22: -2.6068 | Z22: 0.9594 | AA22: 0.7984 | AB22: 0.1412 | AC22: -1.3708 | AD22: 2.5488 | AE22: 0.9272 | AF22: 1.4932 | AG22: 6.76 | AH22: 3.1247 | AI22: 4.4071 | AJ22: 1.2223 | AK22: 2.1539 | AL22: 2.0509
A23: 11/30/2025 | B23: 4.24 | C23: -1.118 | D23: 0 | E23: 0.542 | F23: 0.9142 | G23: 0.41 | H23: 0.8417 | I23: 0 | J23: 2.4857 | K23: -1.6852 | L23: 0.983 | M23: 1.6018 | N23: 0 | O23: -0.09 | P23: -2.1 | Q23: 0.5 | R23: -0.8697 | S23: -2.352 | T23: 0.6837 | U23: 0.3008 | V23: 1.3671 | W23: 3.3873 | X23: 0.5458 | Y23: -1.1003 | Z23: -0.4516 | AA23: 0.4239 | AB23: 0.31 | AC23: -1.62 | AD23: -3.9593 | AE23: 0.96 | AF23: -1.3801 | AG23: 1.7 | AH23: 0 | AI23: 0 | AJ23: 1.17 | AK23: -0.36 | AL23: 1.57
A24: 10/31/2025 | B24: 2.3 | C24: 6.4796 | D24: 0 | E24: 1.1419 | F24: 2.1254 | G24: -2.9 | H24: 1.0843 | I24: 0 | J24: -0.2599 | K24: 0.3358 | L24: 0.6865 | M24: 2.0641 | N24: 0 | O24: 1.25 | P24: -2.8554 | Q24: 0.5 | R24: 2.5658 | S24: 2.2413 | T24: 0.6426 | U24: 0.3188 | V24: 1.3616 | W24: 2.8874 | X24: -0.1207 | Y24: 0.5039 | Z24: 1.7126 | AA24: 0.8353 | AB24: 1.02 | AC24: -5.6858 | AD24: -1.1074 | AE24: -0.4031 | AF24: 3.4092 | AG24: 3.88 | AH24: 0 | AI24: 0 | AJ24: 1.8362 | AK24: 2.8777 | AL24: 0.6801
A25: 09/30/2025 | B25: -1.44 | C25: -1.9312 | D25: 4.0715 | E25: 0.6557 | F25: 10.14 | G25: -0.1 | H25: 0.8474 | I25: 2 | J25: -2.762 | K25: -1.4119 | L25: 1.83 | M25: 1.8279 | N25: -0.419 | O25: 4.07 | P25: 0.5805 | Q25: 0.2911 | R25: -0.766 | S25: 1.0309 | T25: 0.1296 | U25: 7.5373 | V25: 0.9643 | W25: 0.5202 | X25: 0.32 | Y25: -3.0643 | Z25: -0.6875 | AA25: 0.995 | AB25: 1.466 | AC25: 1.5372 | AD25: 1.7105 | AE25: -0.083 | AF25: 1.3446 | AG25: 0.58 | AH25: 29.5072 | AI25: 0.7868 | AJ25: 0.1386 | AK25: -6.8957 | AL25: 0.4689
A26: 08/31/2025 | B26: 1.86 | C26: 0.3813 | D26: 0 | E26: 0.9606 | F26: 0.44 | G26: 1.79 | H26: 1.0691 | I26: 0 | J26: 3.4639 | K26: -0.3081 | L26: 0.67 | M26: 0.6712 | N26: 0 | O26: 1.43 | P26: -0.205 | Q26: 0.9 | R26: 3.6 | S26: 2.4527 | T26: 0.8823 | U26: 0.3612 | V26: -0.4977 | W26: -2.9994 | X26: 2.4 | Y26: -0.1344 | Z26: 0.4137 | AA26: 0.6196 | AB26: 0.8378 | AC26: -3.2763 | AD26: 2.2216 | AE26: 0.617 | AF26: 1.0138 | AG26: -0.62 | AH26: 0 | AI26: 0 | AJ26: 0.6951 | AK26: 3.9654 | AL26: 1.1094
A27: 07/31/2025 | B27: -3.37 | C27: -7.3885 | D27: 0 | E27: 0.6362 | F27: 0.85 | G27: -2.65 | H27: -0.0388 | I27: 0 | J27: -1.2063 | K27: -1.1801 | L27: 1.58 | M27: 1.5827 | N27: 0 | O27: -1.07 | P27: 0.5017 | Q27: 0.2 | R27: 1.2928 | S27: 2.7625 | T27: -0.492 | U27: 0.3584 | V27: 0.6252 | W27: 2.49 | X27: 0.1137 | Y27: -0.14 | Z27: 1.6498 | AA27: 0.6746 | AB27: 1.1444 | AC27: -1.1658 | AD27: 0.7088 | AE27: 0.5201 | AF27: 1.2942 | AG27: 6.88 | AH27: 0 | AI27: 0 | AJ27: -0.1719 | AK27: 0.6811 | AL27: 0.4805
A28: 06/30/2025 | B28: -0.76 | C28: -1.9088 | D28: 1.5336 | E28: 0.8828 | F28: 0.74 | G28: 1.45 | H28: 0.1267 | I28: 2.83 | J28: 0.5198 | K28: 1.213 | L28: 1.7 | M28: -0.0233 | N28: 1.3236 | O28: 4.46 | P28: 2.4271 | Q28: 0.8048 | R28: 1.6215 | S28: 1.3637 | T28: 1.2134 | U28: -1.2453 | V28: 0.6961 | W28: 1.3148 | X28: 9.4671 | Y28: -0.4357 | Z28: 1.4059 | AA28: 0.9773 | AB28: 1.1064 | AC28: 4.21 | AD28: -1.38 | AE28: 0.6556 | AF28: 2.305 | AG28: 2.49 | AH28: -2.3458 | AI28: 9.1677 | AJ28: 1.3886 | AK28: -0.6399 | AL28: 1.8266
A29: 05/31/2025 | B29: 3.15 | C29: 1.4074 | D29: 0 | E29: 0.8053 | F29: 1.13 | G29: 3.24 | H29: 0.7576 | I29: 0 | J29: 0.3805 | K29: 2.5668 | L29: 0.5 | M29: 1.4743 | N29: 0 | O29: 0.81 | P29: 3.1306 | Q29: 0.4 | R29: 0.8945 | S29: 1.01 | T29: 0.2775 | U29: 0.3436 | V29: 0.9212 | W29: -0.101 | X29: 0.6629 | Y29: -0.594 | Z29: -2.1662 | AA29: 0.6795 | AB29: -0.4669 | AC29: 2.7902 | AD29: 0.8986 | AE29: 0.8073 | AF29: 1.18 | AG29: 2.9 | AH29: 0 | AI29: 0 | AJ29: 0.4637 | AK29: 1.2564 | AL29: 1.154
... A98: 08/31/2019 | B98: 0 | C98: -5.62 | D98: 0.75 | E98: 0.94 | F98: 0.21 | G98: -1.26 | H98: 0.7878 | I98: 0.21 | J98: -0.64 | K98: 0.81 | L98: 2.6 | M98: 0.9155 | N98: 0 | O98: 1 | P98: 2.5 | Q98: 0.2 | R98: 0.82 | S98: 1.24 | T98: 2.39 | U98: 0.0817 | V98: -0.1836 | W98: 2.36 | X98: 1.5878 | Y98: -1.17 | Z98: 0.98 | AA98: -0.02 | AB98: -4.4835 | AC98: -3.56 | AD98: -0.9 | AE98: -0.6084 | AF98: -0.64 | AG98: -4.2337 | AH98: -2.48 | AI98: -2.48 | AJ98: 0.29 | AK98: -0.18 | AL98: 1

Sheet GLOSSARY
A4: RISK MEASURES
A5: StDev | E5: Standard Deviation | L5: The volatility of the portfolio returns around the mean. It represents a symmetric risk measure, i.e. recognizing both upside and downside deviations from the mean and capturing the central risk only.
A7: VaR | E7: Value at Risk | L7: The highest possible loss over a certain period of time with a given level of confidence
A9: ETL | E9: Expected Tail Loss | L9: The average (expected) loss beyond Value-at-Risk (VaR). It can be interpreted as the expected shortfall given that the VaR threshold has been exceeded. It is a risk measure focusing on downside only
A11: RETURN MEASURES
A12: Mean | E12: Mean Return (%) | L12: The average of the simulated returns of the asset/strategy
A14: ETR | E14: Expected Tail Return | L14: The upside potential of a portfolio or asset. It is conceptually similar to ETL but applies to gains rather than losses, i.e. ETR measure the average gain should the positive VaR be exceeded
A16: RISK ADJUSTED MEASURES
A17: Sharpe | E17: Sharpe Ratio | L17: Return per unit of risk, where risk is defined as standard deviation
A19: STARR | E19: STARR Ratio | L19: Return per unit of risk, where risk is defined as expected tail loss
A21: Rachev | E21: Rachev Ratio | L21: Tail return per unit of tail risk, where tail return is defined as expected tail return (ETR) and tail loss is defined as expected tail loss (ETL)
A23: PERCENTAGE AND MARGINAL CONTRIBUTION
A24: PC to Return | E24: Percent Contribution to Return | L24: The fraction of total portfolio expected mean return contributed by each risk driver.
A26: PC to StDev (%) | E26: Percent Contribution to Standard Deviation | L26: The fraction of total portfolio volatility contributed by each asset/strategy
A28: MC to StDev (bps) | E28: Marginal Contribution to Standard Deviation | L28: Portfolio volatility sensitivity to a small change in the weight of each asset
A30: PC to ETL (%) | E30: Percent Contribution to Expected Tail Loss | L30: The fraction of total portfolio expected tail loss contributed by each asset/strategy
A32: MC to ETL (bps) | E32: Marginal Contribution to Expected Tail Loss | L32: Portfolio expected tail loss sensitivity to a small change in the weight of each asset
A34: PC to ETR (%) | E34: Percent Contribution to Expected Tail Return | L34: The fraction of total portfolio expected tail return contributed by each asset/strategy
A36: MC to ETR (bps) | E36: Marginal Contribution to Expected Tail Return | L36: Portfolio expected tail return sensitivity to a small change in the weight of each asset
A38: Factor PC to StDev (%) | E38: Factor Percent Contribution to Standard Deviation | L38: The fraction of total portfolio volatility contributed by each market index
A40: Factor MC to StDev (bps) | E40: Factor Marginal Contribution to Standard Deviation | L40: Portfolio volatility sensitivity to a small change in the exposure to each market index
A42: Factor PC to ETL (%) | E42: Factor Percent Contribution to Expected Tail Loss | L42: The fraction of total portfolio expected tail loss contributed by each market index
A44: Factor MC to ETL (bps) | E44: Factor Marginal Contribution to Expected Tail Loss | L44: Portfolio expected tail loss sensitivity to a small change in the exposure to each market index
A46: OTHER STATISTICS
A47: Skewness | L47: The degree of asymmetry of a distribution around its mean. Positive skewness indicates a distribution with an asymmetric tail extending toward more positive values. Negative skewness indicates a distribution with an asymmetric tail extending toward more negative values.
A49: Excess Kurtosis | L49: The degree to which a distribution is more or less peaked than a normal distribution. Positive kurtosis indicates a relatively peaked distribution. Negative kurtosis indicates a relatively flat distribution
A51: Upside Volatility | L51: The volatility of the positive returns of the asset
A53: Downside Volatility | L53: The volatility of the negative returns of the asset
A55: Implied Return (ETL) | L55: The return an asset must deliver in order to justify the amount of tail risk it contributes to the overall portfolio
A57: Implied Return (StDev) | L57: The return an asset must deliver in order to justify the amount of volatility it contributes to the overall portfolio
A59: Portfolio Exposure | L59: The weighted sum of asset betas to each market index
A61: Max Drawdown | L61: Encompasses both the period from the asset's peak to the asset's valley (length), and the time from the asset's valley to a new asset high (recovery).

Sheet STYLES
A1: hd
A2: backfill
A3: artificial
A4: date
A6: &sub& portfolio
A7: &sub& number 0.01 | B7: &sub& number 0.01 | C7: &sub& number 0.001
A9: highlight if Robust - Classical > 0.3
A11: conditional factor

Sheet BottomManagersPerScenario_Data
A1: 2008 Lehman Blow-Up | B1: 2008 Lehman Blow-Up | C1: 2002 Market Downturn | D1: 2002 Market Downturn | E1: 2001 WTC Attack | F1: 2001 WTC Attack | G1: 1987 Black Monday | H1: 1987 Black Monday | I1: 1998 Russian Crisis | J1: 1998 Russian Crisis | K1: 2008 January Crisis | L1: 2008 January Crisis | M1: 2007 August Crisis | N1: 2007 August Crisis | O1: 2001 Nasdaq | P1: 2001 Nasdaq | Q1: 1997 - 1998 Asian Crisis | R1: 1997 - 1998 Asian Crisis | S1: 1990 Kuwait Invasion | T1: 1990 Kuwait Invasion | U1: 2005 Katrina | V1: 2005 Katrina | W1: scenarios
A2: Silver Point Capital: Silver Point Distressed Opportunity Institutional Partners + Silver Point HF | B2: -42.289325 | C2: PIMCO: PIMCO Commodity Alpha Fund | D2: -26.684504 | E2: Silver Point Capital: Silver Point Distressed Opportunity Institutional Partners + Silver Point HF | F2: -11.380305 | G2: Silver Point Capital: Silver Point Distressed Opportunity Institutional Partners + Silver Point HF | H2: -28.416508 | I2: PIMCO: PIMCO Commodity Alpha Fund | J2: -7.5970198 | K2: PIMCO: PIMCO Commodity Alpha Fund | L2: -7.5670559 | M2: Saba: CEF1 MN - 2.75x | N2: -3.8341475 | O2: Silver Point Capital: Silver Point Distressed Opportunity Institutional Partners + Silver Point HF | P2: -8.6402481 | Q2: PIMCO: PIMCO Commodity Alpha Fund | R2: -2.779568 | S2: Rokos Global Macro Fund LP: Rokos Global Macro Fund LP | T2: -7.6864085 | U2: Silver Point Capital: Silver Point Distressed Opportunity Institutional Partners + Silver Point HF | V2: -2.802416
A3: LibreMax Partners LP: LibreMax Partners LP | B3: -23.790872 | C3: Silver Point Capital: Silver Point Distressed Opportunity Institutional Partners + Silver Point HF | D3: -23.43874 | E3: PIMCO: PIMCO Commodity Alpha Fund | F3: -7.9984564 | G3: Aquatic: Aquatic - Nautilus CFM (Net) | H3: -8.6444407 | I3: Silver Point Capital: Silver Point Distressed Opportunity Institutional Partners + Silver Point HF | J3: -7.345846 | K3: Saba: CEF1 MN - 2.75x | L3: -5.3643522 | M3: PIMCO: PIMCO Commodity Alpha Fund | N3: -3.5451571 | O3: PIMCO: PIMCO Commodity Alpha Fund | P3: -4.5800419 | Q3: Aquatic: Aquatic - Nautilus CFM (Net) | R3: -1.5928982 | S3: PIMCO: PIMCO Commodity Alpha Fund | T3: -6.1479654 | U3: PIMCO: PIMCO Commodity Alpha Fund | V3: -1.2212106
A4: PIMCO: PIMCO Commodity Alpha Fund | B4: -22.480782 | C4: Rokos Global Macro Fund LP: Rokos Global Macro Fund LP | D4: -17.907609 | E4: Saba: CEF1 MN - 2.75x | F4: -7.3312916 | G4: PIMCO: PIMCO Commodity Alpha Fund | H4: -8.5078155 | I4: Saba: CEF1 MN - 2.75x | J4: -7.1881349 | K4: Silver Point Capital: Silver Point Distressed Opportunity Institutional Partners + Silver Point HF | L4: -4.527934 | M4: LibreMax Partners LP: LibreMax Partners LP | N4: -2.5716398 | O4: Mesarete: Prior TR+back with Pharo Macro+Mesarete Capital Fund | P4: -3.0934759 | Q4: Rokos Global Macro Fund LP: Rokos Global Macro Fund LP | R4: -1.3056845 | S4: Aquatic: Aquatic - Nautilus CFM (Net) | T4: -2.9249691 | U4: Aquatic: Aquatic - Nautilus CFM (Net) | V4: -1.199001
A5: Saba: CEF1 MN - 2.75x | B5: -22.023037 | C5: Saba: CEF1 MN - 2.75x | D5: -12.305299 | E5: LibreMax Partners LP: LibreMax Partners LP | F5: -5.0703637 | G5: King Street Capital LP: King Street Capital LP | H5: -7.6120141 | I5: LibreMax Partners LP: LibreMax Partners LP | J5: -7.0528825 | K5: Rokos Global Macro Fund LP: Rokos Global Macro Fund LP | L5: -3.6627768 | M5: Mesarete: Prior TR+back with Pharo Macro+Mesarete Capital Fund | N5: -2.3252195 | O5: HF: Current Coinvests (Excluding BH Coinvests) | P5: -2.3753222 | Q5: King Street Capital LP: King Street Capital LP | R5: -1.2404076 | S5: Saba: CEF1 MN - 2.75x | T5: -2.5962676 | U5: HF: Current Coinvests (Excluding BH Coinvests) | V5: -0.912812
A6: Graham Absolute Return Ltd: Graham Absolute Return Ltd | B6: -16.97762 | C6: Graham Absolute Return Ltd: Graham Absolute Return Ltd | D6: -11.838912 | E6: Graham Absolute Return Ltd: Graham Absolute Return Ltd | F6: -4.7514883 | G6: Saba: CEF1 MN - 2.75x | H6: -7.5699809 | I6: Graham Absolute Return Ltd: Graham Absolute Return Ltd | J6: -5.4571408 | K6: HF: Current Coinvests (Excluding BH Coinvests) | L6: -3.2731405 | M6: Aquatic: Aquatic - Nautilus CFM (Net) | N6: -2.235365 | O6: Saba: CEF1 MN - 2.75x | P6: -2.1782199 | Q6: Mesarete: Prior TR+back with Pharo Macro+Mesarete Capital Fund | R6: -1.1603701 | S6: Brevan Howard MB Macro Fund: Brevan Howard MB Macro Fund with proforma | T6: -2.1274732 | U6: Mesarete: Prior TR+back with Pharo Macro+Mesarete Capital Fund | V6: -0.86863254
